Workbook
Name Print_Area_MI: 'Equip Review 032310'!$B$2:$Z$12

Sheet LOC13
A1: ABS EQUIPMENT LEASING INC.
A2: FIXED ASSET LEDGER - LOCATION SUMMARY
B3: REVISED AS OF 10/24/13
E5: M | F5: included in Misc. Summary
J6: A | P6: B | Q6: C | R6: A + B + C | W6: RECONCILIATION TO F11 SCH | Z6: F 11 | AA6: Linked to sheets
A7: Asset | I7: Fiscal | J7: Total | L7: Book | M7: FMV | P7: ON | Q7: FORECAST | R7: TOTAL | U7: Orig | V7: FINAL | Z7: VARIANCE | AA7: Additions | AB7: Additions | AC7: Additions
A8: # | B8: Description | C8: Model | D8: Serial # | E8: M | F8: Location | G8: LOCATION 2 | H8: Bay | I8: Purch Yr. | J8: F13 Costs | K8: Depreciation | L8: Value | M8: ESTIMATE | N8: Active/Inactive | P8: DEPOSIT | Q8: SPEND | R8: COSTS | S8: Vendor | U8: PO # | V8: F11 | X8: F11 | Y8: F11 | Z8: TO F13 | AA8: F12 | AB8: F13 | AC8: F14
A9: 100 | B9: =+'100'!A7 -> FORESTLINE #1 | C9: =+'100'!A8 -> VECOMIL 563 5 AXIS CNC VERTICAL | D9: =+'100'!C7 -> 3051 | F9: =+'100'!B11 -> MISS | G9: 1495 | H9: 1495 | I9: 2004 | J9: =+'100'!R7 -> 1971035.5 | K9: =+'100'!S7 -> 1971035.5 | L9: =+J9-K9 -> 0 | M9: 1500000 | N9: A | O9: =+J9-K9-L9 -> -4.6566129e-10 | P9: =82000+347000 -> 429000 | Q9: =307000+82000 -> 389000 | R9: =+J9+P9+Q9 -> 2789035.5 | V9: 1122082.2 | W9: 100 | Z9: =+J9-V9 -> 848953.25 | AA9: =+'100'!V14 -> 440690.72
A10: 108 | B10: =+'108'!A7 -> SAN ROCCO - FUTURA 14 | C10: =+'108'!A9 -> HORIZONTAL BORING MILL | D10: =+'108'!C7 -> F07/6 | F10: =+'108'!B11 -> MISS | G10: 1495 | H10: 1495 | I10: 1994 | J10: =+'108'!R7 -> 1288891.3 | K10: =+'108'!S7 -> 1288891.3 | L10: =+J10-K10 -> 0 | M10: 875000 | N10: A | O10: =+J10-K10-L10 -> -2.3283064e-10 | R10: =+J10+P10+Q10 -> 1288891.3 | V10: 1288891.3 | W10: 108 | Z10: =+J10-V10 -> 0
A11: 117 | B11: TOSHIBA BTD-13F.R22 | D11: 144926 | F11: MISS | G11: 1495 | H11: 1495 | I11: ='117'!$Q$13 -> 2007 | J11: =+'117'!R7 -> 749420.97 | K11: =+'117'!S7 -> 749420.97 | L11: =+J11-K11 -> 0 | M11: 600000 | N11: A | O11: =+J11-K11-L11 -> 0 | R11: =+J11+P11+Q11 -> 749420.97 | V11: 749420.97 | W11: 117 | Z11: =+J11-V11 -> 0
A12: 118 | B12: TOSHIBA TMD - 16 | C12: CNC VBM | D12: 420165 | F12: MISS | G12: 1495 | H12: 1495 | I12: ='118'!$Q$13 -> 2007 | J12: =+'118'!R7 -> 691113.35 | K12: =+'118'!S7 -> 691113.35 | L12: =+J12-K12 -> 0 | M12: 500000 | N12: A | O12: =+J12-K12-L12 -> -1.1641532e-10 | R12: =+J12+P12+Q12 -> 691113.35 | V12: 691113.35 | W12: 118 | Z12: =+J12-V12 -> 0
A13: 119 | B13: TOSHIBA TUE-15 | C13: ='119'!$A$7 -> VBM | D13: 440376 | F13: MISS | G13: 1495 | H13: 1495 | I13: 2009 | J13: =+'119'!R7 -> 442044 | K13: =+'119'!S7 -> 442044 | L13: =+J13-K13 -> 0 | M13: 350000 | N13: A | O13: =+J13-K13-L13 -> 5.8207661e-11 | R13: =+J13+P13+Q13 -> 442044 | V13: 442044 | W13: 119 | Z13: =+J13-V13 -> 0
A14: 159 | B14: TOSHIBA BP-150.R22 #2 | C14: BP-150.R22 | D14: 130380 | F14: MISS | G14: 1495 | H14: 1495 | I14: 2009 | J14: =+'159'!R7 -> 935280.49 | K14: =+'159'!S7 -> 935280.49 | L14: =+J14-K14 -> 0 | M14: 750000 | N14: A | O14: =+J14-K14-L14 -> -1.1641532e-10 | R14: =+J14+P14+Q14 -> 935280.49 | V14: 935280.49 | W14: 144 | Z14: =+J14-V14 -> 0
A15: 164 | B15: TOSHIBA TMD-23 #1 | C15: VBM | D15: 420182 | F15: MISS | G15: 1495 | H15: 1495 | I15: 2009 | J15: =+'164'!R7 -> 897755.57 | K15: =+'164'!S7 -> 897755.57 | L15: =+J15-K15 -> 0 | M15: 800000 | N15: A | O15: =+J15-K15-L15 -> 1.1641532e-10 | R15: =+J15+P15+Q15 -> 897755.57 | V15: 892865.71 | W15: 159 | Z15: =+J15-V15 -> 4889.86
A16: 175 | B16: CRANE; STAHLKRANE; 7.5[t]; BRIDGE TYPE | D16: M0190435 | E16: M | F16: MISS | G16: 1495 | H16: 1495 | L16: =+J16-K16 -> 0 | N16: A | O16: =+J16-K16-L16 -> 0 | R16: =+J16+P16+Q16 -> 0 | V16: 0 | W16: 160 | Z16: =+J16-V16 -> 0
A17: 211 | B17: E-R MAIER VERTICAL BANDSAW | E17: M | F17: MISS | G17: 1495 | H17: 1495 | L17: =+J17-K17 -> 0 | M17: 500 | N17: A | O17: =+J17-K17-L17 -> 0 | R17: =+J17+P17+Q17 -> 0 | W17: 200 | Z17: =+J17-V17 -> 0
A18: 299 | B18: STYLINER SUPER STRINGER | C18: HAND MARKING HEAD | F18: MISS | G18: 1495 | H18: 1495 | I18: 2010 | J18: 9685 | L18: =+J18-K18 -> 9685 | M18: 6000 | N18: A | O18: =+J18-K18-L18 -> 0 | R18: =+J18+P18+Q18 -> 9685 | V18: 9685 | W18: 278 | Z18: =+J18-V18 -> 0
A19: 316 | B19: NOMURA | C19: HBM-HBA-110T-R3 | D19: 5380 | F19: MISS | G19: 1495 | H19: 1495 | I19: 2012 | J19: =495000+16300 -> 511300 | M19: =+J19 -> 511300 | R19: =+J19+P19+Q19 -> 511300 | W19: 296 | Z19: =+J19-V19 -> 511300 | AB19: 619412.89
G20: 1495 Total | M20: =SUBTOTAL(9,M9:M19) -> 5892800 | AB20: =SUBTOTAL(9,AB9:AB19) -> 619412.89
A21: 273 | B21: VIRGINIA CRANE DOUBLE GIRDER | C21: BRIDGE CRANE (50/10 TON) | D21: VC89-323 | F21: 3100 | G21: 3100 | I21: 2010 | J21: ='273'!C14 -> 120322.9 | L21: =+J21-K21 -> 120322.9 | M21: 100000 | N21: A | O21: =+J21-K21-L21 -> 0 | R21: =+J21+P21+Q21 -> 120322.9 | V21: 93679.4 | W21: 254 | Z21: =+J21-V21 -> 26643.5
A22: 295 | B22: SHAW BOX 40 TON CRANE | C22: GIRDER OVER BRIDGE 72 FT. | D22: 59-37500 | F22: 3100 | G22: 3100 | I22: 2011 | J22: =17257.87+17257.87+186009.78 -> 220525.52 | L22: =+J22-K22 -> 220525.52 | M22: 55000 | N22: A | O22: =+J22-K22-L22 -> 0 | R22: =+J22+P22+Q22 -> 220525.52 | V22: 34515.74 | W22: 274 | Z22: =+J22-V22 -> 186009.78
A23: 296 | B23: CRANE HOIST 30 TON & 15 AUXILARY | C23: IST LEASIING CORP | F23: 3100 | G23: 3100 | I23: 2010 | J23: 17500 | L23: =+J23-K23 -> 17500 | M23: 45000 | N23: A | O23: =+J23-K23-L23 -> 0 | R23: =+J23+P23+Q23 -> 17500 | V23: 17500 | W23: 275 | Z23: =+J23-V23 -> 0
A24: 301 | B24: WELDING ELECTRICAL | F24: 3100 | G24: 3100 | I24: 2011 | J24: 96028 | L24: =+J24-K24 -> 96028 | M24: 50000 | N24: A | O24: =+J24-K24-L24 -> 0 | R24: =+J24+P24+Q24 -> 96028 | V24: 96028 | W24: 280 | Z24: =+J24-V24 -> 0
A25: 302 | B25: COMPRESSOR | F25: 3100 | G25: 3100 | I25: 2011 | J25: 11773 | L25: =+J25-K25 -> 11773 | M25: 8000 | N25: A | O25: =+J25-K25-L25 -> 0 | R25: =+J25+P25+Q25 -> 11773 | V25: 11773 | W25: 281 | Z25: =+J25-V25 -> 0
A26: 303 | B26: WELDING STN FLOOR PLATES | F26: 3100 | G26: 3100 | I26: 2011 | J26: 200351 | L26: =+J26-K26 -> 200351 | M26: 200000 | N26: A | O26: =+J26-K26-L26 -> 0 | R26: =+J26+P26+Q26 -> 200351 | V26: 200351 | W26: 282 | Z26: =+J26-V26 -> 0
A27: 304 | B27: WELDING EQUIPMENT | F27: 3100 | G27: 3100 | I27: 2011 | J27: 153084 | L27: =+J27-K27 -> 153084 | M27: 100000 | N27: A | O27: =+J27-K27-L27 -> 0 | R27: =+J27+P27+Q27 -> 153084 | V27: 153084 | W27: 283 | Z27: =+J27-V27 -> 0
A28: 305 | B28: CRANES 3100 | F28: 3100 | G28: 3100 | I28: 2011 | J28: =120321+186009+51651+90550 -> 448531 | L28: =+J28-K28 -> 448531 | M28: 250000 | N28: A | O28: =+J28-K28-L28 -> 0 | R28: =+J28+P28+Q28 -> 448531 | V28: 448531 | W28: 284 | Z28: =+J28-V28 -> 0
A29: 719.2 | B29: LOCKERS WELD SHOP | F29: 3100 | G29: 3100 | I29: 2011 | J29: 2340 | L29: =+J29-K29 -> 2340 | M29: =+J29 -> 2340 | N29: A | O29: =+J29-K29-L29 -> 0 | R29: =+J29+P29+Q29 -> 2340 | V29: 2340 | W29: 709 | Z29: =+J29-V29 -> 0
A30: 827 | B30: DRIVE ROLL | C30: WELD SHOP' | F30: 3100 | G30: 3100 | I30: 2012 | J30: 32986 | M30: =+J30 -> 32986 | R30: =+J30+P30+Q30 -> 32986 | S30: PO-107807 | T30: RED-D-ARC | Z30: =+J30-V30 -> 32986
A31: 115 | B31: WELDING POSITIONER NEW | C31: 30-6 AB POSIT | D31: 15312X08-20 | F31: MISS | G31: 3100 | H31: 3100 | I31: 2009 | J31: ='115'!$R$7 -> 38496.5 | K31: ='115'!$S$7 -> 38496.5 | L31: =+J31-K31 -> 0 | M31: 8000 | N31: A | O31: =+J31-K31-L31 -> 7.2759576e-12 | R31: =+J31+P31+Q31 -> 38496.5 | V31: 19120.07 | W31: 115 | Z31: =+J31-V31 -> 19376.43
A32: 835 | B32: ARONSON WELDING POSITIONER (Gi200) | C32: G1200 | D32: 48131 | F32: MISS | G32: 3100 | H32: 3100 | J32: 261100 | M32: 261100
A33: 836 | B33: ARONSON WELDING POSITIONER (HD500) | C33: HD 500 | D33: 48315 | F33: MISS | G33: 3100 | H33: 3100 | J33: 165000 | M33: 165000
G34: 3100 Total | M34: =SUBTOTAL(9,M21:M33) -> 1277426 | AB34: =SUBTOTAL(9,AB21:AB33) -> 0
A35: MISC | B35: SEE MISC. SHEET | C35: M = SEE MISC. SHEET | E35: M | F35: 94-10 | G35: 94-10 | J35: =MISC!$S$7 -> 5916533.8 | K35: =MISC!$T$7 -> 4699006.8 | L35: =+J35-K35 -> 1217527 | M35: 300000 | O35: =+J35-K35-L35 -> 0 | R35: =+J35+P35+Q35 -> 5916533.8 | V35: 4886192.5 | Z35: =+J35-V35 -> 1030341.3
G36: 94-10 Total | M36: =SUBTOTAL(9,M35:M35) -> 300000 | AB36: =SUBTOTAL(9,AB35:AB35) -> 0
A37: 277 | B37: DELKEN TABLE CAPACITY 10 TON (WOTAN RAPID 2) | C37: DCN 150 ST | F37: BRAM | G37: BRAM | I37: 2005 | J37: ='277'!$R$7 -> 185377.28 | K37: ='277'!$S$7 -> 185377.28 | L37: =+J37-K37 -> 0 | M37: 150000 | O37: =+J37-K37-L37 -> 2.910383e-11 | R37: =+J37+P37+Q37 -> 185377.28 | V37: 185377.28 | W37: 259 | Z37: =+J37-V37 -> 0
A38: 309 | B38: RAVENSBURG LATHE | C38: KH 100 | D38: 9326 | F38: BRAM | G38: BRAM | I38: 2011 | J38: 90000 | L38: =+J38-K38 -> 90000 | M38: =+J38 -> 90000 | N38: A | O38: =+J38-K38-L38 -> 0 | R38: =+J38+P38+Q38 -> 90000 | V38: 90000 | W38: 289 | Z38: =+J38-V38 -> 0
A39: 310 | B39: RAVENSBURG LATHE | C39: KH 100 | D39: 9327 | F39: BRAM | G39: BRAM | I39: 2011 | J39: 90000 | L39: =+J39-K39 -> 90000 | M39: =+J39 -> 90000 | N39: A | O39: =+J39-K39-L39 -> 0 | R39: =+J39+P39+Q39 -> 90000 | V39: 90000 | W39: 290 | Z39: =+J39-V39 -> 0
A40: 502 | B40: =+'502'!A7 -> MANDELLI | C40: =+'502'!A8 -> M 8 | D40: =+'502'!C7 -> 7874 | F40: BRAM | G40: BRAM | I40: 2004 | J40: =+'502'!R7 -> 695116 | K40: =+'502'!S7 -> 695116 | L40: =+J40-K40 -> 0 | M40: 300000 | N40: A | O40: =+J40-K40-L40 -> 1.1641532e-10 | R40: =+J40+P40+Q40 -> 695116 | V40: 695116 | W40: 304 | Z40: =+J40-V40 -> 0
A41: 512 | B41: R 16 TOSHIBA 144725 | D41: 144725 | F41: BRAM | G41: BRAM | I41: 2005 | J41: =+'512'!R7 -> 855698.36 | K41: =+'512'!S7 -> 855698.36 | L41: =+J41-K41 -> 0 | M41: 450000 | N41: A | O41: =+J41-K41-L41 -> -2.3283064e-10 | R41: =+J41+P41+Q41 -> 855698.36 | V41: 860698.36 | W41: 500 | Z41: =+J41-V41 -> -5000
A42: 513 | B42: R 16 TOSHIBA 144728 | D42: 144728 | F42: BRAM | G42: BRAM | I42: 2005 | J42: =+'513'!R7 -> 855069.67 | K42: =+'513'!S7 -> 855069.67 | L42: =+J42-K42 -> 0 | M42: 450000 | N42: A | O42: =+J42-K42-L42 -> -1.1641532e-10 | R42: =+J42+P42+Q42 -> 855069.67 | V42: 860069.67 | W42: 501 | Z42: =+J42-V42 -> -5000
A43: 514 | B43: PROECO TYPHOON PARTS WASHER | F43: BRAM | G43: BRAM | I43: 2010 | J43: 15074 | L43: =+J43-K43 -> 15074 | M43: =+J43 -> 15074 | N43: A | O43: =+J43-K43-L43 -> 0 | R43: =+J43+P43+Q43 -> 15074 | V43: 22574 | W43: 502 | Z43: =+J43-V43 -> -7500
A44: 515.1 | B44: AMANDA SAW (ORR METAL) | C44: Italian Made | F44: BRAM | G44: BRAM | L44: =+J44-K44 -> 0 | M44: 10000 | N44: A | O44: =+J44-K44-L44 -> 0 | R44: =+J44+P44+Q44 -> 0 | W44: 503 | Z44: =+J44-V44 -> 0
A45: 516 | B45: CMM INSPECTION | E45: M | F45: BRAM | G45: BRAM | L45: =+J45-K45 -> 0 | M45: 35000 | N45: A | O45: =+J45-K45-L45 -> 0 | R45: =+J45+P45+Q45 -> 0 | W45: 504 | X45: 985659 | Y45: SOLD | Z45: =+J45-V45 -> 0
A46: 700 | B46: =+'700'!A7 -> G&L (2 machines) | C46: =+'700'!A8 -> MC50 W FANUC 18iMB | D46: =+'700'!C7 -> 285_286 | F46: =+'700'!B11 -> DUNDALK | G46: BRAM | I46: 2008 | J46: =+'700'!R7 -> 957552.3 | K46: =+'700'!S7 -> 957552.3 | L46: =+J46-K46 -> 0 | M46: 700000 | N46: A | O46: need to split up depr spreadsheet | R46: =+J46+P46+Q46 -> 957552.3 | V46: 957552.3 | W46: 513 | Z46: =+J46-V46 -> 0
A47: 700 A | B47: G&L | C47: MC50 W FANUC 18iMB | D47: 285 | F47: BRAM | G47: BRAM | R47: =+J47+P47+Q47 -> 0 | W47: 514 | Z47: =+J47-V47 -> 0
A48: 700 B | B48: G&L | C48: MC50 W FANUC 18iMB | D48: 286 | F48: BRAM | G48: BRAM | R48: =+J48+P48+Q48 -> 0 | W48: 515 | Z48: =+J48-V48 -> 0
A49: 701 | B49: SAN ROCCO (MESSIER-DOWTY) | C49: FUTURA 901 (320) | D49: 153685 F07/07 | F49: BRAM | G49: BRAM | I49: 2008 | J49: ='701'!R7 -> 231804.79 | K49: ='701'!S7 -> 231804.79 | L49: =+J49-K49 -> 0 | M49: 350000 | N49: A | O49: =+J49-K49-L49 -> 0 | R49: =+J49+P49+Q49 -> 231804.79 | V49: 231804.79 | W49: 514 | Z49: =+J49-V49 -> 0
A50: 702 | B50: TOSHIBA TSS 30/55 | C50: VBM | D50: 310455 | F50: BRAM | G50: BRAM | I50: 2007 | J50: =+'702'!R7 -> 965193.69 | K50: =+'702'!S7 -> 965193.69 | L50: =+J50-K50 -> 0 | M50: 780000 | N50: A | O50: =+J50-K50-L50 -> -1.1641532e-10 | R50: =+J50+P50+Q50 -> 965193.69 | V50: 965193.69 | W50: 515 | X50: 671438.89 | Y50: SOLD | Z50: =+J50-V50 -> 0
A51: 703 | B51: TOSHIBA BP150 R22 #1 | C51: BP150 R22 | D51: 130369 | F51: BRAM | G51: BRAM | I51: 2008 | J51: =+'703'!R7 -> 942015.25 | K51: =+'703'!S7 -> 942015.25 | L51: =+J51-K51 -> 0 | M51: 750000 | N51: A | O51: =+J51-K51-L51 -> -1.1641532e-10 | R51: =+J51+P51+Q51 -> 942015.25 | V51: 935233.52 | W51: 516 | Z51: =+J51-V51 -> 6781.73
A52: 704 | B52: TOSHIBA TMD - 23 #2 | C52: VBM | D52: 420184 | F52: BRAM | G52: BRAM | I52: 2010 | J52: =+'704'!R7 -> 893344.4 | K52: =+'704'!S7 -> 884930.69 | L52: =+J52-K52 -> 8413.7143 | M52: 750000 | N52: A | O52: =+J52-K52-L52 -> 0 | R52: =+J52+P52+Q52 -> 893344.4 | V52: 876889.79 | W52: 517 | Z52: =+J52-V52 -> 16454.61
A53: 708 | B53: TOSHIBA BSF 150 #2 | C53: [new] | D53: 520472 | F53: BRAM | G53: BRAM | I53: 2007 | J53: =+'708'!R7 -> 2449653.4 | K53: =+'708'!S7 -> 2359817.5 | L53: =+J53-K53 -> 89835.843 | M53: 2400000 | N53: A | O53: =+J53-K53-L53 -> 0 | R53: =+J53+P53+Q53 -> 2449653.4 | V53: 2342699.6 | W53: 520 | X53: 464725.27 | Y53: SOLD | Z53: =+J53-V53 -> 106953.8
A54: 710 | B54: 20 TON DELKEN TABLE | C54: BSF 150 | F54: BRAM | G54: BRAM | I54: 2007 | J54: ='710'!R7 -> 205281.15 | K54: ='710'!S7 -> 205281.15 | L54: =+J54-K54 -> 0 | M54: INCL | N54: A | O54: =+J54-K54-L54 -> 2.910383e-11 | R54: =+J54+P54+Q54 -> 205281.15 | V54: 205281.15 | Z54: =+J54-V54 -> 0
A55: 711 | B55: 2 - NEW COMPRESSORS COMPREVAC | F55: BRAM | G55: BRAM | I55: 2008 | J55: ='711'!R7 -> 80160.79 | K55: ='711'!S7 -> 80160.79 | L55: =+J55-K55 -> 0 | M55: 40000 | N55: A | O55: =+J55-K55-L55 -> 0 | R55: =+J55+P55+Q55 -> 80160.79 | V55: 80160.79 | W55: 700 | Z55: =+J55-V55 -> 0
A56: 712 | B56: MISC | E56: M | F56: BRAM | G56: BRAM | L56: =+J56-K56 -> 0 | M56: 100000 | N56: A | O56: =+J56-K56-L56 -> 0 | R56: =+J56+P56+Q56 -> 0 | V56: 0 | W56: 701 | Z56: =+J56-V56 -> 0
A57: 713 | B57: TOSHIBA MPC 3680B #2 | D57: 910516 | F57: BRAM | G57: BRAM | I57: 2009 | J57: =+'713'!R7 -> 2278744.4 | K57: =+'713'!S7 -> 2278744.4 | L57: =+J57-K57 -> 0 | M57: 2000000 | N57: A | O57: =+J57-K57-L57 -> 0 | R57: =+J57+P57+Q57 -> 2278744.4 | V57: 2278744.4 | W57: 702 | Z57: =+J57-V57 -> 0
A58: 714 | B58: MISC FOUNDATIONS, FORKLIFTS, CRANES | E58: M | F58: BRAM | G58: BRAM | L58: =+J58-K58 -> 0 | M58: 100000 | N58: A | O58: =+J58-K58-L58 -> 0 | R58: =+J58+P58+Q58 -> 0 | W58: 703 | Z58: =+J58-V58 -> 0
A59: 715 | B59: CABINETS - BRAMPTON | E59: M | F59: BRAM | G59: BRAM | L59: =+J59-K59 -> 0 | M59: 50000 | N59: A | O59: =+J59-K59-L59 -> 0 | R59: =+J59+P59+Q59 -> 0 | W59: 704 | Z59: =+J59-V59 -> 0
A60: 716 | B60: CRANES - BRAMPTON | F60: BRAM | G60: BRAM | I60: 2008 | J60: ='716'!R7 -> 236734.97 | K60: ='716'!S7 -> 236734.97 | L60: =+J60-K60 -> 0 | M60: 50000 | N60: A | O60: =+J60-K60-L60 -> 0 | R60: =+J60+P60+Q60 -> 236734.97 | V60: 236734.97 | W60: 705 | X60: 440774.69 | Y60: SOLD | Z60: =+J60-V60 -> 0
A61: 717 | B61: TOSHIBA TSS NEW 30/55 | C61: [new] | D61: 310349 | F61: BRAM | G61: BRAM | I61: 2010 | J61: =+'717'!R7 -> 982583.15 | K61: =+'717'!S7 -> 982583.15 | L61: =+J61-K61 -> 0 | M61: 800000 | N61: A | O61: =+J61-K61-L61 -> 0 | R61: =+J61+P61+Q61 -> 982583.15 | V61: 982583.15 | W61: 706 | Z61: =+J61-V61 -> 0
A62: 719.7 | B62: SNORKEL | C62: ATB38 | D62: 992754 | F62: BRAM | G62: BRAM | I62: 2011 | J62: 8500 | L62: =+J62-K62 -> 8500 | M62: =+J62 -> 8500 | N62: A | O62: =+J62-K62-L62 -> 0 | R62: =+J62+P62+Q62 -> 8500 | V62: 8500 | W62: 713 | Z62: =+J62-V62 -> 0
A63: 722 | B63: HYSTER LIFT TRUCK | D63: K005D05153X | F63: BRAM | G63: BRAM | I63: 2010 | J63: 15000 | L63: =+J63-K63 -> 15000 | M63: 10000 | N63: A | O63: =+J63-K63-L63 -> 0 | R63: =+J63+P63+Q63 -> 15000 | V63: 15000 | W63: 719.1 | Z63: =+J63-V63 -> 0
A64: 724 | B64: TOSHIBA R22 #4 | C64: BP-150 HBM | D64: 130401 | F64: BRAM | G64: BRAM | I64: 2011 | J64: ='724'!R7 -> 912932.41 | L64: =+J64-K64 -> 912932.41 | M64: 852863 | N64: A | O64: =+J64-K64-L64 -> 0 | R64: =+J64+P64+Q64 -> 912932.41 | V64: 852563 | W64: 719.3 | Z64: =+J64-V64 -> 60369.41
A65: 725 | B65: CMEGAMAT LIFT MODEL | C65: FSE 3.6 1224/816-7010 | D65: PO-100342 | F65: BRAM | G65: BRAM | I65: 2011 | J65: 67000 | L65: =+J65-K65 -> 67000 | M65: =+J65 -> 67000 | N65: A | O65: =+J65-K65-L65 -> 0 | R65: =+J65+P65+Q65 -> 67000 | V65: 67000 | W65: 719.4 | Z65: =+J65-V65 -> 0
A66: 726 | B66: TOSHIBA R22 #5 | C66: BP 150 LN HBM | D66: 130410 | F66: BRAM | G66: BRAM | I66: 2012 | J66: ='726'!$C$14 -> 852662.5 | L66: =+J66-K66 -> 852662.5 | M66: =+J66 -> 852662.5 | N66: A | O66: =+J66-K66-L66 -> 0 | R66: =+J66+P66+Q66 -> 852662.5 | W66: 719.5 | Z66: =+J66-V66 -> 852662.5
A67: 727 | B67: DEA DELTA 4507 GANTRY CMM | F67: BRAM | G67: BRAM | I67: 2013 | J67: =196450+2210 -> 198660 | L67: =+J67-K67 -> 198660 | M67: 196450 | O67: =+J67-K67-L67 -> 0 | R67: =+J67+P67+Q67 -> 198660 | W67: 719.6 | Z67: =+J67-V67 -> 198660 | AB67: 20201.95
A68: 728 | B68: PAMA AT 150/4 | D68: 33C070449 | F68: BRAM | G68: BRAM | I68: 2013 | J68: 501131.53 | M68: =+(365000+26010+25648)*1.33 -> 554155.14 | N68: INSTALL TBD | Q68: 25000 | R68: =+J68+P68+Q68 -> 526131.53 | W68: 719.7 | Z68: =+J68-V68 -> 501131.53 | AB68: 536139.48
A69: 802 | B69: 46" BULLARD # 1 | C69: DYN-AU-TAPE | D69: 3072 | F69: BRAM | G69: BRAM | I69: 2012 | J69: =262349/2 -> 131174.5 | M69: =+J69 -> 131174.5 | N69: INSTALL TBD | Q69: 2500 | R69: =+J69+P69+Q69 -> 133674.5 | S69: PO-105953 | T69: ADEL AUTOMATION INC. | W69: 720.2 | Z69: =+J69-V69 -> 131174.5 | AA69: =118406.09/2 -> 59203.045 | AB69: 167067.83
A70: 803 | B70: 46" BULLARD # 2 | C70: DYN-AU-TAPE | D70: 3075 | F70: BRAM | G70: BRAM | I70: 2012 | J70: =262349/2 -> 131174.5 | M70: =+J70 -> 131174.5 | N70: INSTALL TBD | Q70: 2500 | R70: =+J70+P70+Q70 -> 133674.5 | S70: PO-105953 | T70: ADEL AUTOMATION INC. | W70: 720.3 | Z70: =+J70-V70 -> 131174.5 | AA70: =118406.09/2 -> 59203.045 | AB70: 167068
A71: 806 | B71: VERTICAL MACHINING CENTRE | C71: MCV-300 | D71: 301269 | F71: BRAM | G71: BRAM | I71: 2013 | J71: 44081.25 | M71: =+J71 -> 44081.25 | R71: =+J71+P71+Q71 -> 44081.25 | S71: PO-109586 | T71: HEINMAN | Z71: =+J71-V71 -> 44081.25 | AB71: 44081.25
A72: 807 | B72: SLANT BED CNC LATHE | C72: FCL-820 | D72: A0070701 | F72: BRAM | G72: BRAM | I72: 2013 | J72: 58000 | M72: =+J72 -> 58000 | R72: =+J72+P72+Q72 -> 58000 | S72: PO-109586 | T72: HEINMAN | Z72: =+J72-V72 -> 58000 | AB72: 58000
A73: 808 | B73: PRECISION HANDFEED SURFACE GRINDER | C73: FSG-618M | D73: A3096001 | F73: BRAM | G73: BRAM | I73: 2013 | J73: 10445.25 | M73: =+J73 -> 10445.25 | R73: =+J73+P73+Q73 -> 10445.25 | S73: PO-109586 | T73: HEINMAN | Z73: =+J73-V73 -> 10445.25 | AB73: 10445.25
A74: 809 | B74: BAND SAW | C74: 115-B | D74: 6159 | F74: BRAM | G74: BRAM | I74: 2013 | J74: 3562.5 | M74: =+J74 -> 3562.5 | R74: =+J74+P74+Q74 -> 3562.5 | S74: PO-109586 | T74: HEINMAN | Z74: =+J74-V74 -> 3562.5 | AB74: 10687.5
A75: 812 | B75: VERTICAL MILLING MACHINE | C75: LC-1 1/2VS | D75: 731291 | F75: BRAM | G75: BRAM | I75: 2013 | J75: 9594.05 | M75: =+J75 -> 9594.05 | R75: =+J75+P75+Q75 -> 9594.05 | S75: PO-109586 | T75: HEINMAN | W75: 722 | Z75: =+J75-V75 -> 9594.05 | AB75: 9594.05
A76: 813 | B76: VERTICAL MILLING MACHINE | C76: LC-1 1/2VS | D76: 731290 | F76: BRAM | G76: BRAM | I76: 2013 | J76: 9594.05 | M76: =+J76 -> 9594.05 | R76: =+J76+P76+Q76 -> 9594.05 | S76: PO-109586 | T76: HEINMAN | Z76: =+J76-V76 -> 9594.05 | AB76: 9594.05
A77: 814 | B77: MICROWEILY HIGH SPEED PRECISION LATHE | C77: TY-1640S | D77: S10006-023 | F77: BRAM | G77: BRAM | I77: 2013 | J77: 16671.55 | M77: =+J77 -> 16671.55 | R77: =+J77+P77+Q77 -> 16671.55 | S77: PO-109586 | T77: HEINMAN | W77: 724 | Z77: =+J77-V77 -> 16671.55 | AB77: 16671.55
A78: 816 | B78: FRONIUS WELDING CENTRE | F78: BRAM | G78: BRAM | I78: 2014 | M78: 450000 | P78: 178000 | Q78: 227000 | R78: =+J78+P78+Q78 -> 405000 | W78: MISC | Z78: =+J78-V78 -> 0
A79: 706 | B79: SCHARMANN (PRESTIGE) 945M US | C79: [used] | F79: BRAM | G79: BRAM | I79: 2007 | J79: =+'706'!R7 -> 1085452.5 | K79: =+'706'!$S$7 -> 1085452.5 | L79: =+J79-K79 -> 0 | M79: 2500000 | N79: STORAGE | O79: =+J79-K79-L79 -> 2.3283064e-10 | P79: 40000 | Q79: 950000 | R79: =+J79+P79+Q79 -> 2075452.5 | V79: 1085452.5 | W79: 518 | Z79: =+J79-V79 -> 0
G80: BRAM Total | M80: =SUBTOTAL(9,M37:M79) -> 16366002 | AB80: =SUBTOTAL(9,AB37:AB79) -> 1049550.9
A81: 298 | B81: LATHE - MORI-SEIKI SL-6 | C81: 1981 FANUX CTL 6T SYSTEM | D81: 227 | F81: BURL | G81: BURL | I81: 2010 | J81: 32765.66 | L81: =+J81-K81 -> 32765.66 | M81: 30000 | N81: A | O81: =+J81-K81-L81 -> 0 | R81: =+J81+P81+Q81 -> 32765.66 | S81: see # 521 | V81: 62765.66 | W81: 277 | Z81: =+J81-V81 -> -30000
A82: 500 | B82: =+'500'!A7 -> G&L 42" | C82: =+'500'!A8 -> FHVTC | D82: =+'500'!C7 -> 511-152-90 | F82: =+'500'!B11 -> DUNDALK | G82: BURL | I82: 2003 | J82: =+'500'!C14 -> 344790.52 | K82: =+'500'!S7 -> 344790.52 | L82: =+J82-K82 -> 0 | M82: 135000 | N82: A | O82: =+J82-K82-L82 -> 0 | R82: =+J82+P82+Q82 -> 344790.52 | V82: 344790.52 | W82: 302 | Z82: =+J82-V82 -> 0
A83: 501 | B83: =+'501'!A7 -> MANDELLI | C83: =+'501'!A8 -> 1500 B HMC | D83: =+'501'!C7 -> 7588 | F83: =+'501'!B11 -> BURL | G83: BURL | I83: 2006 | J83: =+'501'!R7 -> 1102622 | K83: =+'501'!S7 -> 1102622 | L83: =+J83-K83 -> 0 | M83: 600000 | N83: A | O83: =+J83-K83-L83 -> -2.3283064e-10 | R83: =+J83+P83+Q83 -> 1102622 | V83: 1102622 | W83: 303 | Z83: =+J83-V83 -> 0
A84: 503 | B84: =+'503'!A7 -> MANDELLI | C84: =+'503'!A8 -> 7555 | D84: =+'503'!C7 -> 7555 | F84: =+'503'!B11 -> BURL 1 | G84: BURL | I84: 2005 | J84: =+'503'!R7 -> 902774 | K84: =+'503'!S7 -> 902774 | L84: =+J84-K84 -> 0 | M84: 650000 | N84: A | O84: =+J84-K84-L84 -> -1.1641532e-10 | R84: =+J84+P84+Q84 -> 902774 | V84: 902774 | W84: 305 | Z84: =+J84-V84 -> 0
A85: 505 | B85: 10 TON CRANE KONE (2) | C85: [included with bldg] | E85: M | F85: BURL | G85: BURL | L85: =+J85-K85 -> 0 | M85: 20000 | O85: =+J85-K85-L85 -> 0 | R85: =+J85+P85+Q85 -> 0 | W85: 306 | Z85: =+J85-V85 -> 0
A86: 506 | B86: 5 TON KONE | C86: [included with bldg] | E86: M | F86: BURL | G86: BURL | L86: =+J86-K86 -> 0 | M86: 10000 | O86: =+J86-K86-L86 -> 0 | R86: =+J86+P86+Q86 -> 0 | W86: 307 | Z86: =+J86-V86 -> 0
A87: 507 | B87: 1 TON JIB CRANE (6) | C87: [included with bldg] | E87: M | F87: BURL | G87: BURL | L87: =+J87-K87 -> 0 | M87: 24000 | O87: =+J87-K87-L87 -> 0 | R87: =+J87+P87+Q87 -> 0 | W87: 308 | Z87: =+J87-V87 -> 0
A88: 508 | B88: 2 DEMAG 10 & 5 TON CRANES | E88: M | F88: BURL | G88: BURL | L88: =+J88-K88 -> 0 | M88: 35000 | O88: =+J88-K88-L88 -> 0 | R88: =+J88+P88+Q88 -> 0 | W88: 309 | Z88: =+J88-V88 -> 0
A89: 509 | B89: 10 TON CRANE - CDN. CRANE | C89: [new] | E89: M | F89: BURL | G89: BURL | L89: =+J89-K89 -> 0 | M89: 15000 | O89: =+J89-K89-L89 -> 0 | R89: =+J89+P89+Q89 -> 0 | W89: 310 | Z89: =+J89-V89 -> 0 | AB89: 74464.08
A90: 511 | B90: COMPRESSOR | C90: [new] | E90: M | F90: BURL | G90: BURL | L90: =+J90-K90 -> 0 | O90: =+J90-K90-L90 -> 0 | R90: =+J90+P90+Q90 -> 0 | Z90: =+J90-V90 -> 0 | AB90: 11990
A91: 517 | B91: FLOOR SWEEPER | E91: M | F91: BURL | G91: BURL | L91: =+J91-K91 -> 0 | M91: 5000 | N91: A | O91: =+J91-K91-L91 -> 0 | R91: =+J91+P91+Q91 -> 0 | W91: 505 | Z91: =+J91-V91 -> 0
A92: 518 | B92: CRANES - BURLINGTON (YE 2005) | E92: M | F92: BURL | G92: BURL | I92: 2012 | L92: =+J92-K92 -> 0 | M92: 35000 | N92: A | O92: =+J92-K92-L92 -> 0 | R92: =+J92+P92+Q92 -> 0 | W92: 506 | Z92: =+J92-V92 -> 0
A93: 519 | B93: HYSTE 2003 LIFT TRUCK - BURL | E93: M | F93: BURL | G93: BURL | L93: =+J93-K93 -> 0 | M93: 10000 | N93: A | O93: =+J93-K93-L93 -> 0 | R93: =+J93+P93+Q93 -> 0 | W93: 507 | Z93: =+J93-V93 -> 0
A94: 521 | B94: LATHE - MORI-SEIKI SL-3H | C94: 1985 FANUC CTL 10TE-F | D94: 4539 | F94: BURL | G94: BURL | I94: 2011 | J94: =12006.46 -> 12006.46 | L94: =+J94-K94 -> 12006.46 | M94: =+J94 -> 12006.46 | N94: NOT INSTALLED | O94: =+J94-K94-L94 -> 0 | R94: =+J94+P94+Q94 -> 12006.46 | V94: 22006.46 | W94: 508 | Z94: =+J94-V94 -> -10000
A95: 523 | B95: CMM INSPECTION - UPGRADE | C95: BROWN AND SHARP | D95: 0196-2404 | F95: BURL | G95: BURL | I95: 2012 | J95: 16000 | L95: =+J95-K95 -> 16000 | M95: =+J95 -> 16000 | N95: A | O95: =+J95-K95-L95 -> 0 | R95: =+J95+P95+Q95 -> 16000 | W95: 510 | Z95: =+J95-V95 -> 16000
A96: 810 | B96: BAND SAW | C96: 115-B | D96: 6158 | F96: BURL | G96: BURL | I96: 2013 | J96: 3562.5 | M96: =+J96 -> 3562.5 | R96: =+J96+P96+Q96 -> 3562.5 | S96: PO-109586 | T96: HEINMAN | W96: 720 | Z96: =+J96-V96 -> 3562.5
A97: 815 | B97: MICROWEILY HIGH SPEED PRECISION LATHE | C97: TY-1640S | D97: S10006-021 | F97: BURL | G97: BURL | I97: 2013 | J97: 16671.55 | M97: =+J97 -> 16671.55 | R97: =+J97+P97+Q97 -> 16671.55 | S97: PO-109586 | T97: HEINMAN | Z97: =+J97-V97 -> 16671.55 | AB97: 16884.66
G98: BURL Total | M98: =SUBTOTAL(9,M81:M97) -> 1617240.5 | AB98: =SUBTOTAL(9,AB81:AB97) -> 103338.74
A99: 241 | B99: OUTSIDE CRANE - 20 TON | E99: M | F99: BURL1 | G99: BURL1 | L99: =+J99-K99 -> 0 | N99: I | O99: =+J99-K99-L99 -> 0 | R99: =+J99+P99+Q99 -> 0 | W99: 231 | Z99: =+J99-V99 -> 0
A100: 723 | B100: KOLOMNA VBM | C100: 1A563F4 CNC | D100: 1 | F100: BURL1 | G100: BURL1 | I100: 2012 | J100: ='723'!$C$14 -> 2939202.4 | L100: =+J100-K100 -> 2939202.4 | M100: =+J100 -> 2939202.4 | N100: I | O100: =+J100-K100-L100 -> 0 | P100: 99000 | Q100: 561000 | R100: =+J100+P100+Q100 -> 3599202.4 | W100: 719.2 | Z100: =+J100-V100 -> 2939202.4 | AB100: 326945.26
A101: 800 | B101: PAMA ACC 200/530 | D101: 62-2011 | F101: BURL1 | G101: BURL1 | I101: 2012 | J101: 335624.1 | M101: =1350000*1.38 -> 1863000 | N101: INSTALL TBD | P101: =1267000+196000 -> 1463000 | Q101: 873000 | R101: =+J101+P101+Q101 -> 2671624.1 | T101: BONETTI | W101: 720.1 | Z101: =+J101-V101 -> 335624.1 | AB101: 310018.29
...

Sheet Annual Depr.
A1: ABS EQUIPMENT LEASING INC.
A2: Select Equipment List
A3: Source: F 2009 Fixed Asset Summary
S4: Total | U4: Book
A5: Description | B5: Asset # | C5: Serial # | S5: Costs | T5: Depr. | U5: Value
S7: =+#REF! -> #REF! | T7: =+-C34 -> #REF! | U7: =+S7-T7 -> #REF!
B11: Asset #
A13: Purchased Year Ending | C13: Total | D13: 1994 | E13: misc | F13: 1995 | G13: 1996 | H13: 1997 | I13: 1998 | J13: 1999 | K13: 2000 | L13: 2001 | M13: 2002 | N13: 2003 | O13: 2004 | P13: 2005 | Q13: 2006 | R13: 2007 | S13: 2008 | T13: 2009 | U13: 2010
A14: Purchases (Fiscal Yr.)
A15: check | D15: Segal | E15: ABS
A16: Depreciation | B16: 1994 | C16: #REF!
B17: 1995 | C17: #REF!
B18: 1996 | C18: #REF!
B19: 1997 | C19: #REF!
B20: 1998 | C20: #REF!
B21: 1999 | C21: #REF!
B22: 2000 | C22: #REF! | D22: -539044 | E22: -2400321.2
B23: 2001 | C23: #REF! | D23: -785174 | E23: -2739563.9
B24: 2002 | C24: #REF! | D24: -1683282 | E24: -2975686.1
B25: 2003 | C25: #REF! | D25: -1933030 | E25: -3044242.8
B26: 2004 | C26: #REF! | D26: -2164488.4 | E26: -3127839
B27: 2005 | C27: #REF! | D27: -2548243 | E27: -3210482.9
B28: 2006 | C28: #REF! | D28: -2640430 | E28: -3164727.2
B29: 2007 | C29: #REF! | D29: -2680139 | E29: -2960489
B30: 2008 | C30: #REF! | D30: -3239313 | E30: -3386109.1
B31: 2009 | C31: #REF! | D31: -3886113 | E31: -3937819.3
A32: To April 30th, 2010 | B32: 2010 | C32: #REF!
A34: ST | C34: =SUM(C16:C33) -> #REF! | D34: =SUM(D16:D33) -> -22099256 | E34: =SUM(E16:E33) -> -30947281
A36: Total depr. As per summary | C36: 40949363
A37: Variance | C37: =SUM(C34:C36) -> #REF!
O39: =SUM(F32:F39) -> 0

Sheet templ
A1: ABS EQUIPMENT LEASING INC. | O1: "Do not add rows or columns"
A2: Equipment List
A3: Source: F 2014 Fixed Asset Summary
R4: Total | T4: Book
A5: Description | B5: Asset # | C5: Serial # | R5: Costs | S5: Depr. | T5: Value
R7: =+C14 -> 0 | S7: =+-C40 -> 0 | T7: =+R7-S7 -> 0
A11: Location:
A13: Purchased Year Ending | C13: Total | D13: 1994 | E13: 1995 | F13: 1996 | G13: 1997 | H13: 1998 | I13: 1999 | J13: 2000 | K13: 2001 | L13: 2002 | M13: 2003 | N13: 2004 | O13: 2005 | P13: 2006 | Q13: 2007 | R13: 2008 | S13: 2009 | T13: 2010 | U13: 2011 | V13: 2012 | W13: 2013 | X13: 2014 | Y13: 2015
A14: Purchases (Fiscal Yr.) | C14: =SUM(D14:X14) -> 0 | D14: 0 | E14: 0 | F14: 0 | G14: 0 | H14: 0 | I14: 0 | J14: 0 | K14: 0 | L14: 0 | M14: 0
A16: Depreciation | B16: 1994 | C16: =-SUM(D16:X16) -> 0 | D16: =+D$14/7/2 -> 0
B17: 1995 | C17: =-SUM(D17:X17) -> 0 | D17: =+D$14/7 -> 0 | E17: =+E$14/7/2 -> 0
B18: 1996 | C18: =-SUM(D18:X18) -> 0 | D18: =+D17 -> 0 | E18: =+E$14/7 -> 0 | F18: =+F$14/7/2 -> 0
B19: 1997 | C19: =-SUM(D19:X19) -> 0 | D19: =+D18 -> 0 | E19: =+E18 -> 0 | F19: =+F$14/7 -> 0 | G19: =+G$14/7/2 -> 0
B20: 1998 | C20: =-SUM(D20:X20) -> 0 | D20: =+D19 -> 0 | E20: =+E19 -> 0 | F20: =+F19 -> 0 | G20: =+G$14/7 -> 0 | H20: =+H$14/7/2 -> 0
B21: 1999 | C21: =-SUM(D21:X21) -> 0 | D21: =+D20 -> 0 | E21: =+E20 -> 0 | F21: =+F20 -> 0 | G21: =+G20 -> 0 | H21: =+H$14/7 -> 0 | I21: =+I$14/7/2 -> 0
B22: 2000 | C22: =-SUM(D22:X22) -> 0 | D22: =+D21 -> 0 | E22: =+E21 -> 0 | F22: =+F21 -> 0 | G22: =+G21 -> 0 | H22: =+H21 -> 0 | I22: =+I$14/7 -> 0 | J22: =+J$14/7/2 -> 0
B23: 2001 | C23: =-SUM(D23:X23) -> 0 | D23: =+D$14/7/2 -> 0 | E23: =+E22 -> 0 | F23: =+F22 -> 0 | G23: =+G22 -> 0 | H23: =+H22 -> 0 | I23: =+I22 -> 0 | J23: =+J$14/7 -> 0 | K23: =+K$14/7/2 -> 0
B24: 2002 | C24: =-SUM(D24:X24) -> 0 | E24: =+E$14/7/2 -> 0 | F24: =+F23 -> 0 | G24: =+G23 -> 0 | H24: =+H23 -> 0 | I24: =+I23 -> 0 | J24: =+J23 -> 0 | K24: =+K$14/7 -> 0 | L24: =+L$14/7/2 -> 0
B25: 2003 | C25: =-SUM(D25:X25) -> 0 | F25: =+F$14/7/2 -> 0 | G25: =+G24 -> 0 | H25: =+H24 -> 0 | I25: =+I24 -> 0 | J25: =+J24 -> 0 | K25: =+K24 -> 0 | L25: =+L$14/7 -> 0 | M25: =+M$14/7/2 -> 0
B26: 2004 | C26: =-SUM(D26:X26) -> 0 | G26: =+G$14/7/2 -> 0 | H26: =+H25 -> 0 | I26: =+I25 -> 0 | J26: =+J25 -> 0 | K26: =+K25 -> 0 | L26: =+L25 -> 0 | M26: =+M$14/7 -> 0 | N26: =+N$14/7/2 -> 0
B27: 2005 | C27: =-SUM(D27:X27) -> 0 | H27: =+H$14/7/2 -> 0 | I27: =+I26 -> 0 | J27: =+J26 -> 0 | K27: =+K26 -> 0 | L27: =+L26 -> 0 | M27: =+M26 -> 0 | N27: =+N$14/7 -> 0 | O27: =+O$14/7/2 -> 0
B28: 2006 | C28: =-SUM(D28:X28) -> 0 | I28: =+I$14/7/2 -> 0 | J28: =+J27 -> 0 | K28: =+K27 -> 0 | L28: =+L27 -> 0 | M28: =+M27 -> 0 | N28: =+N27 -> 0 | O28: =+O$14/7 -> 0 | P28: =+P$14/7/2 -> 0
B29: 2007 | C29: =-SUM(D29:X29) -> 0 | J29: =+J$14/7/2 -> 0 | K29: =+K28 -> 0 | L29: =+L28 -> 0 | M29: =+M28 -> 0 | N29: =+N28 -> 0 | O29: =+O28 -> 0 | P29: =+P$14/7 -> 0 | Q29: =+Q$14/7/2 -> 0
B30: 2008 | C30: =-SUM(D30:X30) -> 0 | K30: =+K$14/7/2 -> 0 | L30: =+L29 -> 0 | M30: =+M29 -> 0 | N30: =+N29 -> 0 | O30: =+O29 -> 0 | P30: =+P29 -> 0 | Q30: =+Q$14/7 -> 0 | R30: =+R$14/7/2 -> 0
B31: 2009 | C31: =-SUM(D31:X31) -> 0 | L31: =+L$14/7/2 -> 0 | M31: =+M30 -> 0 | N31: =+N30 -> 0 | O31: =+O30 -> 0 | P31: =+P30 -> 0 | Q31: =+Q30 -> 0 | R31: =+R$14/7 -> 0 | S31: =+S$14/7/2 -> 0
A32: To April 30th, 2010 | B32: 2010 | C32: =-SUM(D32:X32) -> 0 | M32: =+M$14/7/2 -> 0 | N32: =+N31 -> 0 | O32: =+O31 -> 0 | P32: =+P31 -> 0 | Q32: =+Q31 -> 0 | R32: =+R31 -> 0 | S32: =+S$14/7 -> 0 | T32: =+T$14/7/2 -> 0
B33: 2011 | C33: =-SUM(D33:X33) -> 0 | N33: =+N$14/7/2 -> 0 | O33: =+O32 -> 0 | P33: =+P32 -> 0 | Q33: =+Q32 -> 0 | R33: =+R32 -> 0 | S33: =+S32 -> 0 | T33: =+T$14/7 -> 0 | U33: =+U$14/7/2 -> 0
B34: 2012 | C34: =-SUM(D34:X34) -> 0 | O34: =+O$14/7/2 -> 0 | P34: =+P33 -> 0 | Q34: =+Q33 -> 0 | R34: =+R33 -> 0 | S34: =+S33 -> 0 | T34: =+T$14/7 -> 0 | U34: =+U$14/7 -> 0 | V34: =+V$14/7/2 -> 0
B35: 2013 | C35: =-SUM(D35:X35) -> 0
B36: 2014 | C36: =-SUM(D36:X36) -> 0
B37: 2015
A40: ST | B40: =SUM(D40:X40) -> 0 | C40: =SUM(C16:C39) -> 0 | D40: =-SUM(D16:D39)+D14 -> 0 | E40: =-SUM(E16:E39)+E14 -> 0 | F40: =-SUM(F16:F39)+F14 -> 0 | G40: =-SUM(G16:G39)+G14 -> 0 | H40: =-SUM(H16:H39)+H14 -> 0 | I40: =-SUM(I16:I39)+I14 -> 0 | J40: =-SUM(J16:J39)+J14 -> 0 | K40: =-SUM(K16:K39)+K14 -> 0 | ... X40: =-SUM(X16:X39)+X14 -> 0
A42: Net Book Value | C42: =+C14+C40 -> 0
N45: =SUM(E32:E45) -> 0

Sheet SUMMARY
A1: ABS EQUIPMENT LEASING INC. | F1: 1490 A
A2: FIXED ASSET LEDGER | F2: 1490 B | I2: LINKED | J2: LINKED TO DET SHEET
B3: REVISED AS OF Jul 17, 2024 | J3: VALUE UPDATED TO F13
B4: NEW FILE FOR F 25 | J4: IN MISC SUMMARY | X4: MAY NOT
E5: M | F5: included in Misc. Summary | X5: BE RELAVENT | AB5: PAMA
I6: A | O6: B | P6: C | Q6: A + B + C | U6: RECONCILIATION TO F11 SCH | X6: F 11 | Y6: Linked to sheets | Z6: Linked to sheets | AA6: Linked to sheets | AB6: F13 | AC6: Linked to sheets | AH6: Linked to sheets | AI6: Linked to sheets | AK6: F16 ABSEL | AL6: F14 ABSEL | AM6: F15 ABSM | AP6: Linked to sheets | AR6: Linked to sheets | AT6: Linked to sheets | AV6: Linked to sheets | AX6: Linked to sheets | AZ6: Linked to sheets | BB6: Linked to sheets | BD6: Linked to sheets
A7: Asset | H7: Fiscal | I7: Total | K7: Book | L7: FMV | M7: Active/ Inactive | O7: ON | P7: FORECAST | Q7: TOTAL | S7: Orig | T7: FINAL BEG | X7: VARIANCE | Y7: Additions | Z7: Additions | AA7: Additions | AB7: PAMA | AC7: Additions | AH7: Additions | AI7: Additions | AK7: DEPOSIT TO | AL7: DEPOSIT TO | AM7: DEPOSIT TO | AP7: Additions | AR7: Additions | AT7: Additions | AV7: Additions | AX7: Additions | AZ7: Additions | BB7: Additions | BD7: Additions
A8: # | B8: Machine Name | C8: Model | D8: Serial # | E8: M | F8: Location | G8: Bay | H8: Purch Yr. | I8: Costs to Date | J8: Depreciation | K8: Value | L8: ESTIMATE | O8: DEPOSIT | P8: SPEND | Q8: COSTS | R8: Vendor | S8: PO # | T8: F11 | V8: F11 | W8: F11 | X8: TO F13 | Y8: F11 | Z8: F12 | AA8: F13 | AB8: ALLOCATION | AC8: F14 | AD8: NOTES | AE8: DEPRECIATION | AF8: BOOK VALUE | AH8: F15 | AI8: F16 | AJ8: NOTES | AK8: VENDOR | AL8: VENDOR | AM8: VENDOR | AP8: F17 | AR8: F18 | AT8: F19 | AV8: F20 | AX8: F21 | AZ8: F22 | BB8: F23 | BD8: F24
A9: 100 | B9: FORESTLINE #1 | C9: =+'100'!A8 -> VECOMIL 563 5 AXIS CNC VERTICAL | D9: 3051 | F9: MISS | G9: 1495 | H9: 2004 | I9: ='100'!C14 -> 1971035.5 | J9: =+'100'!S7 -> 1971035.5 | K9: =+I9-J9 -> 0 | L9: 2000000 | M9: A | N9: =+I9-J9-K9 -> -4.6566129e-10 | O9: =82000+347000 -> 429000 | P9: =307000+82000 -> 389000 | Q9: =+I9+O9+P9 -> 2789035.5 | T9: =544455 -> 544455 | U9: 100 | X9: =+I9-T9 -> 1426580.5 | Y9: ='100'!U14 -> 33173 | Z9: =+'100'!V14 -> 440690.72 | AA9: ='100'!W14 -> 37505.37 | AC9: ='100'!X14 -> 902360.38 | AE9: ='100'!S7 -> 1971035.5 | AF9: ='100'!T7 -> 0 | AH9: ='100'!Y14 -> 12851.4
A10: 101 | B10: MONTI FT 50 TG ( PURCH - ALESA MONTI) | C10: FT50TG | D10: 293/05.95 | F10: MISS | G10: ='101'!$C$11 -> C2 | H10: ='101'!$F$13 -> 1996 | I10: =+'101'!R7 -> 970993.94 | J10: =+'101'!S7 -> 825242.42 | K10: =+I10-J10 -> 145751.52 | L10: 200000 | M10: A | N10: =+I10-J10-K10 -> 0 | Q10: =+I10+O10+P10 -> 970993.94 | T10: 661741.31 | U10: 101 | X10: =+I10-T10 -> 309252.63 | AA10: ='101'!W14 -> 0 | AC10: ='101'!X15 -> 0 | AH10: ='101'!$Y$14 -> 0 | AV10: ='101'!AD14 -> 62123.56 | AX10: ='101'!AE14 -> 247129.07
A11: 102 | B11: FORESTLINE #2 | C11: FORESTLINE RETROFIT | D11: 3052 | F11: DUNDALK | H11: 2004 | I11: ='102'!R7 -> 560665.7 | J11: =+'102'!S7 -> 560665.7 | K11: =+I11-J11 -> 0 | L11: 500000 | M11: I | N11: =+I11-J11-K11 -> -1.1641532e-10 | Q11: =+I11+O11+P11 -> 560665.7 | T11: =T9 -> 544455 | U11: 102 | X11: =+I11-T11 -> 16210.7 | AA11: ='102'!W14 -> 0 | AC11: ='102'!X14 -> 0 | AD11: IN STORAGE | AH11: ='102'!$Y$14 -> 16211.08
A12: 103 | B12: PAMA SPEEDRAM # 3 INCL TBL | C12: BONETTI RETROFIT | D12: 33C-7168 | F12: BURL 1 | G12: 1601 | H12: ='103'!$I$13 -> 1999 | I12: =+'103'!R7 -> 3824420.5 | J12: =+'103'!S7 -> 3802179.5 | K12: =+I12-J12 -> 22241.024 | L12: 2500000 | M12: A | N12: =+I12-J12-K12 -> 0 | O12: 533000 | P12: 1505000 | Q12: =+I12+O12+P12 -> 5862420.5 | T12: 1307028.3 | U12: 103 | X12: =+I12-T12 -> 2517392.3 | AA12: ='103'!W14 -> 77000 | AB12: 77000 | AC12: ='103'!X14 -> 0 | AD12: TSF 1115008 | AH12: ='103'!$Y$14 -> 0 | AI12: ='103'!Z14 -> 2416440.4 | AL12: =66325+560822+139559+182181 -> 948887 | AM12: =26232.76+84780+193903.8+152604 -> 457520.56 | BD12: ='103'!AH14 -> 23951.88
A13: 104 | B13: PAMA CENTER 110 PO 113295 | C13: 5 AXIS | D13: 7357 | F13: JL | H13: ='104'!$D$13 -> 1994 | I13: =+'104'!R7 -> 2069204.1 | J13: =+'104'!S7 -> 2069204.1 | K13: =+I13-J13 -> 0 | L13: 1500000 | M13: A | N13: =+I13-J13-K13 -> -2.3283064e-10 | O13: 274000 | P13: 718000 | Q13: =+I13+O13+P13 -> 3061204.1 | T13: 783833.82 | U13: 104 | X13: =+I13-T13 -> 1285370.3 | AB13: 0 | AC13: ='104'!X14 -> 0 | AD13: TSF 1115008 | AH13: ='104'!$Y$14 -> 1366692.1 | AL13: =117808+224914+73270+80646 -> 496638 | AP13: =+'104'!AA14 -> -81321.82
A14: 105 | B14: WOTAN RAPID 2 | D14: 68142 | F14: MISS | G14: ='105'!$C$11 -> B4 | H14: ='105'!$M$13 -> 2003 | I14: =+'105'!R7 -> 827862.17 | J14: =+'105'!S7 -> 827862.17 | K14: =+I14-J14 -> 0 | L14: 450000 | M14: A | N14: =+I14-J14-K14 -> 1.1641532e-10 | Q14: =+I14+O14+P14 -> 827862.17 | T14: 743479.62 | U14: 105 | X14: =+I14-T14 -> 84382.55 | AC14: ='105'!X14 -> 0 | AH14: ='105'!$Y$14 -> 0
A15: 106 | B15: WOTAN 5 - Rapid 5P | C15: =+'106'!A8 -> CNC W/CNC A.B.840 D | D15: =+'106'!C7 -> 67019 | F15: =+'106'!B11 -> MISS | G15: ='106'!$C$11 -> A3 | H15: 2002 | I15: =+'106'!R7 -> 985457.86 | J15: =+'106'!S7 -> 984734.75 | K15: =+I15-J15 -> 723.10714 | L15: 750000 | M15: A | N15: =+I15-J15-K15 -> 0 | Q15: =+I15+O15+P15 -> 985457.86 | T15: 982083.36 | U15: 106 | X15: =+I15-T15 -> 3374.5 | AH15: ='106'!$Y$14 -> 0 | AT15: =+'106'!AC14 -> 3374.5
A16: 107 | B16: WOTAN RAPID 6 | C16: CNC HBM | D16: 65027 | F16: BURL 1 | G16: 1601 | H16: ='107'!$K$13 -> 2001 | I16: =+'107'!R7 -> 1785899.9 | J16: =+'107'!S7 -> 1682124.8 | K16: =+I16-J16 -> 103775.19 | L16: 1500000 | M16: A | N16: =+I16-J16-K16 -> 0 | Q16: =+I16+O16+P16 -> 1785899.9 | T16: 1628901 | U16: 107 | X16: =+I16-T16 -> 156998.98 | AH16: ='107'!$Y$14 -> 0 | AP16: =+'107'!AA14 -> 10468.74 | AR16: =+'107'!AB14 -> 22283.16 | AX16: ='107'!AE14 -> 24951.91 | AZ16: ='107'!AF14 -> 25584.97 | BB16: ='107'!AG14 -> 73710.2
A17: 108 | B17: =+'108'!A7 -> SAN ROCCO - FUTURA 14 | C17: =+'108'!A9 -> HORIZONTAL BORING MILL | D17: =+'108'!C7 -> F07/6 | F17: =+F11 -> DUNDALK | G17: 1495 | H17: 1994 | I17: =+'108'!R7 -> 1288891.3 | J17: =+'108'!S7 -> 1288891.3 | K17: =+I17-J17 -> 0 | L17: 875000 | M17: A | N17: =+I17-J17-K17 -> -2.3283064e-10 | Q17: =+I17+O17+P17 -> 1288891.3 | T17: 1288891.3 | U17: 108 | X17: =+I17-T17 -> 0 | AH17: ='108'!$Y$14 -> 0
A18: 110 | B18: NOT IN USE - SOLD | L18: =+I18 -> 0 | M18: I | S18: 645516
A19: 111 | B19: TOSHIBA BSF - 150B #1 | D19: 520443 | F19: MISS | G19: ='111'!$C$11 -> A2 | H19: ='111'!$J$13 -> 2000 | I19: =+'111'!R7 -> 2296413.2 | J19: ='111'!S7 -> 2245293.5 | K19: =+I19-J19 -> 51119.653 | L19: 1300000 | M19: A | N19: =+I19-J19-K19 -> 0 | Q19: =+I19+O19+P19 -> 2296413.2 | T19: 2216893.7 | U19: 111 | X19: =+I19-T19 -> 79519.46 | AH19: ='111'!$Y$14 -> 0 | AZ19: ='111'!AF14 -> 79519.46
A20: 112 | B20: =+'112'!A7 -> TOSHIBA BTD-110 - R 16 | C20: =+'112'!A8 -> HB&M | D20: =+'112'!C7 -> 143601 | F20: =+'112'!B11 -> MISS | G20: ='112'!$C$11 -> C1 | H20: 1997 | I20: =+'112'!R7 -> 668543.53 | J20: =+'112'!S7 -> 668543.53 | K20: =+I20-J20 -> 0 | L20: 285000 | M20: A | N20: =+I20-J20-K20 -> 0 | Q20: =+I20+O20+P20 -> 668543.53 | T20: 668543.53 | U20: 112 | X20: =+I20-T20 -> 0 | AH20: ='112'!$Y$14 -> 0
A21: 113 | B21: =+'113'!A7 -> Toshiba BTD 200QF | C21: =+'113'!A8 -> HB&M | D21: 144237 | F21: =+'113'!B11 -> MISS | G21: C1 | H21: 2001 | I21: =+'113'!R7 -> 685302.63 | J21: =+'113'!S7 -> 685302.63 | K21: =+I21-J21 -> 0 | L21: 375000 | M21: A | N21: =+I21-J21-K21 -> -1.1641532e-10 | Q21: =+I21+O21+P21 -> 685302.63 | T21: 685302.63 | U21: 113 | X21: =+I21-T21 -> 0 | AH21: ='113'!$Y$14 -> 0
A22: 115 | B22: WELDING POSITIONER NEW | C22: 30-6 AB POSIT | D22: 15312X08-20 | F22: 3100 | G22: 3100 | H22: 2009 | I22: ='115'!$R$7 -> 38496.5 | J22: ='115'!S7 -> 38496.5 | K22: =+I22-J22 -> 0 | L22: 8000 | M22: A | N22: =+I22-J22-K22 -> 7.2759576e-12 | Q22: =+I22+O22+P22 -> 38496.5 | T22: 19120.07 | U22: 115 | X22: =+I22-T22 -> 19376.43 | AH22: ='115'!$Y$14 -> 0 | AI22: ='115'!$Z$14 -> 19376.43
A23: 117 | B23: TOSHIBA BTD-13F.R22 | D23: 144926 | F23: MISS | G23: 1495 | H23: ='117'!$Q$13 -> 2007 | I23: =+'117'!R7 -> 749420.97 | J23: =+'117'!S7 -> 749420.97 | K23: =+I23-J23 -> 0 | L23: 600000 | M23: A | N23: =+I23-J23-K23 -> 0 | Q23: =+I23+O23+P23 -> 749420.97 | T23: 749420.97 | U23: 117 | X23: =+I23-T23 -> 0 | AH23: ='117'!$Y$14 -> 0
A24: 118 | B24: TOSHIBA TMD - 16 | C24: CNC VBM | D24: 420165 | F24: MISS | G24: 1495 | H24: ='118'!$Q$13 -> 2007 | I24: =+'118'!R7 -> 691113.35 | J24: =+'118'!S7 -> 691113.35 | K24: =+I24-J24 -> 0 | L24: 500000 | M24: A | N24: =+I24-J24-K24 -> -1.1641532e-10 | Q24: =+I24+O24+P24 -> 691113.35 | T24: 691113.35 | U24: 118 | X24: =+I24-T24 -> 0 | AH24: ='118'!$Y$14 -> 0
A25: 119 | B25: TOSHIBA TUE-15 | C25: ='119'!$A$7 -> VBM | D25: 440376 | F25: MISS | G25: 1495 | H25: 2009 | I25: =+'119'!R7 -> 442044 | J25: =+'119'!S7 -> 442044 | K25: =+I25-J25 -> 0 | L25: 350000 | M25: A | N25: =+I25-J25-K25 -> 5.8207661e-11 | Q25: =+I25+O25+P25 -> 442044 | T25: 442044 | U25: 119 | X25: =+I25-T25 -> 0 | AH25: ='119'!$Y$14 -> 0
A26: 122 | B26: =+'122'!A7 -> TOSHIBA BP 110 | C26: =+'122'!A8 -> HORIZONTAL PLANER TYPE | D26: =+'122'!C7 -> 130255 | F26: =+'122'!B11 -> MISS | G26: ='122'!$C$11 -> C2 | H26: 1998 | I26: =+'122'!R7 -> 583938.71 | J26: =+'122'!S7 -> 583938.71 | K26: =+I26-J26 -> 0 | L26: 300000 | M26: A | N26: =+I26-J26-K26 -> 0 | Q26: =+I26+O26+P26 -> 583938.71 | T26: 579784.84 | U26: 122 | X26: =+I26-T26 -> 4153.87 | AI26: =+'122'!Z14 -> 4153.87
A27: 124 | B27: DAEWOO ACE V850 | C27: ACE V850 | D27: V850075 | F27: MISS | G27: ='124'!$C$11 -> C2 | H27: ='124'!$H$13 -> 1998 | I27: =+'124'!R7 -> 342161.39 | J27: =+'124'!S7 -> 342161.39 | K27: =+I27-J27 -> 0 | L27: 75000 | M27: A | N27: =+I27-J27-K27 -> 0 | Q27: =+I27+O27+P27 -> 342161.39 | T27: 342161.39 | U27: 124 | X27: =+I27-T27 -> 0
A28: 126 | B28: =+'126'!A7 -> TOSHIBA BF-130B | C28: HB & M | D28: =+'126'!C7 -> 510658 | F28: =+'126'!B11 -> MISS | G28: ='126'!$C$11 -> A2 | H28: 1999 | I28: =+'126'!R7 -> 1239553.1 | J28: =+'126'!S7 -> 1239553.1 | K28: =+I28-J28 -> 0 | L28: 750000 | M28: A | N28: =+I28-J28-K28 -> -4.6566129e-10 | Q28: =+I28+O28+P28 -> 1239553.1 | T28: 1239553.1 | U28: 126 | X28: =+I28-T28 -> 0
A29: 128 | B29: TOSHIBA MPC #2 | C29: 3680B | D29: 910428 | F29: MISS | G29: ='128'!$C$11 -> A2 | H29: ='128'!$K$13 -> 2001 | I29: ='128'!R7 -> 2553028.6 | J29: ='128'!S7 -> 2553028.6 | K29: =+I29-J29 -> 0 | L29: 1400000 | M29: A | N29: =+I29-J29-K29 -> 0 | Q29: =+I29+O29+P29 -> 2553028.6 | T29: 2553028.6 | U29: 127 | V29: 159378.26 | W29: SOLD | X29: =+I29-T29 -> 0
A30: 133 | B30: SAFOP LATHE | C30: HT-850/CNC | D30: 3281 | F30: MISS | G30: ='133'!$C$11 -> B4 | H30: ='133'!$I$13 -> 1999 | I30: =+'133'!R7 -> 904845.26 | J30: =+'133'!S7 -> 904845.26 | K30: =+I30-J30 -> 0 | L30: 400000 | M30: A | N30: =+I30-J30-K30 -> 0 | Q30: =+I30+O30+P30 -> 904845.26 | T30: 885890.26 | U30: 128 | X30: =+I30-T30 -> 18955 | AH30: ='133'!Y14 -> 18955
A31: 141 | B31: KURAKI KBT-13-A | D31: 8172 | F31: MISS | G31: C3 | H31: 2006 | I31: =+'141'!R7 -> 858315.66 | J31: =+'141'!S7 -> 849327.09 | K31: =+I31-J31 -> 8988.5714 | L31: 625000 | M31: A | N31: =+I31-J31-K31 -> 0 | Q31: =+I31+O31+P31 -> 858315.66 | T31: 846875.66 | U31: 133 | X31: =+I31-T31 -> 11440 | BB31: ='141'!AG14 -> 11440
A32: 142 | B32: KURAKI KBT-13E-A | D32: 8189 | F32: MISS | G32: C3 | H32: 2007 | I32: =+'142'!R7 -> 900877.47 | J32: =+'142'!S7 -> 900877.47 | K32: =+I32-J32 -> 0 | L32: 675000 | M32: A | N32: =+I32-J32-K32 -> 0 | Q32: =+I32+O32+P32 -> 900877.47 | T32: 900877.47 | U32: 141 | X32: =+I32-T32 -> 0
A33: 144 | B33: BERTHIEZ TMM 250/315 | C33: TMM | F33: BUR -1601 | H33: 2002 | I33: =+'144'!R7 -> 2348919 | J33: =+'144'!S7 -> 1407030.7 | K33: =+I33-J33 -> 941888.24 | L33: 2000000 | M33: A | N33: =+I33-J33-K33 -> 0 | Q33: =+I33+O33+P33 -> 2348919 | T33: 1093866.1 | U33: 142 | X33: =+I33-T33 -> 1255052.9 | AX33: ='144'!AE14 -> 342005.64 | AZ33: ='144'!AF14 -> 68912.88 | BB33: ='144'!AG14 -> 400783.29 | BD33: ='144'!AH14 -> 443351.06
A34: 158 | B34: MAZAK VARIAXIS 730-5X II | D34: 211296 | F34: John Lucas - Burlington | G34: B3 | H34: 2009 | I34: =+'158'!R7 -> 612727 | J34: =+'158'!S7 -> 612727 | K34: =+I34-J34 -> 0 | L34: 400000 | M34: A | N34: =+I34-J34-K34 -> 0 | Q34: =+I34+O34+P34 -> 612727 | T34: 612727 | U34: 143 | X34: =+I34-T34 -> 0
A35: 159 | B35: TOSHIBA BP-150.R22 #2 | C35: BP-150.R22 | D35: 130380 | F35: MISS | G35: 1495 | H35: 2009 | I35: =+'159'!R7 -> 935280.49 | J35: =+'159'!S7 -> 935280.49 | K35: =+I35-J35 -> 0 | L35: 750000 | M35: A | N35: =+I35-J35-K35 -> -1.1641532e-10 | Q35: =+I35+O35+P35 -> 935280.49 | T35: 935280.49 | U35: 144 | X35: =+I35-T35 -> 0
A36: 160 | B36: MAZAK VBM | C36: ='160'!$A$8 -> E1060V/B | D36: ='160'!$C$7 -> 198546 | F36: =+F34 -> John Lucas - Burlington | G36: B1 | H36: 2008 | I36: =+'160'!R7 -> 1063805.7 | J36: ='160'!S7 -> 1063805.7 | K36: =+I36-J36 -> 0 | L36: 825000 | M36: A | N36: =+I36-J36-K36 -> 2.3283064e-10 | Q36: =+I36+O36+P36 -> 1063805.7 | T36: 1006718 | U36: 158 | X36: =+I36-T36 -> 57087.73 | AA36: ='160'!W14 -> 57087.73
A37: 164 | B37: TOSHIBA TMD-23 #1 | C37: VBM | D37: 420182 | F37: MISS | G37: 1495 | H37: 2009 | I37: =+'164'!R7 -> 897755.57 | J37: =+'164'!S7 -> 897755.57 | K37: =+I37-J37 -> 0 | L37: 800000 | M37: A | N37: =+I37-J37-K37 -> 1.1641532e-10 | Q37: =+I37+O37+P37 -> 897755.57 | T37: 892865.71 | U37: 159 | X37: =+I37-T37 -> 4889.86 | Z37: ='164'!V14 -> 4889.86 | AA37: ='164'!W14 -> 0
A38: 175 | B38: CRANE; STAHLKRANE; 7.5[t]; BRIDGE TYPE | D38: M0190435 | E38: M | F38: MISS | G38: 1490-C2 | K38: =+I38-J38 -> 0 | M38: A | N38: =+I38-J38-K38 -> 0 | Q38: =+I38+O38+P38 -> 0 | T38: 0 | U38: 160 | X38: =+I38-T38 -> 0
A39: 176 | B39: CRANE; SOS; 5[t]; BRIDGE TYPE | E39: M | F39: MISS | K39: =+I39-J39 -> 0 | M39: A | N39: =+I39-J39-K39 -> 0 | Q39: =+I39+O39+P39 -> 0 | T39: 0 | U39: 164 | X39: =+I39-T39 -> 0
A40: 177 | B40: CRANE; UNIFRAN; 2[t]; GANTRY TYPE | F40: MISS | G40: C1 | H40: 1994 | I40: =+'177'!R7 -> 2920 | J40: =+'177'!S7 -> 2920 | K40: =+I40-J40 -> 0 | M40: A | N40: =+I40-J40-K40 -> 0 | Q40: =+I40+O40+P40 -> 2920 | T40: 2920 | U40: 175 | X40: =+I40-T40 -> 0
A41: 178 | B41: CRANE; 2 STAHLKRAN 5[t]; BRIDGE TYPE | D41: 10458 | E41: M | F41: MISS | G41: C5 | K41: =+I41-J41 -> 0 | M41: A | N41: =+I41-J41-K41 -> 0 | Q41: =+I41+O41+P41 -> 0 | T41: 0 | U41: 176 | X41: =+I41-T41 -> 0
A42: 183 | B42: WALDRICH COBURG - STOCK #7743 | C42: 15-10 GM 300 NC YOM 1977 | D42: 7743 | F42: MISS | G42: A3 | H42: 1998 | I42: =+'183'!R7 -> 1904288.2 | J42: =+'183'!S7 -> 1903548.7 | K42: =+I42-J42 -> 739.5 | L42: 1500000 | M42: A | N42: =+I42-J42-K42 -> 0 | Q42: =+I42+O42+P42 -> 1904288.2 | T42: 1895087.2 | U42: 177 | X42: =+I42-T42 -> 9201 | AI42: =+'183'!Z14 -> 5750 | AT42: =+'183'!AC14 -> 3451
A43: 190 | B43: TOSHIBA TSS 20/55 | C43: VBM | D43: 310361 | F43: MISS | G43: A4 | H43: 1994 | I43: =+'190'!R7 -> 747334.13 | J43: =+'190'!S7 -> 747334.13 | K43: =+I43-J43 -> 0 | L43: 425000 | M43: A | N43: =+I43-J43-K43 -> -1.1641532e-10 | Q43: =+I43+O43+P43 -> 747334.13 | T43: 747334.13 | U43: 178 | X43: =+I43-T43 -> 0
A44: 194 | B44: LAGUN GBM 21 | D44: 30017 | F44: MISS | G44: C1 | H44: 2005 | I44: =+'194'!R7 -> 192827.85 | J44: =+'194'!S7 -> 192827.85 | K44: =+I44-J44 -> 0 | L44: 100000 | M44: A | N44: =+I44-J44-K44 -> -2.910383e-11 | Q44: =+I44+O44+P44 -> 192827.85 | T44: 192827.85 | U44: 183 | X44: =+I44-T44 -> 0
A45: 200 | B45: DEA CMM LAMBA MEASURING | C45: CMM - LAMBDA | D45: 550-016 | F45: MISS | G45: B1 | H45: 2002 | I45: =+'200'!R7 -> 360864.21 | J45: =+'200'!S7 -> 360864.21 | K45: =+I45-J45 -> 0 | L45: 300000 | M45: A | N45: =+I45-J45-K45 -> 0 | Q45: =+I45+O45+P45 -> 360864.21 | T45: 360864.21 | U45: 190 | X45: =+I45-T45 -> 0
A46: 207 | B46: 2 STAHLKRAN 15 TON | E46: M | F46: MISS | J46: 0 | K46: =+I46-J46 -> 0 | L46: 48000 | M46: A | N46: =+I46-J46-K46 -> 0 | Q46: =+I46+O46+P46 -> 0 | U46: 194 | X46: =+I46-T46 -> 0
A47: 211 | B47: PEHAKA PLATE/BLOCK VERTICAL BAND SAW | C47: SF92SPEZ | D47: 268884-50524 | E47: M | F47: MISS | G47: 1495 | K47: =+I47-J47 -> 0 | L47: 500 | M47: A | N47: =+I47-J47-K47 -> 0 | Q47: =+I47+O47+P47 -> 0 | U47: 200 | X47: =+I47-T47 -> 0
A48: 213 | B48: DARBERT MILLING MACHINE | C48: 1050 | D48: 990111S | E48: M | F48: MISS | G48: C4 | K48: =+I48-J48 -> 0 | L48: 500 | M48: A | N48: =+I48-J48-K48 -> 0 | Q48: =+I48+O48+P48 -> 0 | U48: 207 | X48: =+I48-T48 -> 0
A49: 214 | B49: DARBERT MILLING MACHINE | C49: ABERNE #3214 112/2-902T | D49: 4100.7005 | E49: M | F49: MISS | G49: C5 | K49: =+I49-J49 -> 0 | L49: 1250 | M49: A | N49: =+I49-J49-K49 -> 0 | Q49: =+I49+O49+P49 -> 0 | U49: 211 | X49: =+I49-T49 -> 0
A50: 220 | B50: FLOOR JIB CRANE - PRO CRANE | E50: M | F50: MISS | K50: =+I50-J50 -> 0 | L50: 3500 | M50: A | N50: =+I50-J50-K50 -> 0 | Q50: =+I50+O50+P50 -> 0 | U50: 213 | X50: =+I50-T50 -> 0
A51: 221 | B51: ROTARY TABLE/CNC CONTROL-OLYMPIA ENG | E51: M | F51: MISS | G51: C1 | K51: =+I51-J51 -> 0 | L51: 20000 | M51: A | N51: =+I51-J51-K51 -> 0 | Q51: =+I51+O51+P51 -> 0 | U51: 214 | X51: =+I51-T51 -> 0
A52: 228 | B52: BLANCHARD GRINDER (DARBERT) | C52: Belive Traded TB to verify | E52: M | F52: MISS | J52: =+'200'!S14 -> 0 | K52: =+I52-J52 -> 0 | N52: =+I52-J52-K52 -> 0 | Q52: =+I52+O52+P52 -> 0 | U52: 220 | X52: =+I52-T52 -> 0
A53: 230 | B53: USED KASTO BANDSAW (TECSAW INT'L) | C53: PB4 460 AU | D53: 02036070/73307 | E53: M | F53: MISS | G53: C5 | J53: =+'200'!S15 -> 0 | K53: =+I53-J53 -> 0 | L53: 10000 | M53: A | N53: =+I53-J53-K53 -> 0 | Q53: =+I53+O53+P53 -> 0 | U53: 221 | X53: =+I53-T53 -> 0
A54: 231 | B54: C.M.T. FERRO 16, 16X40 LATHE | C54: FERRO TECHINIQUE | D54: 11853 | E54: M | F54: MISS | G54: C5 | H54: 1992 | J54: =+'200'!S16 -> 0 | K54: =+I54-J54 -> 0 | L54: 8000 | M54: A | N54: =+I54-J54-K54 -> 0 | Q54: =+I54+O54+P54 -> 0 | U54: 222 | X54: =+I54-T54 -> 0
A55: 232 | B55: CRANES 10 T R.W.O.H CRANE | E55: M | F55: MISS | J55: =+'200'!S17 -> 0 | K55: =+I55-J55 -> 0 | L55: 12500 | M55: A | N55: =+I55-J55-K55 -> 0 | Q55: =+I55+O55+P55 -> 0 | U55: 223 | X55: =+I55-T55 -> 0
A56: 233 | B56: USED MILWAUKEE DRILL PRESS | D56: 59812948 | E56: M | F56: MISS | G56: B1 | J56: =+'200'!S18 -> 0 | K56: =+I56-J56 -> 0 | L56: 500 | M56: A | N56: =+I56-J56-K56 -> 0 | Q56: =+I56+O56+P56 -> 0 | U56: 224 | X56: =+I56-T56 -> 0
A57: 235 | B57: WELDING M/C | E57: M | F57: MISS | J57: =+'200'!S19 -> 0 | K57: =+I57-J57 -> 0 | N57: =+I57-J57-K57 -> 0 | Q57: =+I57+O57+P57 -> 0 | U57: 225 | X57: =+I57-T57 -> 0
A58: 237 | B58: PAMA 300 (KAMES GMBH) AT 130 | C58: 7357 PAMA AT 130 CNC Y.O.M | D58: 7357 | F58: MISS | G58: C2 | H58: 1984 | I58: ='237'!R7 -> 1988096.8 | J58: =+'237'!S7 -> 1957997.8 | K58: =+I58-J58 -> 30098.983 | L58: 2000000 | M58: A | N58: =+I58-J58-K58 -> 0 | O58: =247000+44000 -> 291000 | P58: =576000+178000+10000 -> 764000 | Q58: =+I58+O58+P58 -> 3043096.8 | T58: 582805 | U58: 226 | X58: =+I58-T58 -> 1405291.8 | AA58: ='237'!W14 -> 9053 | AB58: 9053 | AC58: ='237'!X14 -> 1359200.6 | AD58: bonétec | AE58: ='237'!S7 -> 1957997.8 | AF58: ='237'!T7 -> 30098.983 | AH58: ='237'!Y14 -> 0 | AP58: =+'237'!AA14 -> -9782.12 | AZ58: ='237'!AF14 -> 46820.64
A59: 238 | B59: TOSCAN TECH-ELECTRO SPINDLE | E59: M | F59: MISS | J59: =+'200'!S21 -> 0 | K59: =+I59-J59 -> 0 | L59: 10000 | N59: =+I59-J59-K59 -> 0 | Q59: =+I59+O59+P59 -> 0 | U59: 227 | X59: =+I59-T59 -> 0
A60: 239 | B60: TOPWELL 5VK TURRET MILL | C60: (PURC H.H. ROBERTS) | E60: M | F60: MISS | J60: =+'200'!S22 -> 0 | K60: =+I60-J60 -> 0 | L60: 1500 | N60: =+I60-J60-K60 -> 0 | Q60: =+I60+O60+P60 -> 0 | U60: 228 | X60: =+I60-T60 -> 0
A61: 240 | B61: CRANES (1490 BLDG) | E61: M | F61: MISS | J61: =+'200'!S23 -> 0 | K61: =+I61-J61 -> 0 | N61: =+I61-J61-K61 -> 0 | Q61: =+I61+O61+P61 -> 0 | U61: 230 | X61: =+I61-T61 -> 0
A62: 241 | B62: OUTSIDE CRANE - 20 TON | E62: M | F62: BURL1 | G62: 1601 | J62: =+'200'!S24 -> 0 | K62: =+I62-J62 -> 0 | M62: I | N62: =+I62-J62-K62 -> 0 | Q62: =+I62+O62+P62 -> 0 | U62: 231 | X62: =+I62-T62 -> 0
A63: 242 | B63: BAY A1 - CRANE | E63: M | F63: MISS | J63: =+'200'!S25 -> 0 | K63: =+I63-J63 -> 0 | N63: =+I63-J63-K63 -> 0 | Q63: =+I63+O63+P63 -> 0 | U63: 232 | X63: =+I63-T63 -> 0
A64: 243 | B64: 16 TON CRANE - (FRAIZO) | E64: M | F64: MISS | G64: A4 | J64: =+'200'!S26 -> 0 | K64: =+I64-J64 -> 0 | N64: =+I64-J64-K64 -> 0 | Q64: =+I64+O64+P64 -> 0 | U64: 233 | X64: =+I64-T64 -> 0
A65: 244 | B65: CRANES Y/E 2003 | E65: M | F65: MISS | J65: =+'200'!S27 -> 0 | K65: =+I65-J65 -> 0 | N65: =+I65-J65-K65 -> 0 | Q65: =+I65+O65+P65 -> 0 | U65: 234 | X65: =+I65-T65 -> 0
A66: 245 | B66: 5 TON CRANE Y/E 2004 | C66: 313344 | E66: M | F66: MISS | G66: A4 | J66: =+'200'!S28 -> 0 | K66: =+I66-J66 -> 0 | N66: =+I66-J66-K66 -> 0 | Q66: =+I66+O66+P66 -> 0 | U66: 235 | X66: =+I66-T66 -> 0
A67: 246 | B67: 88/10 TON CRANE (1490) | E67: M | F67: BURL3 - 800 Laurentian | J67: =+'200'!S29 -> 0 | K67: =+I67-J67 -> 0 | N67: =+I67-J67-K67 -> 0 | Q67: =+I67+O67+P67 -> 0 | U67: 237 | X67: =+I67-T67 -> 0
A68: 247 | B68: CRANES - 3100 JARROW (Y/E 2005) | F68: =+F67 -> BURL3 - 800 Laurentian | H68: 2005 | I68: ='247'!R7 -> 162102.44 | J68: ='247'!S7 -> 162102.44 | K68: =+I68-J68 -> 0 | L68: 100000 | M68: A | N68: =+I68-J68-K68 -> 0 | Q68: =+I68+O68+P68 -> 162102.44 | T68: 162102.44 | U68: 238 | X68: =+I68-T68 -> 0
A69: 250 | B69: HYSTER FORKLIFT (McLEARY) | E69: M | F69: MISS | G69: DELIO 1495 | K69: =+I69-J69 -> 0 | N69: =+I69-J69-K69 -> 0 | Q69: =+I69+O69+P69 -> 0 | U69: 239 | X69: =+I69-T69 -> 0
A70: 251 | B70: WELDING EQUIPTMENT | E70: M | F70: MISS | K70: =+I70-J70 -> 0 | N70: =+I70-J70-K70 -> 0 | Q70: =+I70+O70+P70 -> 0 | U70: 240 | X70: =+I70-T70 -> 0
A71: 253 | B71: TOS300 OMNITRADE | C71: WHN110 CNC | D71: OSO58 SI-16563 | F71: MISS | G71: C2 | H71: 1996 | I71: =+'253'!R7 -> 536593.71 | J71: =+'253'!S7 -> 536593.71 | K71: =+I71-J71 -> 0 | L71: 200000 | M71: A | N71: =+I71-J71-K71 -> 0 | Q71: =+I71+O71+P71 -> 536593.71 | T71: 536593.71 | U71: 241 | X71: =+I71-T71 -> 0 | AH71: ='253'!$Y$14 -> 0 | AI71: ='253'!$Z$14 -> 0
A72: 254 | B72: ENS100 - CAHMAC INT'L ENSHU - VERT MILLING | C72: EV650B | D72: 104 | F72: MISS | G72: C1 | H72: 1996 | I72: =+'254'!R7 -> 305098.4 | J72: =+'254'!S7 -> 305098.4 | K72: =+I72-J72 -> 0 | L72: 80000 | M72: A | N72: =+I72-J72-K72 -> 0 | Q72: =+I72+O72+P72 -> 305098.4 | T72: 305098.4 | U72: 242 | X72: =+I72-T72 -> 0
A73: 258 | B73: MURA TABLES | E73: M | F73: BURL 1 | K73: =+I73-J73 -> 0 | L73: 300000 | N73: =+I73-J73-K73 -> 0 | Q73: =+I73+O73+P73 -> 0 | U73: 243 | X73: =+I73-T73 -> 0
A74: 260 | B74: EIMELDINGEN | E74: M | F74: MISS | K74: =+I74-J74 -> 0 | L74: 15000 | N74: =+I74-J74-K74 -> 0 | Q74: =+I74+O74+P74 -> 0 | U74: 244 | X74: =+I74-T74 -> 0
A75: 261 | B75: SVM100 | E75: M | F75: MISS | K75: =+I75-J75 -> 0 | L75: 3000 | N75: =+I75-J75-K75 -> 0 | Q75: =+I75+O75+P75 -> 0 | U75: 245 | X75: =+I75-T75 -> 0
A76: 263 | B76: USED FRORIEP TDV 80T TABLE | E76: M | F76: =+F73 -> BURL 1 | K76: =+I76-J76 -> 0 | L76: 150000 | N76: =+I76-J76-K76 -> 0 | Q76: =+I76+O76+P76 -> 0 | U76: 246 | X76: =+I76-T76 -> 0
A77: 265 | B77: M&M TABLE - USED (CAME WITH MITSUBISHI) | E77: M | F77: =+F76 -> BURL 1 | K77: =+I77-J77 -> 0 | L77: 150000 | M77: A | N77: =+I77-J77-K77 -> 0 | Q77: =+I77+O77+P77 -> 0 | U77: 247 | X77: =+I77-T77 -> 0
A78: 266 | B78: TOSHIBA TABLES (2) - ONE SOLD | F78: =+F77 -> BURL 1 | H78: 2001 | I78: =+'266'!C14 -> 110454 | J78: =+'266'!S7 -> 110454 | K78: =+I78-J78 -> 0 | L78: 150000 | M78: A | N78: =+I78-J78-K78 -> 0 | Q78: =+I78+O78+P78 -> 110454 | U78: 248 | X78: =+I78-T78 -> 110454
A79: 268 | B79: CMT LATHE'S - PHOENIX X 2 | D79: 13334,5 | E79: M | F79: MISS | G79: C5 | K79: =+I79-J79 -> 0 | L79: 20000 | N79: =+I79-J79-K79 -> 0 | Q79: =+I79+O79+P79 -> 0 | U79: 249 | X79: =+I79-T79 -> 0
A80: 269 | B80: TOOLCRIB EQUIPMENT | E80: M | F80: MISS | K80: =+I80-J80 -> 0 | L80: 2500000 | M80: A | N80: =+I80-J80-K80 -> 0 | Q80: =+I80+O80+P80 -> 0 | U80: 250 | X80: =+I80-T80 -> 0
A81: 270 | B81: ZOLLER PRESETTER & MEASURIGN MACHINE | C81: Upgrade Purch F 2015 | F81: MISS | G81: B 1TOOLCRIB | H81: 2004 | I81: ='270'!$R$7 -> 76857.08 | J81: ='270'!$S$7 -> 76857.08 | K81: =+I81-J81 -> 0 | L81: 95000 | M81: A | N81: =+I81-J81-K81 -> 1.4551915e-11 | Q81: =+I81+O81+P81 -> 76857.08 | S81: P609150 | T81: 76857.08 | U81: 251 | X81: =+I81-T81 -> 0 | AH81: ='270'!Y14 -> 0
A82: 272 | B82: WELDING MACHINE | E82: M | F82: MISS | K82: =+I82-J82 -> 0 | L82: 35000 | M82: A | N82: =+I82-J82-K82 -> 0 | Q82: =+I82+O82+P82 -> 0 | U82: 253 | X82: =+I82-T82 -> 0
A83: 273 | B83: VIRGINIA CRANE DOUBLE GIRDER | C83: BRIDGE CRANE (50/10 TON) | D83: VC89-323 | F83: 3100 | H83: 2011 | I83: ='273'!C14 -> 120322.9 | J83: ='273'!$S$7 -> 120322.9 | K83: =+I83-J83 -> 0 | L83: 100000 | M83: A | N83: =+I83-J83-K83 -> 0 | Q83: =+I83+O83+P83 -> 120322.9 | T83: 93679.4 | U83: 254 | X83: =+I83-T83 -> 26643.5 | Y83: ='273'!U14 -> 120322.9
A84: 274 | B84: UNIVERSAL MILLING HEAD | C84: LS WALKER | D84: PO-96660 | F84: MISS | H84: 2010 | I84: ='274'!C14 -> 4900 | J84: ='274'!$S$7 -> 4900 | K84: =+I84-J84 -> 0 | L84: 5000 | N84: =+I84-J84-K84 -> 0 | Q84: =I84+O84+P84 -> 4900 | T84: 4900 | U84: 255 | X84: =+I84-T84 -> 0 | AC84: ='274'!X14 -> 0
A85: 275 | B85: Jenny Oil fired Steam Cleaner | E85: M | F85: MISS | H85: 2005 | K85: =+I85-J85 -> 0 | L85: 2000 | N85: =+I85-J85-K85 -> 0 | Q85: =+I85+O85+P85 -> 0 | U85: 257 | V85: 61725 | W85: SOLD | X85: =+I85-T85 -> 0
A86: 276 | B86: POWER CORRECTION SYSTEM - MILAN ELECTRIC | F86: MISS | H86: 2005 | I86: ='276'!R7 -> 66969.8 | J86: ='276'!S7 -> 66969.8 | K86: =+I86-J86 -> 0 | L86: 20000 | M86: A | N86: =+I86-J86-K86 -> 0 | Q86: =+I86+O86+P86 -> 66969.8 | T86: 66969.8 | U86: 258 | X86: =+I86-T86 -> 0
A87: 277 | B87: DELKEN TABLE CAPACITY 10 TON (WOTAN RAPID 2) | C87: DCN 150 ST | F87: MISS | H87: 2005 | I87: ='277'!$R$7 -> 185377.28 | J87: ='277'!$S$7 -> 185377.28 | K87: =+I87-J87 -> 0 | L87: 150000 | M87: I | N87: =+I87-J87-K87 -> 2.910383e-11 | Q87: =+I87+O87+P87 -> 185377.28 | T87: 185377.28 | U87: 259 | X87: =+I87-T87 -> 0
A88: 278 | B88: DELKEN TABLE 175 SPECIAL | C88: BF 150B BSF 150 | F88: M/BR | H88: 2006 | I88: ='278'!R7 -> 91421.42 | J88: ='278'!S7 -> 91421.42 | K88: =+I88-J88 -> 0 | L88: 150000 | M88: A | N88: =+I88-J88-K88 -> 0 | Q88: =+I88+O88+P88 -> 91421.42 | T88: 91421.42 | U88: 260 | X88: =+I88-T88 -> 0
A89: 279 | B89: PAMA S/R # 2 (VOITH PAPER) | C89: BONETTI RETROFIT | D89: =+'279'!C6 -> 5E10647006 | F89: MISS | G89: A1 | H89: 2007 | I89: ='279'!R7 -> 2001327 | J89: ='279'!S7 -> 1971228 | K89: =+I89-J89 -> 30098.983 | L89: 1800000 | M89: A | N89: =+I89-J89-K89 -> 0 | Q89: =+I89+O89+P89 -> 2001327 | T89: 1664346 | U89: 261 | X89: =+I89-T89 -> 336980.94 | Y89: ='279'!U14 -> 1268209.6 | Z89: ='279'!V14 -> 146734.73 | AA89: ='279'!W14 -> 133425 | AB89: 133425 | AC89: ='279'!X14 -> 0 | AH89: ='279'!Y14 -> 0 | AZ89: ='279'!AF14 -> 46820.64
A90: 280 | B90: TOYOTA FORKLIFT, PURCH LIFTOW LTD | D90: 14063 | E90: M | F90: MISS | K90: =+I90-J90 -> 0 | L90: 6000 | N90: =+I90-J90-K90 -> 0 | Q90: =+I90+O90+P90 -> 0 | U90: 262 | X90: =+I90-T90 -> 0
A91: 281 | B91: hyster lfit truck -MOGO LIFT EQUIP. #309367 | C91: S120XM | D91: E004V01957Z | E91: M | F91: MISS | H91: 2008 | K91: =+I91-J91 -> 0 | L91: 3000 | N91: =+I91-J91-K91 -> 0 | Q91: =+I91+O91+P91 -> 0 | U91: 263 | X91: =+I91-T91 -> 0
A92: 282 | B92: SPERONIN (EQUIP MARKETING) PRESETTER TOOL | E92: M | F92: MISS | H92: 2008 | K92: =+I92-J92 -> 0 | L92: 10000 | N92: =+I92-J92-K92 -> 0 | Q92: =+I92+O92+P92 -> 0 | U92: 264 | X92: =+I92-T92 -> 0
A93: 283 | B93: TRANSFORMER METAL DISINTEGRATOR | E93: M | F93: MISS | K93: =+I93-J93 -> 0 | L93: 8000 | N93: =+I93-J93-K93 -> 0 | Q93: =+I93+O93+P93 -> 0 | U93: 265 | X93: =+I93-T93 -> 0
A94: 284 | B94: VERTICAL BANDSAW | C94: KM1012 | E94: M | F94: DUNDALK | H94: 2008 | K94: =+I94-J94 -> 0 | L94: 500 | M94: I | N94: =+I94-J94-K94 -> 0 | Q94: =+I94+O94+P94 -> 0 | U94: 266 | X94: =+I94-T94 -> 0
A95: 286 | B95: DELKEN TABLES | F95: MISS | H95: 2008 | I95: ='286'!R7 -> 508523 | J95: ='286'!S7 -> 508523 | K95: =+I95-J95 -> 0 | L95: 200000 | M95: A | N95: =+I95-J95-K95 -> 5.8207661e-11 | Q95: =+I95+O95+P95 -> 508523 | T95: 508523 | U95: 267 | X95: =+I95-T95 -> 0
A96: 287 | B96: SAN ROCCO 110MF USED - 1490 | C96: 110MF | D96: F01-06 | E96: M | F96: DUNDALK | K96: =+I96-J96 -> 0 | L96: 60000 | M96: I | N96: =+I96-J96-K96 -> 0 | Q96: =+I96+O96+P96 -> 0 | U96: 268 | X96: =+I96-T96 -> 0 | AD96: TO BE INSTALLED IN BRAMP
A97: 288 | B97: 4 BOX TABLES 40X40X20 STAN CANADA INC | E97: M | F97: MISS | K97: =+I97-J97 -> 0 | L97: 30000 | N97: =+I97-J97-K97 -> 0 | Q97: =+I97+O97+P97 -> 0 | U97: 269 | X97: =+I97-T97 -> 0
A98: 289 | B98: KPT DIASET (USED ON ALL M/C) | C98: 50D | E98: M | F98: MISS | K98: =+I98-J98 -> 0 | L98: 5000 | N98: =+I98-J98-K98 -> 0 | Q98: =+I98+O98+P98 -> 0 | U98: 270 | X98: =+I98-T98 -> 0
A99: 292 | B99: SKYLIFT - SNORKEL ELECTRIC ATRTICULATING BOOM | C99: ATB 38 | D99: 992754 | F99: 3100 | H99: 2011 | I99: ='292'!C14 -> 8500 | J99: ='292'!S7 -> 8500 | K99: =+I99-J99 -> 0 | L99: 20000 | M99: A | N99: =+I99-J99-K99 -> 0 | Q99: =+I99+O99+P99 -> 8500 | R99: SKYLIFT | S99: V93250 | T99: 8500 | U99: 271 | W99: ='292'!W14 -> 0 | X99: =+I99-T99 -> 0 | Y99: ='292'!U14 -> 8500
A100: 293 | B100: USED MILLING HEAD (LS WALKER) | F100: MISS | H100: 2010 | I100: ='293'!C14 -> 4900 | J100: ='293'!S7 -> 4900 | K100: =+I100-J100 -> 0 | L100: 5000 | M100: A | N100: =+I100-J100-K100 -> 0 | Q100: =+I100+O100+P100 -> 4900 | T100: 4900 | U100: 272 | X100: =+I100-T100 -> 0
...

Sheet MISC
A1: ABS EQUIPMENT LEASING INC.
A2: Select Equipment List
A3: Source: F 2009 Fixed Asset Summary
S4: Total | U4: Book
A5: Description | B5: Asset # | C5: Serial # | S5: Costs | T5: Depr. | U5: Value
H6: 110120 | I6: 333836.86 | J6: 129867.83
S7: =+C123 -> 5916533.8 | T7: =+-C157 -> 4699006.8 | U7: =+S7-T7 -> 1217527
B11: Asset # | D11: 220-221-288-222-175-178-176-207-223-224-213-214-225-226-227-289-229-230-231-232-233-258-234-235-177 | E11: box tables-pallets | F11: 229-237-238-239-251-1761-248 | G11: 237 | H11: 237-240-249-255 | I11: 240-249-259-261 | J11: 240-262-263-264-265 | K11: 260 | L11: 241-242-243-250-267 | M11: 242-268 | N11: 244 | O11: 245-270-271-272-517-269-211 | P11: 518-250-263-272-275-211 | Q11: 229-250-272 | S11: 265-279-519-280-281-282--283-284-715-720-716-701- | T11: 237-229-246-265-287 | U11: 721-tosh MPC
A13: Purchased Year Ending | C13: Total | D13: 1994 | E13: misc | F13: 1995 | G13: 1996 | H13: 1997 | I13: 1998 | J13: 1999 | K13: 2000 | L13: 2001 | M13: 2002 | N13: 2003 | O13: 2004 | P13: 2005 | Q13: 2006 | R13: 2007 | S13: 2008 | T13: 2009 | U13: 2010 | V13: 2011 | W13: 2012 | X13: 2013 | Y13: 2014 | Z13: 2015 | AA13: 2016 | AB13: 2017 | AC13: 2018 | AD13: 2019 | AE13: 2020 | AF13: 2021 | AG13: 2022 | AH13: 2023 | AI13: =AH13+1 -> 2024
A14: Purchases (Fiscal Yr.) | C14: =SUM(D14:AI14) -> -208035.43 | D14: 21496 | E14: 17030 | K14: 40931 | N14: 36715 | O14: 3476.43 | U14: 5769.72 | V14: 3478.42 | W14: =-180025-26162-10000-8140-27605-27268-32986-22378-6017 -> -340581 | X14: 3649
C15: =SUM(D15:AI15) -> 128213.22 | D15: 7000 | E15: 39150 | L15: 7099.74 | O15: 22818.58 | P15: 42022.9 | U15: 4447 | W15: 5175 | X15: 500
C16: =SUM(D16:AI16) -> 1310855.8 | D16: 7000 | F16: 110120 | G16: 333836.86 | H16: 129867.83 | T16: 8980 | W16: 707551.14 | X16: 13500
C17: =SUM(D17:AI17) -> -125550.72 | W17: -125550.72
A18: PAMA AT 130 MOVED FROM MISC SCH | B18: 237 | C18: =SUM(D18:AI18) -> -596304.69 | F18: =-F16 -> -110120 | G18: =-G16 -> -333836.86 | H18: =-H16 -> -129867.83 | T18: =-T16 -> -8980 | X18: =-X16 -> -13500
C19: =SUM(D19:AI19) -> 1891949.5 | D19: 1500 | F19: 16200 | H19: 1140792.8 | I19: 250593.26 | J19: 69321.32 | L19: 363556.65 | M19: 5943.1 | O19: 7902.78 | P19: 13112.15 | Q19: 6211.75 | T19: 17315.75 | X19: -500
C20: =SUM(D20:AI20) -> 335016.55 | D20: 121548.03 | F20: 15500 | H20: 11150 | I20: 32500 | J20: 11122.78 | L20: 38909 | M20: 104286.74
C21: =SUM(D21:AI21) -> 244233.35 | D21: 37606.01 | F21: 43637.34 | H21: 116990 | I21: 5500 | L21: 20500 | P21: 17500 | Q21: 2500
C22: =SUM(D22:AI22) -> 254704.09 | D22: 19282.42 | F22: 20169.44 | I22: 11500 | J22: 153099.23 | P22: 50653
C23: =SUM(D23:AI23) -> 53756.54 | D23: 10000 | F23: 7500 | J23: 36256.54
C24: =SUM(D24:AI24) -> 19882.42 | D24: 2166 | J24: 3687.1 | S24: 11690.14 | T24: 2339.18
C25: =SUM(D25:AI25) -> 48723.87 | D25: 7476.83 | L25: 11500 | O25: 13352.04 | P25: 6395 | S25: 10000
C26: =SUM(D26:AI26) -> 41558.8 | D26: 8000 | O26: 8402.8 | S26: 25156
C27: =SUM(D27:AI27) -> 34600.79 | D27: 5997 | O27: 3350 | P27: 3483.79 | S27: 21770
C28: =SUM(D28:AI28) -> 299438.57 | D28: 97200 | F28: 182234.12 | Q28: 3072.86 | T28: 16931.59
C29: =SUM(D29:AI29) -> 43000 | D29: 28000 | S29: 15000
C30: =SUM(D30:AI30) -> 59749.1 | D30: 51205 | S30: 8544.1
C31: =SUM(D31:AI31) -> 18089.4 | D31: 14665.3 | S31: 3424.1
C32: =SUM(D32:AI32) -> 9360.26 | D32: 1250 | S32: 8110.26
C33: =SUM(D33:AI33) -> 350736.43 | D33: 339414.37 | S33: 11322.06
C34: =SUM(D34:AI34) -> 186786.15 | D34: 45000 | F34: 124932.61 | G34: 16853.54
C35: =SUM(D35:AI35) -> 4971.56 | D35: 4971.56
C36: =SUM(D36:AI36) -> 3420 | D36: 2920 | T36: 500
C37: =SUM(D37:AI37) -> 500 | T37: 500
C38: =SUM(D38:AI38) -> 37000 | T38: 37000
C39: =SUM(D39:AI39) -> 6580 | Y39: 6580
C40: =SUM(D40:AI40) -> 8500 | Y40: 8500
C41: =SUM(D41:AI41) -> 9108 | Y41: =9108 -> 9108
C42: =SUM(D42:AI42) -> 18370 | Y42: 18370
A43: Toshiba MPC 1" Angle Head | C43: =SUM(D43:AI43) -> 330 | Z43: 330
A44: Miss Plant 2 - 1490 General | C44: =SUM(D44:AI44) -> 149208.48 | Z44: 3900.68 | AG44: 120628.95 | AH44: 24678.85
A45: Miss - Weld shop | C45: =SUM(D45:AI45) -> 31992.45 | Z45: 31992.45
A46: Miss - 1495 | C46: =SUM(D46:AI46) -> 0
A47: CMM ROC Heat Install New 5 ton Carrier Roof top - Brampton | C47: =SUM(D47:AI47) -> 7155 | Z47: 7155
A48: Welding - Burl shop - 5284 | C48: =SUM(D48:AI48) -> 185374.06 | Z48: 128128.09 | AG48: 48741.93 | AH48: =1520+6984.04 -> 8504.04
A49: Arson Welding Positioner - Yoder Mach | C49: =SUM(D49:AI49) -> 6513.6 | Z49: 6513.6
A50: 30"x30"x30" Impala black Granite 5-face Master Square | C50: =SUM(D50:AI50) -> 14411 | Z50: 14411
A51: Pressure tester for Garder and Weir power frames | C51: =SUM(D51:AI51) -> 12775.68 | Z51: 12775.68
A52: Pressure tester Assembly - Job 200714 | C52: =SUM(D52:AI52) -> 3439.89 | Z52: 3439.89
A53: 14P Weld Automation Centre Job 200774 | C53: =SUM(D53:AI53) -> 37743.12 | Z53: 37743.12
A54: Bulington shop 2- 1601 | C54: =SUM(D54:AI54) -> 181062.52 | Z54: 44024 | AA54: 8600 | AG54: 31703.1 | AI54: 96735.42
A55: Bulington shop 2 Welding - 1601 | C55: =SUM(D55:AI55) -> 5989.69 | AI55: 5989.69
A56: Welding - Brampton | C56: =SUM(D56:AI56) -> 6820.2 | Z56: 6820.2
A57: Start up of two air compressors - Burl 1601 Corporate | C57: =SUM(D57:AI57) -> 5264 | Z57: 5264
A58: Retractable Enclosure | C58: =SUM(D58:AI58) -> 8495 | Z58: 8495
A59: TOS WHN100Q | C59: =SUM(D59:AI59) -> 29304.96 | Z59: 28800.49 | AA59: 504.47
C60: =SUM(D60:AI60) -> 650 | Z60: 650
A61: Munck 25 ton crane | C61: =SUM(D61:AI61) -> 11970.02 | AA61: 11970.02
A62: PML2000 Lift Magnet | C62: =SUM(D62:AI62) -> 3944.5 | AA62: 3944.5
A63: Magnet Lifter 5000 | C63: =SUM(D63:AI63) -> 4085.46 | AA63: 4085.46
A64: 100 hp Air compressor A/C GA75FF | C64: =SUM(D64:AI64) -> 3603.76 | AA64: 3603.76
A65: 8 pc Iron Floor Plates | C65: =SUM(D65:AI65) -> 30053.34 | AA65: 30053.34
A66: Mixing Room | C66: =SUM(D66:AI66) -> 1960 | AA66: 1960
A67: Misc Electrical - 1601 Corporate | C67: =SUM(D67:AI67) -> 22500 | AA67: 22500
A68: UNIDEN 4G 3G, LTE ENHANCEMENT KIT | C68: =SUM(D68:AI68) -> 3990 | AB68: 3990
A69: ANGELO PC | C69: =SUM(D69:AI69) -> 3126 | AB69: 3126
A70: 8 WELD STATIONS | C70: =SUM(D70:AI70) -> 21973 | AB70: 21973
A71: MICROSOFT SURFACE PRO4-12.3"-CORE i5 6300U-4GB RAM-128 GB SSD | C71: =SUM(D71:AI71) -> 1286.06 | AB71: 1286.06
A72: HP ZBOOK 15 G3 15.6" MOBILE WORKSTATION-Intel Core i7 | C72: =SUM(D72:AI72) -> 1959 | AB72: 1959
A73: ASUS 23.6" LCD MONITOR | C73: =SUM(D73:AI73) -> 398 | AB73: 398
A74: Laptop Msi GE62MVR | C74: =SUM(D74:AI74) -> 2299 | AC74: 2299
A75: Garret Programming Robot | C75: =SUM(D75:AI75) -> 4569.05 | AC75: 4569.05
A76: Kingston 16 GB Module | C76: =SUM(D76:AI76) -> 420 | AC76: 420
A77: Security System Installation | C77: =SUM(D77:AI77) -> 6918.8 | AC77: 6918.8
A78: Siris 3 10TB appliance | C78: =SUM(D78:AI78) -> 6278 | AC78: 6278
A79: Computer Asus Z270-P for Shadi | C79: =SUM(D79:AI79) -> 3280 | AC79: 3280
A80: Cat 34 Sweeper | C80: =SUM(D80:AI80) -> 4795 | AC80: 4795
A81: Octupuz-1 welding solution-software for robotic welding | C81: =SUM(D81:AI81) -> 19600 | AC81: 19600
A82: Intel i7-7700K Angelo'S Computer | C82: =SUM(D82:AI82) -> 3321.4 | AC82: 3321.4
A83: Programming PC-Luigi Caputo SN#705NTHM6V017 | C83: =SUM(D83:AI83) -> 2550.9 | AC83: 2550.9
A84: Styliner Super-Stinger portable marking system | C84: =SUM(D84:AI84) -> 9713.46 | AC84: 9713.46
A85: Work Station & Furniture 1490 | C85: =SUM(D85:AI85) -> 8945.88 | AC85: 8945.88
... A91: Time Clocks | C91: =SUM(D91:AI91) -> 5535 | AC91: 5535
A92: 2 DESKTOP COMPUTERS & MONIOTRS SPARES | C92: =SUM(D92:AI92) -> 4716.54 | AD92: 4716.54
A93: INSPECTION SOFTWARE | C93: =SUM(D93:AI93) -> 12949 | AD93: 12949
A94: FOLDERMILL | C94: =SUM(D94:AI94) -> 1550 | AD94: 1550
A95: Computer desktop -Paul Marcotte | C95: =SUM(D95:AI95) -> 1712.31 | AD95: 1712.31
A96: Computer desktop -Dejan Kovacevic | C96: =SUM(D96:AI96) -> 1136.48 | AD96: 1136.48
A97: spare PC for Mississauga Shop 2 | C97: =SUM(D97:AI97) -> 4943.55 | AD97: 4943.55
A98: PC for Paul Marcotte | C98: =SUM(D98:AI98) -> 2899.16 | AD98: 2899.16
A99: Computer desktop -Peter Vidmar PO#642897 | C99: =SUM(D99:AI99) -> 4057 | AD99: 4057
A100: Standard Programmer workstation | C100: =SUM(D100:AI100) -> 4057 | AD100: 4057
A101: Lenovo Desktop Computer (Tony Bosco) | C101: =SUM(D101:AI101) -> 2772 | AD101: 2772
A102: IM Pro Floating License | C102: =SUM(D102:AI102) -> 11039.67 | AE102: 11039.67
A103: Scale cable 3M | C103: =SUM(D103:AI103) -> 994.5 | AE103: 994.5
A104: Hot Water Pressure Cleaner | C104: =SUM(D104:AI104) -> 4153.63 | AE104: 4153.63
A105: FLUX RECOVERY SYSTEM | C105: =SUM(D105:AI105) -> 3990 | AE105: 3990
A106: SLOTS PARALLELS/FLAMMABLE CABINETS - APEX Auctions | C106: =SUM(D106:AI106) -> 25797.16 | AE106: 25797.16
A107: MESH CHAIR | C107: =SUM(D107:AI107) -> 692 | AF107: 692
A108: OCTOPUZ 2 - UPGRADE | C108: =SUM(D108:AI108) -> 6000 | AF108: 6000
A109: COMPUTER HARDWARE - MFG | C109: =SUM(D109:AI109) -> 137526.32 | AF109: 65795.92 | AH109: =65962.4+5768 -> 71730.4
...

Sheet 100
A1: ABS EQUIPMENT LEASING INC.
A2: Equipment List
A3: Source: Fixed Asset Summary
R4: Total | T4: Book
A5: Description | B5: Asset # | C5: Serial # | R5: Costs | S5: Depr. | T5: Value
A7: FORESTLINE #1 | B7: =+SUMMARY!A9 -> 100 | C7: 3051 | R7: =+C14 -> 1971035.5 | S7: =+-C49 -> 1971035.5 | T7: =+R7-S7 -> 0
A8: VECOMIL 563 5 AXIS CNC VERTICAL
A9: sn:3051
A11: Location: | B11: MISS | C11: 1495
A13: Purchased Year Ending | C13: Total | D13: 1994 | E13: 1995 | F13: 1996 | G13: 1997 | H13: 1998 | I13: 1999 | J13: 2000 | K13: 2001 | L13: 2002 | M13: 2003 | N13: 2004 | O13: =N13+1 -> 2005 | P13: =O13+1 -> 2006 | Q13: =P13+1 -> 2007 | R13: =Q13+1 -> 2008 | S13: =R13+1 -> 2009 | T13: =S13+1 -> 2010 | U13: =T13+1 -> 2011 | V13: =U13+1 -> 2012 | ... AH13: =AG13+1 -> 2024
A14: Purchases (Fiscal Yr.) | C14: =SUM(D14:AH14) -> 1971035.5 | D14: =+'Equip Review 032310'!G29 -> 0 | E14: =+'Equip Review 032310'!H29 -> 0 | F14: =+'Equip Review 032310'!I29 -> 0 | G14: =+'Equip Review 032310'!J29 -> 0 | H14: =+'Equip Review 032310'!K29 -> 0 | I14: =+'Equip Review 032310'!L29 -> 0 | J14: =+'Equip Review 032310'!M29 -> 0 | K14: =+'Equip Review 032310'!N29 -> 0 | ... M14: =+'Equip Review 032310'!P29 -> 0 | N14: =+'Equip Review 032310'!Q29/2 -> 235173.89 | O14: =+'Equip Review 032310'!R29/2 -> 36232.98 | P14: =+'Equip Review 032310'!S29/2 -> 48260.59 | Q14: =(+'Equip Review 032310'!T29)/2 -> 185222.12 | R14: =(+'Equip Review 032310'!U29+'Equip Review 032310'!V29)/2 -> 39565.04 | S14: =+'Equip Review 032310'!W29 -> 0 | U14: 33173 | V14: 440690.72 | W14: 37505.37 | X14: 902360.38 | Y14: 12851.4 | Z14: 0 | AA14: 0 | AB14: 0 | AC14: 0 | AD14: 0
A16: Depreciation | B16: 1994 | C16: =-SUM(D16:AH16) -> 0 | D16: =+D$14/7/2 -> 0
B17: =B16+1 -> 1995 | C17: =-SUM(D17:AH17) -> 0 | D17: =+D$14/7 -> 0 | E17: =+E$14/7/2 -> 0
B18: =B17+1 -> 1996 | C18: =-SUM(D18:AH18) -> 0 | D18: =+D17 -> 0 | E18: =+E$14/7 -> 0 | F18: =+F$14/7/2 -> 0
B19: =B18+1 -> 1997 | C19: =-SUM(D19:AH19) -> 0 | D19: =+D18 -> 0 | E19: =+E18 -> 0 | F19: =+F$14/7 -> 0 | G19: =+G$14/7/2 -> 0
B20: =B19+1 -> 1998 | C20: =-SUM(D20:AH20) -> 0 | D20: =+D19 -> 0 | E20: =+E19 -> 0 | F20: =+F19 -> 0 | G20: =+G$14/7 -> 0 | H20: =+H$14/7/2 -> 0
B21: =B20+1 -> 1999 | C21: =-SUM(D21:AH21) -> 0 | D21: =+D20 -> 0 | E21: =+E20 -> 0 | F21: =+F20 -> 0 | G21: =+G20 -> 0 | H21: =+H$14/7 -> 0 | I21: =+I$14/7/2 -> 0
B22: =B21+1 -> 2000 | C22: =-SUM(D22:AH22) -> 0 | D22: =+D21 -> 0 | E22: =+E21 -> 0 | F22: =+F21 -> 0 | G22: =+G21 -> 0 | H22: =+H21 -> 0 | I22: =+I$14/7 -> 0 | J22: =+J$14/7/2 -> 0
B23: =B22+1 -> 2001 | C23: =-SUM(D23:AH23) -> 0 | D23: =+D$14/7/2 -> 0 | E23: =+E22 -> 0 | F23: =+F22 -> 0 | G23: =+G22 -> 0 | H23: =+H22 -> 0 | I23: =+I22 -> 0 | J23: =+J$14/7 -> 0 | K23: =+K$14/7/2 -> 0
B24: =B23+1 -> 2002 | C24: =-SUM(D24:AH24) -> 0 | E24: =+E$14/7/2 -> 0 | F24: =+F23 -> 0 | G24: =+G23 -> 0 | H24: =+H23 -> 0 | I24: =+I23 -> 0 | J24: =+J23 -> 0 | K24: =+K$14/7 -> 0 | L24: =+L$14/7/2 -> 0
B25: =B24+1 -> 2003 | C25: =-SUM(D25:AH25) -> 0 | F25: =+F$14/7/2 -> 0 | G25: =+G24 -> 0 | H25: =+H24 -> 0 | I25: =+I24 -> 0 | J25: =+J24 -> 0 | K25: =+K24 -> 0 | L25: =+L$14/7 -> 0 | M25: =+M$14/7/2 -> 0
B26: =B25+1 -> 2004 | C26: =-SUM(D26:AH26) -> -16798.135 | G26: =+G$14/7/2 -> 0 | H26: =+H25 -> 0 | I26: =+I25 -> 0 | J26: =+J25 -> 0 | K26: =+K25 -> 0 | L26: =+L25 -> 0 | M26: =+M$14/7 -> 0 | N26: =+N$14/7/2 -> 16798.135
B27: =B26+1 -> 2005 | C27: =-SUM(D27:AH27) -> -36184.339 | H27: =+H$14/7/2 -> 0 | I27: =+I26 -> 0 | J27: =+J26 -> 0 | K27: =+K26 -> 0 | L27: =+L26 -> 0 | M27: =+M26 -> 0 | N27: =+N$14/7 -> 33596.269 | O27: =+O$14/7/2 -> 2588.07
B28: =B27+1 -> 2006 | C28: =-SUM(D28:AH28) -> -42219.594 | I28: =+I$14/7/2 -> 0 | J28: =+J27 -> 0 | K28: =+K27 -> 0 | L28: =+L27 -> 0 | M28: =+M27 -> 0 | N28: =+N27 -> 33596.269 | O28: =+O$14/7 -> 5176.14 | P28: =+P$14/7/2 -> 3447.185
B29: =B28+1 -> 2007 | C29: =-SUM(D29:AH29) -> -58896.931 | J29: =+J$14/7/2 -> 0 | K29: =+K28 -> 0 | L29: =+L28 -> 0 | M29: =+M28 -> 0 | N29: =+N28 -> 33596.269 | O29: =+O28 -> 5176.14 | P29: =+P$14/7 -> 6894.37 | Q29: =+Q$14/7/2 -> 13230.152
B30: =B29+1 -> 2008 | C30: =-SUM(D30:AH30) -> -74953.157 | K30: =+K$14/7/2 -> 0 | L30: =+L29 -> 0 | M30: =+M29 -> 0 | N30: =+N29 -> 33596.269 | O30: =+O29 -> 5176.14 | P30: =+P29 -> 6894.37 | Q30: =+Q$14/7 -> 26460.304 | R30: =+R$14/7/2 -> 2826.0743
B31: =B30+1 -> 2009 | C31: =-SUM(D31:AH31) -> -77779.231 | L31: =+L$14/7/2 -> 0 | M31: =+M30 -> 0 | N31: =+N30 -> 33596.269 | O31: =+O30 -> 5176.14 | P31: =+P30 -> 6894.37 | Q31: =+Q30 -> 26460.304 | R31: =+R$14/7 -> 5652.1486 | S31: =+S$14/7/2 -> 0
A32: To April 30th, 2010 | B32: =B31+1 -> 2010 | C32: =-SUM(D32:AH32) -> -77779.231 | M32: =+M$14/7/2 -> 0 | N32: =+N31 -> 33596.269 | O32: =+O31 -> 5176.14 | P32: =+P31 -> 6894.37 | Q32: =+Q31 -> 26460.304 | R32: =+R31 -> 5652.1486 | S32: =+S$14/7 -> 0 | T32: =+T$14/7/2 -> 0
B33: =B32+1 -> 2011 | C33: =-SUM(D33:AH33) -> -63350.597 | N33: =+N$14/7/2 -> 16798.135 | O33: =+O32 -> 5176.14 | P33: =+P32 -> 6894.37 | Q33: =+Q32 -> 26460.304 | R33: =+R32 -> 5652.1486 | S33: =+S32 -> 0 | T33: =+T$14/7 -> 0 | U33: =+U$14/7/2 -> 2369.5
B34: =B33+1 -> 2012 | C34: =-SUM(D34:AH34) -> -77811.801 | O34: =+O$14/7/2 -> 2588.07 | P34: =+P33 -> 6894.37 | Q34: =+Q33 -> 26460.304 | R34: =+R33 -> 5652.1486 | S34: =+S33 -> 0 | T34: =+T$14/7 -> 0 | U34: =+U$14/7 -> 4739 | V34: =+V$14/7/2 -> 31477.909
B35: =B34+1 -> 2013 | C35: =-SUM(D35:AH35) -> -105933.41 | P35: =P14/7/2 -> 3447.185 | Q35: =+Q34 -> 26460.304 | R35: =+R34 -> 5652.1486 | U35: =+U$14/7 -> 4739 | V35: =+V$14/7 -> 62955.817 | W35: =W14/7/2 -> 2678.955
B36: =B35+1 -> 2014 | C36: =-SUM(D36:AH36) -> -156389.34 | Q36: =Q14/7/2 -> 13230.152 | R36: =+R35 -> 5652.1486 | U36: =+U$14/7 -> 4739 | V36: =+V$14/7 -> 62955.817 | W36: =+W$14/7 -> 5357.91 | X36: =X14/7/2 -> 64454.313
B37: =B36+1 -> 2015 | C37: =-SUM(D37:AH37) -> -205705.38 | R37: =R14/7/2 -> 2826.0743 | U37: =+U$14/7 -> 4739 | V37: =+V$14/7 -> 62955.817 | W37: =+W$14/7 -> 5357.91 | X37: =$X$14/7 -> 128908.63 | Y37: =Y14/7/2 -> 917.95714
B38: =B37+1 -> 2016 | C38: =-SUM(D38:AH38) -> -203797.27 | U38: =+U$14/7 -> 4739 | V38: =+V$14/7 -> 62955.817 | W38: =+W$14/7 -> 5357.91 | X38: =$X$14/7 -> 128908.63 | Y38: =$Y$14/7 -> 1835.9143
B39: =B38+1 -> 2017 | C39: =-SUM(D39:AH39) -> -203797.27 | U39: =+U$14/7 -> 4739 | V39: =+V$14/7 -> 62955.817 | W39: =+W$14/7 -> 5357.91 | X39: =$X$14/7 -> 128908.63 | Y39: =$Y$14/7 -> 1835.9143
B40: =B39+1 -> 2018 | C40: =-SUM(D40:AH40) -> -201427.77 | U40: 2369.5 | V40: =+V$14/7 -> 62955.817 | W40: =+W$14/7 -> 5357.91 | X40: =$X$14/7 -> 128908.63 | Y40: =$Y$14/7 -> 1835.9143
B41: =B40+1 -> 2019 | C41: =-SUM(D41:AH41) -> -167580.36 | V41: =+V$14/7/2 -> 31477.909 | W41: =+W$14/7 -> 5357.91 | X41: =$X$14/7 -> 128908.63 | Y41: =$Y$14/7 -> 1835.9143 | AC41: =$AC$14/7/2 -> 0
B42: =B41+1 -> 2020 | C42: =-SUM(D42:AH42) -> -133423.49 | W42: =+W$14/7/2 -> 2678.955 | X42: =$X$14/7 -> 128908.63 | Y42: =$Y$14/7 -> 1835.9143 | AC42: =$AC$14/7 -> 0
B43: =B42+1 -> 2021 | C43: =-SUM(D43:AH43) -> -66290.227 | X43: =$X$14/7/2 -> 64454.313 | Y43: =$Y$14/7 -> 1835.9143
B44: =B43+1 -> 2022 | C44: =-SUM(D44:AH44) -> -917.95714 | Y44: =$Y$14/7/2 -> 917.95714
B45: =B44+1 -> 2023 | C45: =-SUM(D45:AH45) -> 0
B46: =B45+1 -> 2024 | C46: =-SUM(D46:AH46) -> 0
A49: ST | B49: =SUM(D49:AH49) -> 0 | C49: =SUM(C16:C48) -> -1971035.5 | D49: =-SUM(D16:D48)+D14 -> 0 | E49: =-SUM(E16:E48)+E14 -> 0 | F49: =-SUM(F16:F48)+F14 -> 0 | G49: =-SUM(G16:G48)+G14 -> 0 | H49: =-SUM(H16:H48)+H14 -> 0 | I49: =-SUM(I16:I48)+I14 -> 0 | J49: =-SUM(J16:J48)+J14 -> 0 | K49: =-SUM(K16:K48)+K14 -> 0 | ... AH49: =-SUM(AH16:AH48)+AH14 -> 0
A51: Net Book Value | C51: =+C14+C49 -> 0 | Y51: =+Y41+X41+W35 -> 133423.49
Y52: =+T7 -> 0
Y53: =+Y52-Y51 -> -133423.49
A54: COMMENTS | N54: =SUM(E32:E54) -> 0
A55: =225000+150000+44000 -> 419000 | B55: IN INVOICES FOUND IN 2003 BY MELISSA | V55: 2020 amortization | X55: =+X41+W49+Y41 -> 130744.54
A56: SPLIT COSTS EQUALLY UNTIL 2007 | V56: plus 5 months | X56: =64454/12*5+1836 -> 28691.833
X57: =SUM(X55:X56) -> 159436.37
V58: nbv sept 20 | X58: =201371-X57 -> 41934.627

Sheet 101
A1: ABS EQUIPMENT LEASING INC.
A2: Equipment List
A3: Source: F 2009 Fixed Asset Summary
R4: Total | T4: Book
A5: Description | B5: Asset # | C5: Serial # | R5: Costs | S5: Depr. | T5: Value
A6: =+SUMMARY!B10 -> MONTI FT 50 TG ( PURCH - ALESA MONTI) | B6: =+SUMMARY!A10 -> 101 | C6: =+SUMMARY!D10 -> 293/05.95
A7: =+SUMMARY!C10 -> FT50TG | R7: =+C14 -> 970993.94 | S7: =+-C48 -> 825242.42 | T7: =+R7-S7 -> 145751.52
A8: PURCH - ALESA MONTI
A11: Location: | B11: =+SUMMARY!F10 -> MISS | C11: C2
A13: Purchased Year Ending | C13: Total | D13: 1994 | E13: 1995 | F13: 1996 | G13: 1997 | H13: 1998 | I13: 1999 | J13: 2000 | K13: 2001 | L13: 2002 | M13: 2003 | N13: 2004 | O13: =N13+1 -> 2005 | P13: =O13+1 -> 2006 | Q13: =P13+1 -> 2007 | R13: =Q13+1 -> 2008 | S13: =R13+1 -> 2009 | T13: =S13+1 -> 2010 | U13: =T13+1 -> 2011 | V13: =U13+1 -> 2012 | ... AH13: =AG13+1 -> 2024
A14: Purchases (Fiscal Yr.) | C14: =SUM(D14:AH14) -> 970993.94 | F14: 661741.31 | AD14: 62123.56 | AE14: 247129.07
A15: =IF(+C14-'Equip Review 032310'!Y29=0,"ok","check") -> check
A16: Depreciation | B16: 1994 | C16: =-SUM(D16:AH16) -> 0 | D16: =+D$14/7/2 -> 0
B17: =B16+1 -> 1995 | C17: =-SUM(D17:AH17) -> 0 | D17: =+D$14/7 -> 0 | E17: =+E$14/7/2 -> 0
B18: =B17+1 -> 1996 | C18: =-SUM(D18:AH18) -> -47267.236 | D18: =+D17 -> 0 | E18: =+E$14/7 -> 0 | F18: =+F$14/7/2 -> 47267.236
B19: =B18+1 -> 1997 | C19: =-SUM(D19:AH19) -> -94534.473 | D19: =+D18 -> 0 | E19: =+E18 -> 0 | F19: =+F$14/7 -> 94534.473 | G19: =+G$14/7/2 -> 0
B20: =B19+1 -> 1998 | C20: =-SUM(D20:AH20) -> -94534.473 | D20: =+D19 -> 0 | E20: =+E19 -> 0 | F20: =+F19 -> 94534.473 | G20: =+G$14/7 -> 0 | H20: =+H$14/7/2 -> 0
B21: =B20+1 -> 1999 | C21: =-SUM(D21:AH21) -> -94534.473 | D21: =+D20 -> 0 | E21: =+E20 -> 0 | F21: =+F20 -> 94534.473 | G21: =+G20 -> 0 | H21: =+H$14/7 -> 0 | I21: =+I$14/7/2 -> 0
B22: =B21+1 -> 2000 | C22: =-SUM(D22:AH22) -> -94534.473 | D22: =+D21 -> 0 | E22: =+E21 -> 0 | F22: =+F21 -> 94534.473 | G22: =+G21 -> 0 | H22: =+H21 -> 0 | I22: =+I$14/7 -> 0 | J22: =+J$14/7/2 -> 0
B23: =B22+1 -> 2001 | C23: =-SUM(D23:AH23) -> -94534.473 | D23: =+D$14/7/2 -> 0 | E23: =+E22 -> 0 | F23: =+F22 -> 94534.473 | G23: =+G22 -> 0 | H23: =+H22 -> 0 | I23: =+I22 -> 0 | J23: =+J$14/7 -> 0 | K23: =+K$14/7/2 -> 0
B24: =B23+1 -> 2002 | C24: =-SUM(D24:AH24) -> -94534.473 | E24: =+E$14/7/2 -> 0 | F24: =+F23 -> 94534.473 | G24: =+G23 -> 0 | H24: =+H23 -> 0 | I24: =+I23 -> 0 | J24: =+J23 -> 0 | K24: =+K$14/7 -> 0 | L24: =+L$14/7/2 -> 0
B25: =B24+1 -> 2003 | C25: =-SUM(D25:AH25) -> -47267.236 | F25: =+F$14/7/2 -> 47267.236 | G25: =+G24 -> 0 | H25: =+H24 -> 0 | I25: =+I24 -> 0 | J25: =+J24 -> 0 | K25: =+K24 -> 0 | L25: =+L$14/7 -> 0 | M25: =+M$14/7/2 -> 0
B26: =B25+1 -> 2004 | C26: =-SUM(D26:AH26) -> 0 | G26: =+G$14/7/2 -> 0 | H26: =+H25 -> 0 | I26: =+I25 -> 0 | J26: =+J25 -> 0 | K26: =+K25 -> 0 | L26: =+L25 -> 0 | M26: =+M$14/7 -> 0 | N26: =+N$14/7/2 -> 0
B27: =B26+1 -> 2005 | C27: =-SUM(D27:AH27) -> 0 | H27: =+H$14/7/2 -> 0 | I27: =+I26 -> 0 | J27: =+J26 -> 0 | K27: =+K26 -> 0 | L27: =+L26 -> 0 | M27: =+M26 -> 0 | N27: =+N$14/7 -> 0 | O27: =+O$14/7/2 -> 0
B28: =B27+1 -> 2006 | C28: =-SUM(D28:AH28) -> 0 | I28: =+I$14/7/2 -> 0 | J28: =+J27 -> 0 | K28: =+K27 -> 0 | L28: =+L27 -> 0 | M28: =+M27 -> 0 | N28: =+N27 -> 0 | O28: =+O$14/7 -> 0 | P28: =+P$14/7/2 -> 0
B29: =B28+1 -> 2007 | C29: =-SUM(D29:AH29) -> 0 | J29: =+J$14/7/2 -> 0 | K29: =+K28 -> 0 | L29: =+L28 -> 0 | M29: =+M28 -> 0 | N29: =+N28 -> 0 | O29: =+O28 -> 0 | P29: =+P$14/7 -> 0 | Q29: =+Q$14/7/2 -> 0
B30: =B29+1 -> 2008 | C30: =-SUM(D30:AH30) -> 0 | K30: =+K$14/7/2 -> 0 | L30: =+L29 -> 0 | M30: =+M29 -> 0 | N30: =+N29 -> 0 | O30: =+O29 -> 0 | P30: =+P29 -> 0 | Q30: =+Q$14/7 -> 0 | R30: =+R$14/7/2 -> 0
B31: =B30+1 -> 2009 | C31: =-SUM(D31:AH31) -> 0 | L31: =+L$14/7/2 -> 0 | M31: =+M30 -> 0 | N31: =+N30 -> 0 | O31: =+O30 -> 0 | P31: =+P30 -> 0 | Q31: =+Q30 -> 0 | R31: =+R$14/7 -> 0 | S31: =+S$14/7/2 -> 0
A32: To April 30th, 2010 | B32: =B31+1 -> 2010 | C32: =-SUM(D32:AH32) -> 0 | M32: =+M$14/7/2 -> 0 | N32: =+N31 -> 0 | O32: =+O31 -> 0 | P32: =+P31 -> 0 | Q32: =+Q31 -> 0 | R32: =+R31 -> 0 | S32: =+S$14/7 -> 0 | T32: =+T$14/7/2 -> 0
B33: =B32+1 -> 2011 | C33: =-SUM(D33:AH33) -> 0 | N33: =+N$14/7/2 -> 0 | O33: =+O32 -> 0 | P33: =+P32 -> 0 | Q33: =+Q32 -> 0 | R33: =+R32 -> 0 | S33: =+S32 -> 0 | T33: =+T$14/7 -> 0 | U33: =+U$14/7/2 -> 0
B34: =B33+1 -> 2012 | C34: =-SUM(D34:AH34) -> 0 | Q34: =+Q33 -> 0 | R34: =+R33 -> 0 | S34: =+S33 -> 0 | T34: =+T$14/7 -> 0 | U34: =+U$14/7 -> 0 | V34: =+V$14/7/2 -> 0
B35: =B34+1 -> 2013 | C35: =-SUM(D35:AH35) -> 0
B36: =B35+1 -> 2014 | C36: =-SUM(D36:AH36) -> 0
B37: =B36+1 -> 2015 | C37: =-SUM(D37:AH37) -> 0
B38: =B37+1 -> 2016 | C38: =-SUM(D38:AH38) -> 0
B39: =B38+1 -> 2017 | C39: =-SUM(D39:AH39) -> 0
B40: =B39+1 -> 2018 | C40: =-SUM(D40:AH40) -> 0
B41: =B40+1 -> 2019 | C41: =-SUM(D41:AH41) -> 0
B42: =B41+1 -> 2020 | C42: =-SUM(D42:AH42) -> -4437.3971 | AD42: =$AD$14/7/2 -> 4437.3971
B43: =B42+1 -> 2021 | C43: =-SUM(D43:AH43) -> -26526.871 | AD43: =$AD$14/7 -> 8874.7943 | AE43: =$AE$14/7/2 -> 17652.076
B44: =B43+1 -> 2022 | C44: =-SUM(D44:AH44) -> -44178.947 | AD44: =$AD$14/7 -> 8874.7943 | AE44: =$AE$14/7 -> 35304.153
B45: =B44+1 -> 2023 | C45: =-SUM(D45:AH45) -> -44178.947 | AD45: =$AD$14/7 -> 8874.7943 | AE45: =$AE$14/7 -> 35304.153
B46: =B45+1 -> 2024 | C46: =-SUM(D46:AH46) -> -44178.947 | AD46: =$AD$14/7 -> 8874.7943 | AE46: =$AE$14/7 -> 35304.153
A48: ST | B48: =SUM(D48:AH48) -> 145751.52 | C48: =SUM(C16:C47) -> -825242.42 | D48: =-SUM(D16:D47)+D14 -> 0 | E48: =-SUM(E16:E47)+E14 -> 0 | F48: =-SUM(F16:F47)+F14 -> 0 | G48: =-SUM(G16:G47)+G14 -> 0 | H48: =-SUM(H16:H47)+H14 -> 0 | I48: =-SUM(I16:I47)+I14 -> 0 | J48: =-SUM(J16:J47)+J14 -> 0 | K48: =-SUM(K16:K47)+K14 -> 0 | ... AE48: =-SUM(AE16:AE47)+AE14 -> 123564.54
A50: Net Book Value | C50: =+C14+C48 -> 145751.52
N53: =SUM(E32:E53) -> 0

Sheet 102
A1: ABS EQUIPMENT LEASING INC.
A2: Equipment List
A3: Source: F 2009 Fixed Asset Summary
R4: Total | T4: Book
A5: Description | B5: Asset # | C5: Serial # | R5: Costs | S5: Depr. | T5: Value
A6: FORESTLINE #2 | B6: 102
A7: FORESTLINE RETROFIT | C7: 3052 | R7: =+C14 -> 560665.7 | S7: =+-C46 -> 560665.7 | T7: =+R7-S7 -> 0
A11: Location: | B11: HAM
A13: Purchased Year Ending | C13: Total | D13: 1994 | E13: 1995 | F13: 1996 | G13: 1997 | H13: 1998 | I13: 1999 | J13: 2000 | K13: 2001 | L13: 2002 | M13: 2003 | N13: 2004 | O13: 2005 | P13: 2006 | Q13: 2007 | R13: 2008 | S13: 2009 | T13: 2010 | U13: 2011 | V13: 2012 | W13: 2013 | X13: 2014 | Y13: 2015 | Z13: 2016 | AA13: 2017 | AB13: 2018 | AC13: 2019
A14: Purchases (Fiscal Yr.) | C14: =SUM(D14:Y14) -> 560665.7 | I14: 0 | L14: 0 | N14: ='100'!N14 -> 235173.89 | O14: ='100'!O14 -> 36232.98 | P14: ='100'!P14 -> 48260.59 | Q14: ='100'!Q14 -> 185222.12 | R14: ='100'!R14 -> 39565.04 | Y14: 16211.08
A15: =IF(+C14-'Equip Review 032310'!Y29=0,"ok","check") -> check
A16: Depreciation | B16: 1994 | C16: =-SUM(D16:Y16) -> 0 | D16: =+D$14/7/2 -> 0
B17: 1995 | C17: =-SUM(D17:Y17) -> 0 | D17: =+D$14/7 -> 0 | E17: =+E$14/7/2 -> 0
B18: 1996 | C18: =-SUM(D18:Y18) -> 0 | D18: =+D17 -> 0 | E18: =+E$14/7 -> 0 | F18: =+F$14/7/2 -> 0
B19: 1997 | C19: =-SUM(D19:Y19) -> 0 | D19: =+D18 -> 0 | E19: =+E18 -> 0 | F19: =+F$14/7 -> 0 | G19: =+G$14/7/2 -> 0
B20: 1998 | C20: =-SUM(D20:Y20) -> 0 | D20: =+D19 -> 0 | E20: =+E19 -> 0 | F20: =+F19 -> 0 | G20: =+G$14/7 -> 0 | H20: =+H$14/7/2 -> 0
B21: 1999 | C21: =-SUM(D21:Y21) -> 0 | D21: =+D20 -> 0 | E21: =+E20 -> 0 | F21: =+F20 -> 0 | G21: =+G20 -> 0 | H21: =+H$14/7 -> 0 | I21: =+I$14/7/2 -> 0
B22: 2000 | C22: =-SUM(D22:Y22) -> 0 | D22: =+D21 -> 0 | E22: =+E21 -> 0 | F22: =+F21 -> 0 | G22: =+G21 -> 0 | H22: =+H21 -> 0 | I22: =+I$14/7 -> 0 | J22: =+J$14/7/2 -> 0
B23: 2001 | C23: =-SUM(D23:Y23) -> 0 | D23: =+D$14/7/2 -> 0 | E23: =+E22 -> 0 | F23: =+F22 -> 0 | G23: =+G22 -> 0 | H23: =+H22 -> 0 | I23: =+I22 -> 0 | J23: =+J$14/7 -> 0 | K23: =+K$14/7/2 -> 0
B24: 2002 | C24: =-SUM(D24:Y24) -> 0 | E24: =+E$14/7/2 -> 0 | F24: =+F23 -> 0 | G24: =+G23 -> 0 | H24: =+H23 -> 0 | I24: =+I23 -> 0 | J24: =+J23 -> 0 | K24: =+K$14/7 -> 0 | L24: =+L$14/7/2 -> 0
B25: 2003 | C25: =-SUM(D25:Y25) -> 0 | F25: =+F$14/7/2 -> 0 | G25: =+G24 -> 0 | H25: =+H24 -> 0 | I25: =+I24 -> 0 | J25: =+J24 -> 0 | K25: =+K24 -> 0 | L25: =+L$14/7 -> 0 | M25: =+M$14/7/2 -> 0
B26: 2004 | C26: =-SUM(D26:Y26) -> -16798.135 | G26: =+G$14/7/2 -> 0 | H26: =+H25 -> 0 | I26: =+I25 -> 0 | J26: =+J25 -> 0 | K26: =+K25 -> 0 | L26: =+L25 -> 0 | M26: =+M$14/7 -> 0 | N26: =+N$14/7/2 -> 16798.135
B27: 2005 | C27: =-SUM(D27:Y27) -> -36184.339 | H27: =+H$14/7/2 -> 0 | I27: =+I26 -> 0 | J27: =+J26 -> 0 | K27: =+K26 -> 0 | L27: =+L26 -> 0 | M27: =+M26 -> 0 | N27: =+N$14/7 -> 33596.269 | O27: =+O$14/7/2 -> 2588.07
B28: 2006 | C28: =-SUM(D28:Y28) -> -42219.594 | I28: =+I$14/7/2 -> 0 | J28: =+J27 -> 0 | K28: =+K27 -> 0 | L28: =+L27 -> 0 | M28: =+M27 -> 0 | N28: =+N27 -> 33596.269 | O28: =+O$14/7 -> 5176.14 | P28: =+P$14/7/2 -> 3447.185
B29: 2007 | C29: =-SUM(D29:Y29) -> -58896.931 | J29: =+J$14/7/2 -> 0 | K29: =+K28 -> 0 | L29: =+L28 -> 0 | M29: =+M28 -> 0 | N29: =+N28 -> 33596.269 | O29: =+O28 -> 5176.14 | P29: =+P$14/7 -> 6894.37 | Q29: =+Q$14/7/2 -> 13230.152
B30: 2008 | C30: =-SUM(D30:Y30) -> -74953.157 | K30: =+K$14/7/2 -> 0 | L30: =+L29 -> 0 | M30: =+M29 -> 0 | N30: =+N29 -> 33596.269 | O30: =+O29 -> 5176.14 | P30: =+P29 -> 6894.37 | Q30: =+Q$14/7 -> 26460.304 | R30: =+R$14/7/2 -> 2826.0743
B31: 2009 | C31: =-SUM(D31:Y31) -> -77779.231 | L31: =+L$14/7/2 -> 0 | M31: =+M30 -> 0 | N31: =+N30 -> 33596.269 | O31: =+O30 -> 5176.14 | P31: =+P30 -> 6894.37 | Q31: =+Q30 -> 26460.304 | R31: =+R$14/7 -> 5652.1486 | S31: =+S$14/7/2 -> 0
A32: To April 30th, 2010 | B32: 2010 | C32: =-SUM(D32:Y32) -> -77779.231 | M32: =+M$14/7/2 -> 0 | N32: =+N31 -> 33596.269 | O32: =+O31 -> 5176.14 | P32: =+P31 -> 6894.37 | Q32: =+Q31 -> 26460.304 | R32: =+R31 -> 5652.1486 | S32: =+S$14/7 -> 0 | T32: =+T$14/7/2 -> 0
B33: 2011 | C33: =-SUM(D33:Y33) -> -60981.097 | N33: =+N$14/7/2 -> 16798.135 | O33: =+O32 -> 5176.14 | P33: =+P32 -> 6894.37 | Q33: =+Q32 -> 26460.304 | R33: =+R32 -> 5652.1486 | S33: =+S32 -> 0 | T33: =+T$14/7 -> 0 | U33: =+U$14/7/2 -> 0
B34: 2012 | C34: =-SUM(D34:Y34) -> -41594.892 | O34: =O14/7/2 -> 2588.07 | P34: =P14/7 -> 6894.37 | Q34: =+Q33 -> 26460.304 | R34: =+R33 -> 5652.1486 | S34: =+S33 -> 0 | T34: =+T$14/7 -> 0 | U34: =+U$14/7 -> 0 | V34: =+V$14/7/2 -> 0
B35: 2013 | C35: =-SUM(D35:Y35) -> -35559.637 | P35: =P14/7/2 -> 3447.185 | Q35: =Q14/7 -> 26460.304 | R35: =R14/7 -> 5652.1486 | W35: =W14/7/2 -> 0
B36: 2014 | C36: =-SUM(D36:Y36) -> -18882.3 | Q36: =Q14/7/2 -> 13230.152 | R36: =R14/7 -> 5652.1486 | W36: =W14/7 -> 0 | X36: =X14/7 -> 0
B37: 2015 | C37: =-SUM(D37:Y37) -> -3984.0086 | R37: =R14/7/2 -> 2826.0743 | Y37: =$Y$14/7/2 -> 1157.9343
B38: 2016 | C38: =-SUM(D38:Y38) -> -2315.8686 | Y38: =$Y$14/7 -> 2315.8686
B39: 2017 | C39: =-SUM(D39:Y39) -> -2315.8686 | Y39: =$Y$14/7 -> 2315.8686
B40: 2018 | C40: =-SUM(N40:AB40) -> -2315.8686 | Y40: =$Y$14/7 -> 2315.8686
B41: 2019 | C41: =-SUM(N41:AB41) -> -2315.8686 | Y41: =$Y$14/7 -> 2315.8686
B42: 2020 | C42: =-SUM(N42:AB42) -> -2315.8686 | Y42: =$Y$14/7 -> 2315.8686
B43: 2021 | C43: =-SUM(N43:AB43) -> -2315.8686 | Y43: =$Y$14/7 -> 2315.8686
B44: 2022 | C44: =-SUM(N44:AB44) -> -1157.9343 | Y44: =$Y$14/7/2 -> 1157.9343
A46: ST | B46: =SUM(D46:Y46) -> 0 | C46: =SUM(C16:C45) -> -560665.7 | D46: =-SUM(D16:D45)+D14 -> 0 | E46: =-SUM(E16:E45)+E14 -> 0 | F46: =-SUM(F16:F45)+F14 -> 0 | G46: =-SUM(G16:G45)+G14 -> 0 | H46: =-SUM(H16:H45)+H14 -> 0 | I46: =-SUM(I16:I45)+I14 -> 0 | J46: =-SUM(J16:J45)+J14 -> 0 | K46: =-SUM(K16:K45)+K14 -> 0 | ... AC46: =-SUM(AC16:AC45)+AC14 -> 0
A48: Net Book Value | C48: =+C14+C46 -> 0
A50: comments
N51: =SUM(E32:E51) -> 0
A52: SEE 100, SPLIT COST EQUALLY UNTIL 2008
A53: INACTIVE, IN STORAGE

Sheet 103
A1: ABS EQUIPMENT LEASING INC.
A2: Equipment List
A3: Source: F 2009 Fixed Asset Summary
R4: Total | T4: Book
A5: Description | B5: Asset # | C5: Serial # | R5: Costs | S5: Depr. | T5: Value
A6: =+SUMMARY!B12 -> PAMA SPEEDRAM # 3 INCL TBL | B6: =+SUMMARY!A12 -> 103 | C6: =+SUMMARY!D12 -> 33C-7168
A7: =+SUMMARY!C12 -> BONETTI RETROFIT | R7: =+C14 -> 3824420.5 | S7: =+-C48 -> 3802179.5 | T7: =+R7-S7 -> 22241.024
A11: Location: | B11: =+SUMMARY!F12 -> BURL 1 | C11: A3
A13: Purchased Year Ending | C13: Total | D13: 1994 | E13: =D13+1 -> 1995 | F13: =E13+1 -> 1996 | G13: =F13+1 -> 1997 | H13: =G13+1 -> 1998 | I13: =H13+1 -> 1999 | J13: =I13+1 -> 2000 | K13: =J13+1 -> 2001 | L13: =K13+1 -> 2002 | ... AH13: =AG13+1 -> 2024
A14: Purchases (Fiscal Yr.) | C14: =SUM(D14:AH14) -> 3824420.5 | I14: 1284796.8 | L14: 11829.56 | O14: 10401.89 | W14: 77000 | Z14: =2412497.35+3943.04 -> 2416440.4 | AH14: 23951.88
A15: =IF(+C14-'Equip Review 032310'!Y29=0,"ok","check") -> check
A16: Depreciation | B16: 1994 | C16: =-SUM(D16:AH16) -> 0 | D16: =+D$14/7/2 -> 0
B17: =B16+1 -> 1995 | C17: =-SUM(D17:AH17) -> 0 | D17: =+D$14/7 -> 0 | E17: =+E$14/7/2 -> 0
B18: =B17+1 -> 1996 | C18: =-SUM(D18:AH18) -> 0 | D18: =+D17 -> 0 | E18: =+E$14/7 -> 0 | F18: =+F$14/7/2 -> 0
B19: =B18+1 -> 1997 | C19: =-SUM(D19:AH19) -> 0 | D19: =+D18 -> 0 | E19: =+E18 -> 0 | F19: =+F$14/7 -> 0 | G19: =+G$14/7/2 -> 0
B20: =B19+1 -> 1998 | C20: =-SUM(D20:AH20) -> 0 | D20: =+D19 -> 0 | E20: =+E19 -> 0 | F20: =+F19 -> 0 | G20: =+G$14/7 -> 0 | H20: =+H$14/7/2 -> 0
B21: =B20+1 -> 1999 | C21: =-SUM(D21:AH21) -> -91771.202 | D21: =+D20 -> 0 | E21: =+E20 -> 0 | F21: =+F20 -> 0 | G21: =+G20 -> 0 | H21: =+H$14/7 -> 0 | I21: =+I$14/7/2 -> 91771.202
B22: =B21+1 -> 2000 | C22: =-SUM(D22:AH22) -> -183542.4 | D22: =+D21 -> 0 | E22: =+E21 -> 0 | F22: =+F21 -> 0 | G22: =+G21 -> 0 | H22: =+H21 -> 0 | I22: =+I$14/7 -> 183542.4 | J22: =+J$14/7/2 -> 0
B23: =B22+1 -> 2001 | C23: =-SUM(D23:AH23) -> -183542.4 | D23: =+D$14/7/2 -> 0 | E23: =+E22 -> 0 | F23: =+F22 -> 0 | G23: =+G22 -> 0 | H23: =+H22 -> 0 | I23: =+I22 -> 183542.4 | J23: =+J$14/7 -> 0 | K23: =+K$14/7/2 -> 0
B24: =B23+1 -> 2002 | C24: =-SUM(D24:AH24) -> -184387.37 | E24: =+E$14/7/2 -> 0 | F24: =+F23 -> 0 | G24: =+G23 -> 0 | H24: =+H23 -> 0 | I24: =+I23 -> 183542.4 | J24: =+J23 -> 0 | K24: =+K$14/7 -> 0 | L24: =+L$14/7/2 -> 844.96857
B25: =B24+1 -> 2003 | C25: =-SUM(D25:AH25) -> -185232.34 | F25: =+F$14/7/2 -> 0 | G25: =+G24 -> 0 | H25: =+H24 -> 0 | I25: =+I24 -> 183542.4 | J25: =+J24 -> 0 | K25: =+K24 -> 0 | L25: =+L$14/7 -> 1689.9371 | M25: =+M$14/7/2 -> 0
B26: =B25+1 -> 2004 | C26: =-SUM(D26:AH26) -> -185232.34 | G26: =+G$14/7/2 -> 0 | H26: =+H25 -> 0 | I26: =+I25 -> 183542.4 | J26: =+J25 -> 0 | K26: =+K25 -> 0 | L26: =+L25 -> 1689.9371 | M26: =+M$14/7 -> 0 | N26: =+N$14/7/2 -> 0
B27: =B26+1 -> 2005 | C27: =-SUM(D27:AH27) -> -185975.33 | H27: =+H$14/7/2 -> 0 | I27: =+I26 -> 183542.4 | J27: =+J26 -> 0 | K27: =+K26 -> 0 | L27: =+L26 -> 1689.9371 | M27: =+M26 -> 0 | N27: =+N$14/7 -> 0 | O27: =+O$14/7/2 -> 742.99214
B28: =B27+1 -> 2006 | C28: =-SUM(D28:AH28) -> -94947.124 | I28: =+I$14/7/2 -> 91771.202 | J28: =+J27 -> 0 | K28: =+K27 -> 0 | L28: =+L27 -> 1689.9371 | M28: =+M27 -> 0 | N28: =+N27 -> 0 | O28: =+O$14/7 -> 1485.9843 | P28: =+P$14/7/2 -> 0
B29: =B28+1 -> 2007 | C29: =-SUM(D29:AH29) -> -3175.9214 | J29: =+J$14/7/2 -> 0 | K29: =+K28 -> 0 | L29: =+L28 -> 1689.9371 | M29: =+M28 -> 0 | N29: =+N28 -> 0 | O29: =+O28 -> 1485.9843 | P29: =+P$14/7 -> 0 | Q29: =+Q$14/7/2 -> 0
B30: =B29+1 -> 2008 | C30: =-SUM(D30:AH30) -> -3175.9214 | K30: =+K$14/7/2 -> 0 | L30: =+L29 -> 1689.9371 | M30: =+M29 -> 0 | N30: =+N29 -> 0 | O30: =+O29 -> 1485.9843 | P30: =+P29 -> 0 | Q30: =+Q$14/7 -> 0 | R30: =+R$14/7/2 -> 0
B31: =B30+1 -> 2009 | C31: =-SUM(D31:AH31) -> -2330.9529 | L31: =+L$14/7/2 -> 844.96857 | M31: =+M30 -> 0 | N31: =+N30 -> 0 | O31: =+O30 -> 1485.9843 | P31: =+P30 -> 0 | Q31: =+Q30 -> 0 | R31: =+R$14/7 -> 0 | S31: =+S$14/7/2 -> 0
A32: To April 30th, 2010 | B32: =B31+1 -> 2010 | C32: =-SUM(D32:AH32) -> -1485.9843 | M32: =+M$14/7/2 -> 0 | N32: =+N31 -> 0 | O32: =+O31 -> 1485.9843 | P32: =+P31 -> 0 | Q32: =+Q31 -> 0 | R32: =+R31 -> 0 | S32: =+S$14/7 -> 0 | T32: =+T$14/7/2 -> 0
B33: =B32+1 -> 2011 | C33: =-SUM(D33:AH33) -> -1485.9843 | N33: =+N$14/7/2 -> 0 | O33: =+O32 -> 1485.9843 | P33: =+P32 -> 0 | Q33: =+Q32 -> 0 | R33: =+R32 -> 0 | S33: =+S32 -> 0 | T33: =+T$14/7 -> 0 | U33: =+U$14/7/2 -> 0
B34: =B33+1 -> 2012 | C34: =-SUM(D34:AH34) -> -743 | O34: 743 | Q34: =+Q33 -> 0 | R34: =+R33 -> 0 | S34: =+S33 -> 0 | T34: =+T$14/7 -> 0 | U34: =+U$14/7 -> 0 | V34: =+V$14/7/2 -> 0
B35: =B34+1 -> 2013 | C35: =-SUM(D35:AH35) -> -5500 | W35: =$W$14/7/2 -> 5500
B36: =B35+1 -> 2014 | C36: =-SUM(D36:AH36) -> -11000 | W36: =$W$14/7 -> 11000
B37: =B36+1 -> 2015 | C37: =-SUM(D37:AH37) -> -11000 | W37: =$W$14/7 -> 11000 | Y37: =Y14/7/2 -> 0
B38: =B37+1 -> 2016 | C38: =-SUM(D38:AH38) -> -183602.89 | W38: =$W$14/7 -> 11000 | Z38: =$Z$14/7/2 -> 172602.89
B39: =B38+1 -> 2017 | C39: =-SUM(D39:AH39) -> -356205.77 | W39: =$W$14/7 -> 11000 | Z39: =$Z$14/7 -> 345205.77
B40: =B39+1 -> 2018 | C40: =-SUM(D40:AH40) -> -356205.77 | W40: =$W$14/7 -> 11000 | Z40: =$Z$14/7 -> 345205.77
B41: =B40+1 -> 2019 | C41: =-SUM(D41:AH41) -> -356205.77 | W41: =$W$14/7 -> 11000 | Z41: =$Z$14/7 -> 345205.77
B42: =B41+1 -> 2020 | C42: =-SUM(D42:AH42) -> -350705.77 | W42: =$W$14/7/2 -> 5500 | Z42: =$Z$14/7 -> 345205.77
B43: =B42+1 -> 2021 | C43: =-SUM(D43:AH43) -> -345205.77 | Z43: =$Z$14/7 -> 345205.77
B44: =B43+1 -> 2022 | C44: =-SUM(D44:AH44) -> -345205.77 | Z44: =$Z$14/7 -> 345205.77
B45: =B44+1 -> 2023 | C45: =-SUM(D45:AH45) -> -172602.89 | Z45: =Z14/7/2 -> 172602.89
B46: =B45+1 -> 2024 | C46: =-SUM(D46:AH46) -> -1710.8486 | AH46: =AH14/7/2 -> 1710.8486
A48: ST | B48: =SUM(D48:AH48) -> 22241.024 | C48: =SUM(C16:C46) -> -3802179.5 | D48: =-SUM(D16:D47)+D14 -> 0 | E48: =-SUM(E16:E47)+E14 -> 0 | F48: =-SUM(F16:F47)+F14 -> 0 | G48: =-SUM(G16:G47)+G14 -> 0 | H48: =-SUM(H16:H47)+H14 -> 0 | I48: =-SUM(I16:I47)+I14 -> 0 | J48: =-SUM(J16:J47)+J14 -> 0 | K48: =-SUM(K16:K47)+K14 -> 0 | ... AH48: =-SUM(AH16:AH47)+AH14 -> 22241.031
A50: Net Book Value | C50: =+C14+C48 -> 22241.024
A53: comments | N53: =SUM(E32:E53) -> 0
A54: additions of $182181.82 transferred to 1115008 as machine at Bonetti for retrofit

Sheet 104
A1: ABS EQUIPMENT LEASING INC.
A2: Equipment List
A3: Source: F 2009 Fixed Asset Summary
R4: Total | T4: Book
A5: Description | B5: Asset # | C5: Serial # | R5: Costs | S5: Depr. | T5: Value
A6: =+SUMMARY!B13 -> PAMA CENTER 110 PO 113295 | B6: =+SUMMARY!A13 -> 104 | C6: =+SUMMARY!D13 -> 7357
A7: =+SUMMARY!C13 -> 5 AXIS | R7: =+C14 -> 2069204.1 | S7: =+-C49 -> 2069204.1 | T7: =+R7-S7 -> 0
A11: Location: | B11: =+SUMMARY!F13 -> JL | C11: C3
A13: Purchased Year Ending | C13: Total | D13: 1994 | E13: 1995 | F13: 1996 | G13: 1997 | H13: 1998 | I13: 1999 | J13: 2000 | K13: 2001 | L13: 2002 | M13: 2003 | N13: 2004 | O13: =N13+1 -> 2005 | P13: =O13+1 -> 2006 | Q13: =P13+1 -> 2007 | R13: =Q13+1 -> 2008 | S13: =R13+1 -> 2009 | T13: =S13+1 -> 2010 | U13: =T13+1 -> 2011 | V13: =U13+1 -> 2012 | ... AH13: =AG13+1 -> 2024
A14: Purchases (Fiscal Yr.) | C14: =SUM(D14:AH14) -> 2069204.1 | D14: 326318.29 | E14: 79857.13 | F14: 177640.13 | J14: 70800 | K14: 129218.27 | X14: 0 | Y14: =426317.04+940375.06 -> 1366692.1 | AA14: -81321.82
A15: =IF(+C14-'Equip Review 032310'!Y29=0,"ok","check") -> check
A16: Depreciation | B16: 1994 | C16: =-SUM(D16:AH16) -> -23308.449 | D16: =+D$14/7/2 -> 23308.449
B17: =B16+1 -> 1995 | C17: =-SUM(D17:AH17) -> -52320.979 | D17: =+D$14/7 -> 46616.899 | E17: =+E$14/7/2 -> 5704.0807
B18: =B17+1 -> 1996 | C18: =-SUM(D18:AH18) -> -70713.641 | D18: =+D17 -> 46616.899 | E18: =+E$14/7 -> 11408.161 | F18: =+F$14/7/2 -> 12688.581
B19: =B18+1 -> 1997 | C19: =-SUM(D19:AH19) -> -83402.221 | D19: =+D18 -> 46616.899 | E19: =+E18 -> 11408.161 | F19: =+F$14/7 -> 25377.161 | G19: =+G$14/7/2 -> 0
B20: =B19+1 -> 1998 | C20: =-SUM(D20:AH20) -> -83402.221 | D20: =+D19 -> 46616.899 | E20: =+E19 -> 11408.161 | F20: =+F19 -> 25377.161 | G20: =+G$14/7 -> 0 | H20: =+H$14/7/2 -> 0
B21: =B20+1 -> 1999 | C21: =-SUM(D21:AH21) -> -83402.221 | D21: =+D20 -> 46616.899 | E21: =+E20 -> 11408.161 | F21: =+F20 -> 25377.161 | G21: =+G20 -> 0 | H21: =+H$14/7 -> 0 | I21: =+I$14/7/2 -> 0
B22: =B21+1 -> 2000 | C22: =-SUM(D22:AH22) -> -88459.364 | D22: =+D21 -> 46616.899 | E22: =+E21 -> 11408.161 | F22: =+F21 -> 25377.161 | G22: =+G21 -> 0 | H22: =+H21 -> 0 | I22: =+I$14/7 -> 0 | J22: =+J$14/7/2 -> 5057.1429
B23: =B22+1 -> 2001 | C23: =-SUM(D23:AH23) -> -79437.934 | D23: =+D$14/7/2 -> 23308.449 | E23: =+E22 -> 11408.161 | F23: =+F22 -> 25377.161 | G23: =+G22 -> 0 | H23: =+H22 -> 0 | I23: =+I22 -> 0 | J23: =+J$14/7 -> 10114.286 | K23: =+K$14/7/2 -> 9229.8764
B24: =B23+1 -> 2002 | C24: =-SUM(D24:AH24) -> -59655.281 | E24: =+E$14/7/2 -> 5704.0807 | F24: =+F23 -> 25377.161 | G24: =+G23 -> 0 | H24: =+H23 -> 0 | I24: =+I23 -> 0 | J24: =+J23 -> 10114.286 | K24: =+K$14/7 -> 18459.753 | L24: =+L$14/7/2 -> 0
B25: =B24+1 -> 2003 | C25: =-SUM(D25:AH25) -> -41262.619 | F25: =+F$14/7/2 -> 12688.581 | G25: =+G24 -> 0 | H25: =+H24 -> 0 | I25: =+I24 -> 0 | J25: =+J24 -> 10114.286 | K25: =+K24 -> 18459.753 | L25: =+L$14/7 -> 0 | M25: =+M$14/7/2 -> 0
B26: =B25+1 -> 2004 | C26: =-SUM(D26:AH26) -> -28574.039 | G26: =+G$14/7/2 -> 0 | H26: =+H25 -> 0 | I26: =+I25 -> 0 | J26: =+J25 -> 10114.286 | K26: =+K25 -> 18459.753 | L26: =+L25 -> 0 | M26: =+M$14/7 -> 0 | N26: =+N$14/7/2 -> 0
B27: =B26+1 -> 2005 | C27: =-SUM(D27:AH27) -> -28574.039 | H27: =+H$14/7/2 -> 0 | I27: =+I26 -> 0 | J27: =+J26 -> 10114.286 | K27: =+K26 -> 18459.753 | L27: =+L26 -> 0 | M27: =+M26 -> 0 | N27: =+N$14/7 -> 0 | O27: =+O$14/7/2 -> 0
B28: =B27+1 -> 2006 | C28: =-SUM(D28:AH28) -> -28574.039 | I28: =+I$14/7/2 -> 0 | J28: =+J27 -> 10114.286 | K28: =+K27 -> 18459.753 | L28: =+L27 -> 0 | M28: =+M27 -> 0 | N28: =+N27 -> 0 | O28: =+O$14/7 -> 0 | P28: =+P$14/7/2 -> 0
B29: =B28+1 -> 2007 | C29: =-SUM(D29:AH29) -> -23516.896 | J29: =+J$14/7/2 -> 5057.1429 | K29: =+K28 -> 18459.753 | L29: =+L28 -> 0 | M29: =+M28 -> 0 | N29: =+N28 -> 0 | O29: =+O28 -> 0 | P29: =+P$14/7 -> 0 | Q29: =+Q$14/7/2 -> 0
B30: =B29+1 -> 2008 | C30: =-SUM(D30:AH30) -> -9229.8764 | K30: =+K$14/7/2 -> 9229.8764 | L30: =+L29 -> 0 | M30: =+M29 -> 0 | N30: =+N29 -> 0 | O30: =+O29 -> 0 | P30: =+P29 -> 0 | Q30: =+Q$14/7 -> 0 | R30: =+R$14/7/2 -> 0
B31: =B30+1 -> 2009 | C31: =-SUM(D31:AH31) -> 0 | L31: =+L$14/7/2 -> 0 | M31: =+M30 -> 0 | N31: =+N30 -> 0 | O31: =+O30 -> 0 | P31: =+P30 -> 0 | Q31: =+Q30 -> 0 | R31: =+R$14/7 -> 0 | S31: =+S$14/7/2 -> 0
A32: To April 30th, 2010 | B32: =B31+1 -> 2010 | C32: =-SUM(D32:AH32) -> 0 | M32: =+M$14/7/2 -> 0 | N32: =+N31 -> 0 | O32: =+O31 -> 0 | P32: =+P31 -> 0 | Q32: =+Q31 -> 0 | R32: =+R31 -> 0 | S32: =+S$14/7 -> 0 | T32: =+T$14/7/2 -> 0
B33: =B32+1 -> 2011 | C33: =-SUM(D33:AH33) -> 0 | N33: =+N$14/7/2 -> 0 | O33: =+O32 -> 0 | P33: =+P32 -> 0 | Q33: =+Q32 -> 0 | R33: =+R32 -> 0 | S33: =+S32 -> 0 | T33: =+T$14/7 -> 0 | U33: =+U$14/7/2 -> 0
B34: =B33+1 -> 2012 | C34: =-SUM(D34:AH34) -> 0 | Q34: =+Q33 -> 0 | R34: =+R33 -> 0 | S34: =+S33 -> 0 | T34: =+T$14/7 -> 0 | U34: =+U$14/7 -> 0 | V34: =+V$14/7/2 -> 0
B35: =B34+1 -> 2013 | C35: =-SUM(D35:AH35) -> 0
B36: =B35+1 -> 2014 | C36: =-SUM(D36:AH36) -> 0
B37: =B36+1 -> 2015 | C37: =-SUM(D37:AH37) -> -97620.864 | Y37: =$Y$14/7/2 -> 97620.864
B38: =B37+1 -> 2016 | C38: =-SUM(D38:AH38) -> -195241.73 | Y38: =$Y$14/7 -> 195241.73
B39: =B38+1 -> 2017 | C39: =-SUM(D39:AH39) -> -189433.03 | Y39: =$Y$14/7 -> 195241.73 | AA39: =$AA$14/7/2 -> -5808.7014
B40: =B39+1 -> 2018 | C40: =-SUM(D40:AH40) -> -183624.33 | Y40: =$Y$14/7 -> 195241.73 | AA40: =$AA$14/7 -> -11617.403
B41: =B40+1 -> 2019 | C41: =-SUM(D41:AH41) -> -183624.33 | Y41: =$Y$14/7 -> 195241.73 | AA41: =$AA$14/7 -> -11617.403
B42: =B41+1 -> 2020 | C42: =-SUM(D42:AH42) -> -183624.33 | Y42: =$Y$14/7 -> 195241.73 | AA42: =$AA$14/7 -> -11617.403
B43: =B42+1 -> 2021 | C43: =-SUM(D43:AH43) -> -183624.33 | Y43: =$Y$14/7 -> 195241.73 | AA43: =$AA$14/7 -> -11617.403
B44: =B43+1 -> 2022 | C44: =-SUM(D44:AH44) -> -86003.461 | Y44: =$Y$14/7/2 -> 97620.864 | AA44: =$AA$14/7 -> -11617.403
B45: =B44+1 -> 2023 | C45: =-SUM(D45:AH45) -> 11617.403 | AA45: =$AA$14/7 -> -11617.403
B46: =B45+1 -> 2024 | C46: =-SUM(D46:AH46) -> 5808.7014 | AA46: =$AA$14/7/2 -> -5808.7014
A49: ST | B49: =SUM(D49:Y49) -> 0 | C49: =SUM(C16:C48) -> -2069204.1 | D49: =-SUM(D16:D48)+D14 -> 0 | E49: =-SUM(E16:E48)+E14 -> 0 | F49: =-SUM(F16:F48)+F14 -> 0 | G49: =-SUM(G16:G48)+G14 -> 0 | H49: =-SUM(H16:H48)+H14 -> 0 | I49: =-SUM(I16:I48)+I14 -> 0 | J49: =-SUM(J16:J48)+J14 -> 0 | K49: =-SUM(K16:K48)+K14 -> 0 | ... AC49: =-SUM(AC16:AC48)+AC14 -> 0
A51: Net Book Value | C51: =+C14+C49 -> 0
A53: comments
A54: 2014 additions of $80646.51 and $73270 allocated to 1115008 | N54: =SUM(E32:E54) -> 0

Sheet 105
A1: ABS EQUIPMENT LEASING INC.
A2: Equipment List
A3: Source: F 2009 Fixed Asset Summary
R4: Total | T4: Book
A5: Description | B5: Asset # | C5: Serial # | R5: Costs | S5: Depr. | T5: Value
A6: =+SUMMARY!B14 -> WOTAN RAPID 2 | B6: =+SUMMARY!A14 -> 105 | C6: =+SUMMARY!D14 -> 68142
A7: =+SUMMARY!C14 -> 0 | R7: =+C14 -> 827862.17 | S7: =+-C43 -> 827862.17 | T7: =+R7-S7 -> 0
A11: Location: | B11: =+SUMMARY!F14 -> MISS | C11: B4
A13: Purchased Year Ending | C13: Total | D13: 1994 | E13: 1995 | F13: 1996 | G13: 1997 | H13: 1998 | I13: 1999 | J13: 2000 | K13: 2001 | L13: 2002 | M13: 2003 | N13: 2004 | O13: 2005 | P13: 2006 | Q13: 2007 | R13: 2008 | S13: 2009 | T13: 2010 | U13: 2011 | V13: 2012 | W13: 2013 | X13: 2014 | Y13: 2015 | Z13: 2016 | AA13: 2017 | AB13: 2018
A14: Purchases (Fiscal Yr.) | C14: =SUM(D14:AB14) -> 827862.17 | M14: 206459.47 | O14: 424514.8 | P14: 112505.35 | U14: 84382.55
A15: =IF(+C14-'Equip Review 032310'!Y29=0,"ok","check") -> check
A16: Depreciation | B16: 1994 | C16: =-SUM(D16:Y16) -> 0 | D16: =+D$14/7/2 -> 0
B17: 1995 | C17: =-SUM(D17:Y17) -> 0 | D17: =+D$14/7 -> 0 | E17: =+E$14/7/2 -> 0
B18: 1996 | C18: =-SUM(D18:Y18) -> 0 | D18: =+D17 -> 0 | E18: =+E$14/7 -> 0 | F18: =+F$14/7/2 -> 0
B19: 1997 | C19: =-SUM(D19:Y19) -> 0 | D19: =+D18 -> 0 | E19: =+E18 -> 0 | F19: =+F$14/7 -> 0 | G19: =+G$14/7/2 -> 0
B20: 1998 | C20: =-SUM(D20:Y20) -> 0 | D20: =+D19 -> 0 | E20: =+E19 -> 0 | F20: =+F19 -> 0 | G20: =+G$14/7 -> 0 | H20: =+H$14/7/2 -> 0
B21: 1999 | C21: =-SUM(D21:Y21) -> 0 | D21: =+D20 -> 0 | E21: =+E20 -> 0 | F21: =+F20 -> 0 | G21: =+G20 -> 0 | H21: =+H$14/7 -> 0 | I21: =+I$14/7/2 -> 0
B22: 2000 | C22: =-SUM(D22:Y22) -> 0 | D22: =+D21 -> 0 | E22: =+E21 -> 0 | F22: =+F21 -> 0 | G22: =+G21 -> 0 | H22: =+H21 -> 0 | I22: =+I$14/7 -> 0 | J22: =+J$14/7/2 -> 0
B23: 2001 | C23: =-SUM(D23:Y23) -> 0 | D23: =+D$14/7/2 -> 0 | E23: =+E22 -> 0 | F23: =+F22 -> 0 | G23: =+G22 -> 0 | H23: =+H22 -> 0 | I23: =+I22 -> 0 | J23: =+J$14/7 -> 0 | K23: =+K$14/7/2 -> 0
B24: 2002 | C24: =-SUM(D24:Y24) -> 0 | E24: =+E$14/7/2 -> 0 | F24: =+F23 -> 0 | G24: =+G23 -> 0 | H24: =+H23 -> 0 | I24: =+I23 -> 0 | J24: =+J23 -> 0 | K24: =+K$14/7 -> 0 | L24: =+L$14/7/2 -> 0
B25: 2003 | C25: =-SUM(D25:Y25) -> -14747.105 | F25: =+F$14/7/2 -> 0 | G25: =+G24 -> 0 | H25: =+H24 -> 0 | I25: =+I24 -> 0 | J25: =+J24 -> 0 | K25: =+K24 -> 0 | L25: =+L$14/7 -> 0 | M25: =+M$14/7/2 -> 14747.105
B26: 2004 | C26: =-SUM(D26:Y26) -> -29494.21 | G26: =+G$14/7/2 -> 0 | H26: =+H25 -> 0 | I26: =+I25 -> 0 | J26: =+J25 -> 0 | K26: =+K25 -> 0 | L26: =+L25 -> 0 | M26: =+M$14/7 -> 29494.21 | N26: =+N$14/7/2 -> 0
B27: 2005 | C27: =-SUM(D27:Y27) -> -59816.696 | H27: =+H$14/7/2 -> 0 | I27: =+I26 -> 0 | J27: =+J26 -> 0 | K27: =+K26 -> 0 | L27: =+L26 -> 0 | M27: =+M26 -> 29494.21 | N27: =+N$14/7 -> 0 | O27: =+O$14/7/2 -> 30322.486
B28: 2006 | C28: =-SUM(D28:Y28) -> -98175.278 | I28: =+I$14/7/2 -> 0 | J28: =+J27 -> 0 | K28: =+K27 -> 0 | L28: =+L27 -> 0 | M28: =+M27 -> 29494.21 | N28: =+N27 -> 0 | O28: =+O$14/7 -> 60644.971 | P28: =+P$14/7/2 -> 8036.0964
B29: 2007 | C29: =-SUM(D29:Y29) -> -106211.37 | J29: =+J$14/7/2 -> 0 | K29: =+K28 -> 0 | L29: =+L28 -> 0 | M29: =+M28 -> 29494.21 | N29: =+N28 -> 0 | O29: =+O28 -> 60644.971 | P29: =+P$14/7 -> 16072.193 | Q29: =+Q$14/7/2 -> 0
B30: 2008 | C30: =-SUM(D30:Y30) -> -106211.37 | K30: =+K$14/7/2 -> 0 | L30: =+L29 -> 0 | M30: =+M29 -> 29494.21 | N30: =+N29 -> 0 | O30: =+O29 -> 60644.971 | P30: =+P29 -> 16072.193 | Q30: =+Q$14/7 -> 0 | R30: =+R$14/7/2 -> 0
B31: 2009 | C31: =-SUM(D31:Y31) -> -106211.37 | L31: =+L$14/7/2 -> 0 | M31: =+M30 -> 29494.21 | N31: =+N30 -> 0 | O31: =+O30 -> 60644.971 | P31: =+P30 -> 16072.193 | Q31: =+Q30 -> 0 | R31: =+R$14/7 -> 0 | S31: =+S$14/7/2 -> 0
A32: To April 30th, 2010 | B32: 2010 | C32: =-SUM(D32:Y32) -> -91464.269 | M32: =+M$14/7/2 -> 14747.105 | N32: =+N31 -> 0 | O32: =+O31 -> 60644.971 | P32: =+P31 -> 16072.193 | Q32: =+Q31 -> 0 | R32: =+R31 -> 0 | S32: =+S$14/7 -> 0 | T32: =+T$14/7/2 -> 0
B33: 2011 | C33: =-SUM(D33:Y33) -> -82744.489 | N33: =+N$14/7/2 -> 0 | O33: =+O32 -> 60644.971 | P33: =+P32 -> 16072.193 | Q33: =+Q32 -> 0 | R33: =+R32 -> 0 | S33: =+S32 -> 0 | T33: =+T$14/7 -> 0 | U33: =+U$14/7/2 -> 6027.325
B34: 2012 | C34: =-SUM(D34:Y34) -> -58449.329 | O34: =+O$14/7/2 -> 30322.486 | P34: =+P33 -> 16072.193 | Q34: =+Q33 -> 0 | R34: =+R33 -> 0 | S34: =+S33 -> 0 | T34: =+T$14/7 -> 0 | U34: =+U$14/7 -> 12054.65 | V34: =+V$14/7/2 -> 0
B35: 2013 | C35: =-SUM(D35:Y35) -> -20090.746 | P35: =P14/7/2 -> 8036.0964 | U35: =+U$14/7 -> 12054.65
B36: 2014 | C36: =-SUM(D36:Y36) -> -12054.65 | U36: =+U$14/7 -> 12054.65
B37: 2015 | C37: =-SUM(D37:Y37) -> -12054.65 | U37: =U36 -> 12054.65
B38: 2016 | C38: =-SUM(D38:AA38) -> -12054.65 | U38: =+U$14/7 -> 12054.65
B39: 2017 | C39: =-SUM(D39:AA39) -> -12054.65 | U39: =+U$14/7 -> 12054.65
B40: 2018 | C40: =-SUM(D40:AB40) -> -6027.325 | U40: =+U$14/7/2 -> 6027.325
B41: 2019 | C41: =-SUM(D41:AB41) -> 0
A43: ST | B43: =SUM(D43:Y43) -> 0 | C43: =SUM(C16:C42) -> -827862.17 | D43: =-SUM(D16:D42)+D14 -> 0 | E43: =-SUM(E16:E42)+E14 -> 0 | F43: =-SUM(F16:F42)+F14 -> 0 | G43: =-SUM(G16:G42)+G14 -> 0 | H43: =-SUM(H16:H42)+H14 -> 0 | I43: =-SUM(I16:I42)+I14 -> 0 | J43: =-SUM(J16:J42)+J14 -> 0 | K43: =-SUM(K16:K42)+K14 -> 0 | ... AB43: =-SUM(AB16:AB42)+AB14 -> 0
A45: Net Book Value | C45: =+C14+C43 -> 0
N48: =SUM(E32:E48) -> 0

Sheet 106
A1: ABS EQUIPMENT LEASING INC.
A2: Equipment List
A3: Source: F 2009 Fixed Asset Summary
R4: Total | T4: Book
A5: Description | B5: Asset # | C5: Serial # | R5: Costs | S5: Depr. | T5: Value
A7: WOTAN 5 - Rapid 5P | B7: 106 | C7: 67019 | R7: =+C14 -> 985457.86 | S7: =+-C48 -> 984734.75 | T7: =+R7-S7 -> 723.10714
A8: CNC W/CNC A.B.840 D
A9: Philadelphia Gear Corp
A11: Location: | B11: MISS | C11: A3
A13: Purchased Year Ending | C13: Total | D13: 1994 | E13: 1995 | F13: 1996 | G13: 1997 | H13: 1998 | I13: 1999 | J13: 2000 | K13: 2001 | L13: 2002 | M13: 2003 | N13: 2004 | O13: =N13+1 -> 2005 | P13: =O13+1 -> 2006 | Q13: =P13+1 -> 2007 | R13: =Q13+1 -> 2008 | S13: =R13+1 -> 2009 | T13: =S13+1 -> 2010 | U13: =T13+1 -> 2011 | V13: =U13+1 -> 2012 | ... AH13: =AG13+1 -> 2024
A14: Purchases (Fiscal Yr.) | C14: =SUM(D14:AH14) -> 985457.86 | D14: =+'Equip Review 032310'!G24 -> 0 | E14: =+'Equip Review 032310'!H24 -> 0 | F14: =+'Equip Review 032310'!I24 -> 0 | G14: =+'Equip Review 032310'!J24 -> 0 | H14: =+'Equip Review 032310'!K24 -> 0 | I14: =+'Equip Review 032310'!L24 -> 0 | J14: =+'Equip Review 032310'!M24 -> 0 | K14: =+'Equip Review 032310'!N24 -> 0 | ... P14: =+'Equip Review 032310'!S24 -> 4328.9 | Q14: =+'Equip Review 032310'!T24+'Equip Review 032310'!U24 -> 0 | R14: =+'Equip Review 032310'!V24 -> 0 | S14: =+'Equip Review 032310'!W24 -> 0 | AC14: =5397.5-2023 -> 3374.5
A15: =IF(+C14-'Equip Review 032310'!Y24=0,"ok","check") -> check
A16: Depreciation | B16: 1994 | C16: =-SUM(D16:AH16) -> 0 | D16: =+D$14/7/2 -> 0
B17: =B16+1 -> 1995 | C17: =-SUM(D17:AH17) -> 0 | D17: =+D$14/7 -> 0 | E17: =+E$14/7/2 -> 0
B18: =B17+1 -> 1996 | C18: =-SUM(D18:AH18) -> 0 | D18: =+D17 -> 0 | E18: =+E$14/7 -> 0 | F18: =+F$14/7/2 -> 0
B19: =B18+1 -> 1997 | C19: =-SUM(D19:AH19) -> 0 | D19: =+D18 -> 0 | E19: =+E18 -> 0 | F19: =+F$14/7 -> 0 | G19: =+G$14/7/2 -> 0
B20: =B19+1 -> 1998 | C20: =-SUM(D20:AH20) -> 0 | D20: =+D19 -> 0 | E20: =+E19 -> 0 | F20: =+F19 -> 0 | G20: =+G$14/7 -> 0 | H20: =+H$14/7/2 -> 0
B21: =B20+1 -> 1999 | C21: =-SUM(D21:AH21) -> 0 | D21: =+D20 -> 0 | E21: =+E20 -> 0 | F21: =+F20 -> 0 | G21: =+G20 -> 0 | H21: =+H$14/7 -> 0 | I21: =+I$14/7/2 -> 0
B22: =B21+1 -> 2000 | C22: =-SUM(D22:AH22) -> 0 | D22: =+D21 -> 0 | E22: =+E21 -> 0 | F22: =+F21 -> 0 | G22: =+G21 -> 0 | H22: =+H21 -> 0 | I22: =+I$14/7 -> 0 | J22: =+J$14/7/2 -> 0
B23: =B22+1 -> 2001 | C23: =-SUM(D23:AH23) -> 0 | D23: =+D$14/7/2 -> 0 | E23: =+E22 -> 0 | F23: =+F22 -> 0 | G23: =+G22 -> 0 | H23: =+H22 -> 0 | I23: =+I22 -> 0 | J23: =+J$14/7 -> 0 | K23: =+K$14/7/2 -> 0
B24: =B23+1 -> 2002 | C24: =-SUM(D24:AH24) -> -53433.345 | E24: =+E$14/7/2 -> 0 | F24: =+F23 -> 0 | G24: =+G23 -> 0 | H24: =+H23 -> 0 | I24: =+I23 -> 0 | J24: =+J23 -> 0 | K24: =+K$14/7 -> 0 | L24: =+L$14/7/2 -> 53433.345
B25: =B24+1 -> 2003 | C25: =-SUM(D25:AH25) -> -110593.29 | F25: =+F$14/7/2 -> 0 | G25: =+G24 -> 0 | H25: =+H24 -> 0 | I25: =+I24 -> 0 | J25: =+J24 -> 0 | K25: =+K24 -> 0 | L25: =+L$14/7 -> 106866.69 | M25: =+M$14/7/2 -> 3726.6029
B26: =B25+1 -> 2004 | C26: =-SUM(D26:AH26) -> -120769.12 | G26: =+G$14/7/2 -> 0 | H26: =+H25 -> 0 | I26: =+I25 -> 0 | J26: =+J25 -> 0 | K26: =+K25 -> 0 | L26: =+L25 -> 106866.69 | M26: =+M$14/7 -> 7453.2057 | N26: =+N$14/7/2 -> 6449.2279
B27: =B26+1 -> 2005 | C27: =-SUM(D27:AH27) -> -133448.78 | H27: =+H$14/7/2 -> 0 | I27: =+I26 -> 0 | J27: =+J26 -> 0 | K27: =+K26 -> 0 | L27: =+L26 -> 106866.69 | M27: =+M26 -> 7453.2057 | N27: =+N$14/7 -> 12898.456 | O27: =+O$14/7/2 -> 6230.4286
B28: =B27+1 -> 2006 | C28: =-SUM(D28:AH28) -> -139988.42 | I28: =+I$14/7/2 -> 0 | J28: =+J27 -> 0 | K28: =+K27 -> 0 | L28: =+L27 -> 106866.69 | M28: =+M27 -> 7453.2057 | N28: =+N27 -> 12898.456 | O28: =+O$14/7 -> 12460.857 | P28: =+P$14/7/2 -> 309.20714
B29: =B28+1 -> 2007 | C29: =-SUM(D29:AH29) -> -140297.62 | J29: =+J$14/7/2 -> 0 | K29: =+K28 -> 0 | L29: =+L28 -> 106866.69 | M29: =+M28 -> 7453.2057 | N29: =+N28 -> 12898.456 | O29: =+O$14/7 -> 12460.857 | P29: =+P$14/7 -> 618.41429 | Q29: =+Q$14/7/2 -> 0
B30: =B29+1 -> 2008 | C30: =-SUM(D30:AH30) -> -140297.62 | K30: =+K$14/7/2 -> 0 | L30: =+L29 -> 106866.69 | M30: =+M29 -> 7453.2057 | N30: =+N29 -> 12898.456 | O30: =+O$14/7 -> 12460.857 | P30: =+P$14/7 -> 618.41429 | Q30: =+Q$14/7 -> 0 | R30: =+R$14/7/2 -> 0
B31: =B30+1 -> 2009 | C31: =-SUM(D31:AH31) -> -86864.278 | L31: =+L$14/7/2 -> 53433.345 | M31: =+M30 -> 7453.2057 | N31: =+N30 -> 12898.456 | O31: =+O$14/7 -> 12460.857 | P31: =+P$14/7 -> 618.41429 | Q31: =+Q30 -> 0 | R31: =+R$14/7 -> 0 | S31: =+S$14/7/2 -> 0
A32: To April 30th, 2010 | B32: =B31+1 -> 2010 | C32: =-SUM(D32:AH32) -> -29704.33 | M32: =+M$14/7/2 -> 3726.6029 | N32: =+N31 -> 12898.456 | O32: =+O$14/7 -> 12460.857 | P32: =+P$14/7 -> 618.41429 | Q32: =+Q31 -> 0 | R32: =+R31 -> 0 | S32: =+S$14/7 -> 0 | T32: =+T$14/7/2 -> 0
B33: =B32+1 -> 2011 | C33: =-SUM(D33:AH33) -> -19528.499 | N33: =+N$14/7/2 -> 6449.2279 | O33: =+O$14/7 -> 12460.857 | P33: =+P$14/7 -> 618.41429 | Q33: =+Q32 -> 0 | R33: =+R32 -> 0 | S33: =+S32 -> 0 | T33: =+T$14/7 -> 0 | U33: =+U$14/7/2 -> 0
B34: =B33+1 -> 2012 | C34: =-SUM(D34:AH34) -> -6848.8429 | O34: =+O$14/7/2 -> 6230.4286 | P34: =+P$14/7 -> 618.41429 | Q34: =+Q33 -> 0 | R34: =+R33 -> 0 | S34: =+S33 -> 0 | T34: =+T$14/7 -> 0 | U34: =+U$14/7 -> 0 | V34: =+V$14/7/2 -> 0
B35: =B34+1 -> 2013 | C35: =-SUM(D35:AH35) -> -309.20714 | P35: =P14/7/2 -> 309.20714
B36: =B35+1 -> 2014 | C36: =-SUM(D36:AH36) -> 0
B37: =B36+1 -> 2015 | C37: =-SUM(D37:AH37) -> 0
B38: =B37+1 -> 2016 | C38: =-SUM(D38:AH38) -> 0
B39: =B38+1 -> 2017 | C39: =-SUM(D39:AH39) -> 0
B40: =B39+1 -> 2018 | C40: =-SUM(D40:AH40) -> 0
B41: =B40+1 -> 2019 | C41: =-SUM(D41:AH41) -> -241.03571 | AC41: =+AC$14/7/2 -> 241.03571
B42: =B41+1 -> 2020 | C42: =-SUM(D42:AH42) -> -482.07143 | AC42: =+AC$14/7 -> 482.07143
B43: =B42+1 -> 2021 | C43: =-SUM(D43:AH43) -> -482.07143 | AC43: =+AC$14/7 -> 482.07143
B44: =B43+1 -> 2022 | C44: =-SUM(D44:AH44) -> -482.07143 | AC44: =+AC$14/7 -> 482.07143
B45: =B44+1 -> 2023 | C45: =-SUM(D45:AH45) -> -482.07143 | AC45: =+AC$14/7 -> 482.07143
B46: =B45+1 -> 2024 | C46: =-SUM(D46:AH46) -> -482.07143 | AC46: =+AC$14/7 -> 482.07143
A48: ST | B48: =SUM(D48:AH48) -> 723.10714 | C48: =SUM(C16:C47) -> -984734.75 | D48: =-SUM(D16:D47)+D14 -> 0 | E48: =-SUM(E16:E47)+E14 -> 0 | F48: =-SUM(F16:F47)+F14 -> 0 | G48: =-SUM(G16:G47)+G14 -> 0 | H48: =-SUM(H16:H47)+H14 -> 0 | I48: =-SUM(I16:I47)+I14 -> 0 | J48: =-SUM(J16:J47)+J14 -> 0 | K48: =-SUM(K16:K47)+K14 -> 0 | ... AC48: =-SUM(AC16:AC47)+AC14 -> 723.10714
A50: Net Book Value | C50: =+C14+C48 -> 723.10714
N53: =SUM(E32:E53) -> 0

Sheet 107
A1: ABS EQUIPMENT LEASING INC.
A2: Equipment List
A3: Source: F 2009 Fixed Asset Summary
R4: Total | T4: Book
A5: Description | B5: Asset # | C5: Serial # | R5: Costs | S5: Depr. | T5: Value
A6: =+SUMMARY!B16 -> WOTAN RAPID 6 | B6: =+SUMMARY!A16 -> 107 | C6: 65027
A7: =+SUMMARY!C16 -> CNC HBM | R7: =+C14 -> 1785899.9 | S7: =+-C48 -> 1682124.8 | T7: =+R7-S7 -> 103775.19
A8: Industrial Machine Tool Inc.
B11: =+SUMMARY!F16 -> BURL 1 | C11: A1
A13: Purchased Year Ending | C13: Total | D13: 1994 | E13: 1995 | F13: 1996 | G13: 1997 | H13: 1998 | I13: 1999 | J13: 2000 | K13: 2001 | L13: 2002 | M13: 2003 | N13: 2004 | O13: =N13+1 -> 2005 | P13: =O13+1 -> 2006 | Q13: =P13+1 -> 2007 | R13: =Q13+1 -> 2008 | S13: =R13+1 -> 2009 | T13: =S13+1 -> 2010 | U13: =T13+1 -> 2011 | V13: =U13+1 -> 2012 | ... AH13: =AG13+1 -> 2024
A14: Purchases (Fiscal Yr.) | C14: =SUM(D14:AH14) -> 1785899.9 | K14: 1398067.2 | L14: 343693.77 | Q14: -112860 | AA14: 10468.74 | AB14: 22283.16 | AE14: 24951.91 | AF14: 25584.97 | AG14: 73710.2
A15: =IF(+C14-'Equip Review 032310'!Y29=0,"ok","check") -> check
A16: Depreciation | B16: 1994 | C16: =-SUM(D16:AH16) -> 0 | D16: =+D$14/7/2 -> 0
B17: =B16+1 -> 1995 | C17: =-SUM(D17:AH17) -> 0 | D17: =+D$14/7 -> 0 | E17: =+E$14/7/2 -> 0
B18: =B17+1 -> 1996 | C18: =-SUM(D18:AH18) -> 0 | D18: =+D17 -> 0 | E18: =+E$14/7 -> 0 | F18: =+F$14/7/2 -> 0
B19: =B18+1 -> 1997 | C19: =-SUM(D19:AH19) -> 0 | D19: =+D18 -> 0 | E19: =+E18 -> 0 | F19: =+F$14/7 -> 0 | G19: =+G$14/7/2 -> 0
B20: =B19+1 -> 1998 | C20: =-SUM(D20:AH20) -> 0 | D20: =+D19 -> 0 | E20: =+E19 -> 0 | F20: =+F19 -> 0 | G20: =+G$14/7 -> 0 | H20: =+H$14/7/2 -> 0
B21: =B20+1 -> 1999 | C21: =-SUM(D21:AH21) -> 0 | D21: =+D20 -> 0 | E21: =+E20 -> 0 | F21: =+F20 -> 0 | G21: =+G20 -> 0 | H21: =+H$14/7 -> 0 | I21: =+I$14/7/2 -> 0
B22: =B21+1 -> 2000 | C22: =-SUM(D22:AH22) -> 0 | D22: =+D21 -> 0 | E22: =+E21 -> 0 | F22: =+F21 -> 0 | G22: =+G21 -> 0 | H22: =+H21 -> 0 | I22: =+I$14/7 -> 0 | J22: =+J$14/7/2 -> 0
B23: =B22+1 -> 2001 | C23: =-SUM(D23:AH23) -> -99861.943 | D23: =+D$14/7/2 -> 0 | E23: =+E22 -> 0 | F23: =+F22 -> 0 | G23: =+G22 -> 0 | H23: =+H22 -> 0 | I23: =+I22 -> 0 | J23: =+J$14/7 -> 0 | K23: =+K$14/7/2 -> 99861.943
B24: =B23+1 -> 2002 | C24: =-SUM(D24:AH24) -> -224273.44 | E24: =+E$14/7/2 -> 0 | F24: =+F23 -> 0 | G24: =+G23 -> 0 | H24: =+H23 -> 0 | I24: =+I23 -> 0 | J24: =+J23 -> 0 | K24: =+K$14/7 -> 199723.89 | L24: =+L$14/7/2 -> 24549.555
B25: =B24+1 -> 2003 | C25: =-SUM(D25:AH25) -> -248823 | F25: =+F$14/7/2 -> 0 | G25: =+G24 -> 0 | H25: =+H24 -> 0 | I25: =+I24 -> 0 | J25: =+J24 -> 0 | K25: =+K24 -> 199723.89 | L25: =+L$14/7 -> 49099.11 | M25: =+M$14/7/2 -> 0
B26: =B25+1 -> 2004 | C26: =-SUM(D26:AH26) -> -248823 | G26: =+G$14/7/2 -> 0 | H26: =+H25 -> 0 | I26: =+I25 -> 0 | J26: =+J25 -> 0 | K26: =+K25 -> 199723.89 | L26: =+L25 -> 49099.11 | M26: =+M$14/7 -> 0 | N26: =+N$14/7/2 -> 0
B27: =B26+1 -> 2005 | C27: =-SUM(D27:AH27) -> -248823 | H27: =+H$14/7/2 -> 0 | I27: =+I26 -> 0 | J27: =+J26 -> 0 | K27: =+K26 -> 199723.89 | L27: =+L26 -> 49099.11 | M27: =+M26 -> 0 | N27: =+N$14/7 -> 0 | O27: =+O$14/7/2 -> 0
B28: =B27+1 -> 2006 | C28: =-SUM(D28:AH28) -> -248823 | I28: =+I$14/7/2 -> 0 | J28: =+J27 -> 0 | K28: =+K27 -> 199723.89 | L28: =+L27 -> 49099.11 | M28: =+M27 -> 0 | N28: =+N27 -> 0 | O28: =+O$14/7 -> 0 | P28: =+P$14/7/2 -> 0
B29: =B28+1 -> 2007 | C29: =-SUM(D29:AH29) -> -240761.57 | J29: =+J$14/7/2 -> 0 | K29: =+K28 -> 199723.89 | L29: =+L28 -> 49099.11 | M29: =+M28 -> 0 | N29: =+N28 -> 0 | O29: =+O28 -> 0 | P29: =+P$14/7 -> 0 | Q29: =+Q$14/7/2 -> -8061.4286
B30: =B29+1 -> 2008 | C30: =-SUM(D30:AH30) -> -132838.2 | K30: =+K$14/7/2 -> 99861.943 | L30: =+L29 -> 49099.11 | M30: =+M29 -> 0 | N30: =+N29 -> 0 | O30: =+O29 -> 0 | P30: =+P29 -> 0 | Q30: =+Q$14/7 -> -16122.857 | R30: =+R$14/7/2 -> 0
B31: =B30+1 -> 2009 | C31: =-SUM(D31:AH31) -> -8426.6979 | L31: =+L$14/7/2 -> 24549.555 | M31: =+M30 -> 0 | N31: =+N30 -> 0 | O31: =+O30 -> 0 | P31: =+P30 -> 0 | Q31: =+Q30 -> -16122.857 | R31: =+R$14/7 -> 0 | S31: =+S$14/7/2 -> 0
A32: To April 30th, 2010 | B32: =B31+1 -> 2010 | C32: =-SUM(D32:AH32) -> 16122.857 | M32: =+M$14/7/2 -> 0 | N32: =+N31 -> 0 | O32: =+O31 -> 0 | P32: =+P31 -> 0 | Q32: =+Q31 -> -16122.857 | R32: =+R31 -> 0 | S32: =+S$14/7 -> 0 | T32: =+T$14/7/2 -> 0
B33: =B32+1 -> 2011 | C33: =-SUM(D33:AH33) -> 16122.857 | N33: =+N$14/7/2 -> 0 | O33: =+O32 -> 0 | P33: =+P32 -> 0 | Q33: =+Q32 -> -16122.857 | R33: =+R32 -> 0 | S33: =+S32 -> 0 | T33: =+T$14/7 -> 0 | U33: =+U$14/7/2 -> 0
B34: =B33+1 -> 2012 | C34: =-SUM(D34:AH34) -> 16122.857 | Q34: =+Q33 -> -16122.857 | R34: =+R33 -> 0 | S34: =+S33 -> 0 | T34: =+T$14/7 -> 0 | U34: =+U$14/7 -> 0 | V34: =+V$14/7/2 -> 0
B35: =B34+1 -> 2013 | C35: =-SUM(D35:AH35) -> 16122.857 | Q35: =+Q34 -> -16122.857
B36: =B35+1 -> 2014 | C36: =-SUM(D36:AH36) -> 8061.4286 | Q36: =Q14/7/2 -> -8061.4286
B37: =B36+1 -> 2015 | C37: =-SUM(D37:AH37) -> 0
B38: =B37+1 -> 2016 | C38: =-SUM(D38:AH38) -> 0
B39: =B38+1 -> 2017 | C39: =-SUM(D39:AH39) -> -747.76714 | AA39: =$AA$14/7/2 -> 747.76714
B40: =B39+1 -> 2018 | C40: =-SUM(D40:AH40) -> -2609.6923 | AA40: =$AA$14/7 -> 1495.5343 | AB40: =+$AB$14/10/2 -> 1114.158
B41: =B40+1 -> 2019 | C41: =-SUM(D41:AH41) -> -3723.8503 | AA41: =$AA$14/7 -> 1495.5343 | AB41: =+$AB$14/10 -> 2228.316
B42: =B41+1 -> 2020 | C42: =-SUM(D42:AH42) -> -3723.8503 | AA42: =$AA$14/7 -> 1495.5343 | AB42: =+$AB$14/10 -> 2228.316
B43: =B42+1 -> 2021 | C43: =-SUM(D43:AH43) -> -5506.1296 | AA43: =$AA$14/7 -> 1495.5343 | AB43: =+$AB$14/10 -> 2228.316 | AE43: =$AE$14/7/2 -> 1782.2793
B44: =B43+1 -> 2022 | C44: =-SUM(D44:AH44) -> -7288.4089 | AA44: =$AA$14/7 -> 1495.5343 | AB44: =+$AB$14/10 -> 2228.316 | AE44: =$AE$14/7 -> 3564.5586
B45: =B44+1 -> 2023 | C45: =-SUM(D45:AH45) -> -12553.423 | AA45: =$AA$14/7 -> 1495.5343 | AB45: =+$AB$14/10 -> 2228.316 | AE45: =$AE$14/7 -> 3564.5586 | AG45: =$AG$14/7/2 -> 5265.0143
B46: =B45+1 -> 2024 | C46: =-SUM(D46:AH46) -> -17070.67 | AA46: =$AA$14/7/2 -> 747.76714 | AB46: =+$AB$14/10 -> 2228.316 | AE46: =$AE$14/7 -> 3564.5586 | AG46: =$AG$14/7 -> 10530.029
A48: ST | B48: =SUM(D48:AH48) -> 103775.19 | C48: =SUM(C16:C47) -> -1682124.8 | D48: =-SUM(D16:D47)+D14 -> 0 | E48: =-SUM(E16:E47)+E14 -> 0 | F48: =-SUM(F16:F47)+F14 -> 0 | G48: =-SUM(G16:G47)+G14 -> 0 | H48: =-SUM(H16:H47)+H14 -> 0 | I48: =-SUM(I16:I47)+I14 -> 0 | J48: =-SUM(J16:J47)+J14 -> 0 | K48: =-SUM(K16:K47)+K14 -> 0 | ... AH48: =-SUM(AH16:AH47)+AH14 -> 0
A50: Net Book Value | C50: =+C14+C48 -> 103775.19
N53: =SUM(E32:E53) -> 0

Sheet 108
A1: ABS EQUIPMENT LEASING INC.
A2: Equipment List
A3: Source: F 2009 Fixed Asset Summary
R4: Total | T4: Book
A5: Description | B5: Asset # | C5: Serial # | R5: Costs | S5: Depr. | T5: Value
A7: SAN ROCCO - FUTURA 14 | B7: 108 | C7: F07/6 | R7: =+C14 -> 1288891.3 | S7: =+-C42 -> 1288891.3 | T7: =+R7-S7 -> 0
A8: 14/34"
A9: HORIZONTAL BORING MILL
A11: Location: | B11: MISS | C11: C2
A13: Purchased Year Ending | C13: Total | D13: 1994 | E13: 1995 | F13: 1996 | G13: 1997 | H13: 1998 | I13: 1999 | J13: 2000 | K13: 2001 | L13: 2002 | M13: 2003 | N13: 2004 | O13: 2005 | P13: 2006 | Q13: 2007 | R13: 2008 | S13: 2009 | T13: 2010 | U13: 2011 | V13: 2012 | W13: 2013 | X13: 2014 | Y13: 2015 | Z13: 2016 | AA13: 2017 | AB13: 2018
A14: Purchases (Fiscal Yr.) | C14: =SUM(D14:Y14) -> 1288891.3 | D14: =+'Equip Review 032310'!G9 -> 1281805.1 | E14: =+'Equip Review 032310'!H9 -> 0 | F14: =+'Equip Review 032310'!I9 -> 7086.2 | G14: =+'Equip Review 032310'!J9 -> 0 | H14: =+'Equip Review 032310'!K9 -> 0 | I14: =+'Equip Review 032310'!L9 -> 0 | J14: =+'Equip Review 032310'!M9 -> 0 | K14: =+'Equip Review 032310'!N9 -> 0 | ... P14: =+'Equip Review 032310'!S9 -> 0 | Q14: =+'Equip Review 032310'!T9+'Equip Review 032310'!U9 -> 0 | R14: =+'Equip Review 032310'!V9 -> 0 | S14: =+'Equip Review 032310'!W9 -> 0
A15: =IF(+C14-'Equip Review 032310'!Y9=0,"ok","check") -> ok
A16: Depreciation | B16: 1994 | C16: =-SUM(D16:Y16) -> -91557.509 | D16: =+D$14/7/2 -> 91557.509
B17: 1995 | C17: =-SUM(D17:Y17) -> -183115.02 | D17: =+D$14/7 -> 183115.02 | E17: =+E$14/7/2 -> 0
B18: 1996 | C18: =-SUM(D18:Y18) -> -183621.18 | D18: =+D17 -> 183115.02 | E18: =+E$14/7 -> 0 | F18: =+F$14/7/2 -> 506.15714
B19: 1997 | C19: =-SUM(D19:Y19) -> -184127.33 | D19: =+D18 -> 183115.02 | E19: =+E18 -> 0 | F19: =+F$14/7 -> 1012.3143 | G19: =+G$14/7/2 -> 0
B20: 1998 | C20: =-SUM(D20:Y20) -> -184127.33 | D20: =+D19 -> 183115.02 | E20: =+E19 -> 0 | F20: =+F19 -> 1012.3143 | G20: =+G$14/7 -> 0 | H20: =+H$14/7/2 -> 0
B21: 1999 | C21: =-SUM(D21:Y21) -> -184127.33 | D21: =+D20 -> 183115.02 | E21: =+E20 -> 0 | F21: =+F20 -> 1012.3143 | G21: =+G20 -> 0 | H21: =+H$14/7 -> 0 | I21: =+I$14/7/2 -> 0
B22: 2000 | C22: =-SUM(D22:Y22) -> -184127.33 | D22: =+D21 -> 183115.02 | E22: =+E21 -> 0 | F22: =+F21 -> 1012.3143 | G22: =+G21 -> 0 | H22: =+H21 -> 0 | I22: =+I$14/7 -> 0 | J22: =+J$14/7/2 -> 0
B23: 2001 | C23: =-SUM(D23:Y23) -> -92569.824 | D23: =+D$14/7/2 -> 91557.509 | E23: =+E22 -> 0 | F23: =+F22 -> 1012.3143 | G23: =+G22 -> 0 | H23: =+H22 -> 0 | I23: =+I22 -> 0 | J23: =+J$14/7 -> 0 | K23: =+K$14/7/2 -> 0
B24: 2002 | C24: =-SUM(D24:Y24) -> -1012.3143 | E24: =+E$14/7/2 -> 0 | F24: =+F23 -> 1012.3143 | G24: =+G23 -> 0 | H24: =+H23 -> 0 | I24: =+I23 -> 0 | J24: =+J23 -> 0 | K24: =+K$14/7 -> 0 | L24: =+L$14/7/2 -> 0
B25: 2003 | C25: =-SUM(D25:Y25) -> -506.15714 | F25: =+F$14/7/2 -> 506.15714 | G25: =+G24 -> 0 | H25: =+H24 -> 0 | I25: =+I24 -> 0 | J25: =+J24 -> 0 | K25: =+K24 -> 0 | L25: =+L$14/7 -> 0 | M25: =+M$14/7/2 -> 0
B26: 2004 | C26: =-SUM(D26:Y26) -> 0 | G26: =+G$14/7/2 -> 0 | H26: =+H25 -> 0 | I26: =+I25 -> 0 | J26: =+J25 -> 0 | K26: =+K25 -> 0 | L26: =+L25 -> 0 | M26: =+M$14/7 -> 0 | N26: =+N$14/7/2 -> 0
B27: 2005 | C27: =-SUM(D27:Y27) -> 0 | H27: =+H$14/7/2 -> 0 | I27: =+I26 -> 0 | J27: =+J26 -> 0 | K27: =+K26 -> 0 | L27: =+L26 -> 0 | M27: =+M26 -> 0 | N27: =+N$14/7 -> 0 | O27: =+O$14/7/2 -> 0
B28: 2006 | C28: =-SUM(D28:Y28) -> 0 | I28: =+I$14/7/2 -> 0 | J28: =+J27 -> 0 | K28: =+K27 -> 0 | L28: =+L27 -> 0 | M28: =+M27 -> 0 | N28: =+N27 -> 0 | O28: =+O$14/7 -> 0 | P28: =+P$14/7/2 -> 0
B29: 2007 | C29: =-SUM(D29:Y29) -> 0 | J29: =+J$14/7/2 -> 0 | K29: =+K28 -> 0 | L29: =+L28 -> 0 | M29: =+M28 -> 0 | N29: =+N28 -> 0 | O29: =+O28 -> 0 | P29: =+P$14/7 -> 0 | Q29: =+Q$14/7/2 -> 0
B30: 2008 | C30: =-SUM(D30:Y30) -> 0 | K30: =+K$14/7/2 -> 0 | L30: =+L29 -> 0 | M30: =+M29 -> 0 | N30: =+N29 -> 0 | O30: =+O29 -> 0 | P30: =+P29 -> 0 | Q30: =+Q$14/7 -> 0 | R30: =+R$14/7/2 -> 0
B31: 2009 | C31: =-SUM(D31:Y31) -> 0 | L31: =+L$14/7/2 -> 0 | M31: =+M30 -> 0 | N31: =+N30 -> 0 | O31: =+O30 -> 0 | P31: =+P30 -> 0 | Q31: =+Q30 -> 0 | R31: =+R$14/7 -> 0 | S31: =+S$14/7/2 -> 0
A32: To April 30th, 2010 | B32: 2010 | C32: =-SUM(D32:Y32) -> 0 | M32: =+M$14/7/2 -> 0 | N32: =+N31 -> 0 | O32: =+O31 -> 0 | P32: =+P31 -> 0 | Q32: =+Q31 -> 0 | R32: =+R31 -> 0 | S32: =+S$14/7 -> 0 | T32: =+T$14/7/2 -> 0
B33: 2011 | C33: =-SUM(D33:Y33) -> 0 | N33: =+N$14/7/2 -> 0 | O33: =+O32 -> 0 | P33: =+P32 -> 0 | Q33: =+Q32 -> 0 | R33: =+R32 -> 0 | S33: =+S32 -> 0 | T33: =+T$14/7 -> 0 | U33: =+U$14/7/2 -> 0
B34: 2012 | C34: =-SUM(D34:Y34) -> 0 | Q34: =+Q33 -> 0 | R34: =+R33 -> 0 | S34: =+S33 -> 0 | T34: =+T$14/7 -> 0 | U34: =+U$14/7 -> 0 | V34: =+V$14/7/2 -> 0
B35: 2013 | C35: =-SUM(D35:Y35) -> 0
B36: 2014 | C36: =-SUM(D36:Y36) -> 0
B37: 2015 | C37: =-SUM(D37:Y37) -> 0
B38: 2016 | C38: =-SUM(D38:Y38) -> 0
B39: 2017 | C39: =-SUM(D39:AB39) -> 0
B40: 2018 | C40: =-SUM(D40:AB40) -> 0
A42: ST | B42: =SUM(D42:Y42) -> 0 | C42: =SUM(C16:C41) -> -1288891.3 | D42: =-SUM(D16:D41)+D14 -> 0 | E42: =-SUM(E16:E41)+E14 -> 0 | F42: =-SUM(F16:F41)+F14 -> 0 | G42: =-SUM(G16:G41)+G14 -> 0 | H42: =-SUM(H16:H41)+H14 -> 0 | I42: =-SUM(I16:I41)+I14 -> 0 | J42: =-SUM(J16:J41)+J14 -> 0 | K42: =-SUM(K16:K41)+K14 -> 0 | ... AB42: =-SUM(AB16:AB41)+AB14 -> 0
A44: Net Book Value | C44: =+C14+C42 -> 0
N47: =SUM(E32:E47) -> 0

Sheet 111
A1: ABS EQUIPMENT LEASING INC.
A2: Select Equipment List
A3: Source: F 2009 Fixed Asset Summary
R4: Total | T4: Book
A5: Description | B5: Asset # | C5: Serial # | R5: Costs | S5: Depr. | T5: Value
A6: TOSHIBA - BSF 150B NEW | B6: 111
R7: =+C14 -> 2296413.2 | S7: =+-C48 -> 2245293.5 | T7: =+R7-S7 -> 51119.653
A11: Location: | B11: MISS | C11: A2
A13: Purchased Year Ending | C13: Total | D13: 1994 | E13: =D13+1 -> 1995 | F13: =E13+1 -> 1996 | G13: =F13+1 -> 1997 | H13: =G13+1 -> 1998 | I13: =H13+1 -> 1999 | J13: =I13+1 -> 2000 | K13: =J13+1 -> 2001 | L13: =K13+1 -> 2002 | ... AH13: =AG13+1 -> 2024
A14: Purchases (Fiscal Yr.) | C14: =SUM(D14:AH14) -> 2296413.2 | J14: 2216893.7 | AF14: 79519.46
A15: =IF(+C14-'Equip Review 032310'!Y29=0,"ok","check") -> check
A16: Depreciation | B16: 1994 | C16: =-SUM(D16:AH16) -> 0 | D16: =+D$14/7/2 -> 0
B17: =B16+1 -> 1995 | C17: =-SUM(D17:AH17) -> 0 | D17: =+D$14/7 -> 0 | E17: =+E$14/7/2 -> 0
B18: =B17+1 -> 1996 | C18: =-SUM(D18:AH18) -> 0 | D18: =+D17 -> 0 | E18: =+E$14/7 -> 0 | F18: =+F$14/7/2 -> 0
B19: =B18+1 -> 1997 | C19: =-SUM(D19:AH19) -> 0 | D19: =+D18 -> 0 | E19: =+E18 -> 0 | F19: =+F$14/7 -> 0 | G19: =+G$14/7/2 -> 0
B20: =B19+1 -> 1998 | C20: =-SUM(D20:AH20) -> 0 | D20: =+D19 -> 0 | E20: =+E19 -> 0 | F20: =+F19 -> 0 | G20: =+G$14/7 -> 0 | H20: =+H$14/7/2 -> 0
B21: =B20+1 -> 1999 | C21: =-SUM(D21:AH21) -> 0 | D21: =+D20 -> 0 | E21: =+E20 -> 0 | F21: =+F20 -> 0 | G21: =+G20 -> 0 | H21: =+H$14/7 -> 0 | I21: =+I$14/7/2 -> 0
B22: =B21+1 -> 2000 | C22: =-SUM(D22:AH22) -> -158349.55 | D22: =+D21 -> 0 | E22: =+E21 -> 0 | F22: =+F21 -> 0 | G22: =+G21 -> 0 | H22: =+H21 -> 0 | I22: =+I$14/7 -> 0 | J22: =+J$14/7/2 -> 158349.55
B23: =B22+1 -> 2001 | C23: =-SUM(D23:AH23) -> -316699.1 | D23: =+D$14/7/2 -> 0 | E23: =+E22 -> 0 | F23: =+F22 -> 0 | G23: =+G22 -> 0 | H23: =+H22 -> 0 | I23: =+I22 -> 0 | J23: =+J$14/7 -> 316699.1 | K23: =+K$14/7/2 -> 0
B24: =B23+1 -> 2002 | C24: =-SUM(D24:AH24) -> -316699.1 | E24: =+E$14/7/2 -> 0 | F24: =+F23 -> 0 | G24: =+G23 -> 0 | H24: =+H23 -> 0 | I24: =+I23 -> 0 | J24: =+J23 -> 316699.1 | K24: =+K$14/7 -> 0 | L24: =+L$14/7/2 -> 0
B25: =B24+1 -> 2003 | C25: =-SUM(D25:AH25) -> -316699.1 | F25: =+F$14/7/2 -> 0 | G25: =+G24 -> 0 | H25: =+H24 -> 0 | I25: =+I24 -> 0 | J25: =+J24 -> 316699.1 | K25: =+K24 -> 0 | L25: =+L$14/7 -> 0 | M25: =+M$14/7/2 -> 0
B26: =B25+1 -> 2004 | C26: =-SUM(D26:AH26) -> -316699.1 | G26: =+G$14/7/2 -> 0 | H26: =+H25 -> 0 | I26: =+I25 -> 0 | J26: =+J25 -> 316699.1 | K26: =+K25 -> 0 | L26: =+L25 -> 0 | M26: =+M$14/7 -> 0 | N26: =+N$14/7/2 -> 0
B27: =B26+1 -> 2005 | C27: =-SUM(D27:AH27) -> -316699.1 | H27: =+H$14/7/2 -> 0 | I27: =+I26 -> 0 | J27: =+J26 -> 316699.1 | K27: =+K26 -> 0 | L27: =+L26 -> 0 | M27: =+M26 -> 0 | N27: =+N$14/7 -> 0 | O27: =+O$14/7/2 -> 0
B28: =B27+1 -> 2006 | C28: =-SUM(D28:AH28) -> -316699.1 | I28: =+I$14/7/2 -> 0 | J28: =+J27 -> 316699.1 | K28: =+K27 -> 0 | L28: =+L27 -> 0 | M28: =+M27 -> 0 | N28: =+N27 -> 0 | O28: =+O$14/7 -> 0 | P28: =+P$14/7/2 -> 0
B29: =B28+1 -> 2007 | C29: =-SUM(D29:AH29) -> -158349.55 | J29: =+J$14/7/2 -> 158349.55 | K29: =+K28 -> 0 | L29: =+L28 -> 0 | M29: =+M28 -> 0 | N29: =+N28 -> 0 | O29: =+O28 -> 0 | P29: =+P$14/7 -> 0 | Q29: =+Q$14/7/2 -> 0
B30: =B29+1 -> 2008 | C30: =-SUM(D30:AH30) -> 0 | K30: =+K$14/7/2 -> 0 | L30: =+L29 -> 0 | M30: =+M29 -> 0 | N30: =+N29 -> 0 | O30: =+O29 -> 0 | P30: =+P29 -> 0 | Q30: =+Q$14/7 -> 0 | R30: =+R$14/7/2 -> 0
B31: =B30+1 -> 2009 | C31: =-SUM(D31:AH31) -> 0 | L31: =+L$14/7/2 -> 0 | M31: =+M30 -> 0 | N31: =+N30 -> 0 | O31: =+O30 -> 0 | P31: =+P30 -> 0 | Q31: =+Q30 -> 0 | R31: =+R$14/7 -> 0 | S31: =+S$14/7/2 -> 0
A32: To April 30th, 2010 | B32: =B31+1 -> 2010 | C32: =-SUM(D32:AH32) -> 0 | M32: =+M$14/7/2 -> 0 | N32: =+N31 -> 0 | O32: =+O31 -> 0 | P32: =+P31 -> 0 | Q32: =+Q31 -> 0 | R32: =+R31 -> 0 | S32: =+S$14/7 -> 0 | T32: =+T$14/7/2 -> 0
B33: =B32+1 -> 2011 | C33: =-SUM(D33:AH33) -> 0 | N33: =+N$14/7/2 -> 0 | O33: =+O32 -> 0 | P33: =+P32 -> 0 | Q33: =+Q32 -> 0 | R33: =+R32 -> 0 | S33: =+S32 -> 0 | T33: =+T$14/7 -> 0 | U33: =+U$14/7/2 -> 0
B34: =B33+1 -> 2012 | C34: =-SUM(D34:AH34) -> 0 | Q34: =+Q33 -> 0 | R34: =+R33 -> 0 | S34: =+S33 -> 0 | T34: =+T$14/7 -> 0 | U34: =+U$14/7 -> 0 | V34: =+V$14/7/2 -> 0
B35: =B34+1 -> 2013 | C35: =-SUM(D35:AH35) -> 0
B36: =B35+1 -> 2014 | C36: =-SUM(D36:AH36) -> 0
B37: =B36+1 -> 2015 | C37: =-SUM(D37:AH37) -> 0
B38: =B37+1 -> 2016 | C38: =-SUM(D38:AH38) -> 0
B39: =B38+1 -> 2017 | C39: =-SUM(D39:AH39) -> 0
B40: =B39+1 -> 2018 | C40: =-SUM(D40:AH40) -> 0
B41: =B40+1 -> 2019 | C41: =-SUM(D41:AH41) -> 0
B42: =B41+1 -> 2020 | C42: =-SUM(D42:AH42) -> 0
B43: =B42+1 -> 2021 | C43: =-SUM(D43:AH43) -> 0
B44: =B43+1 -> 2022 | C44: =-SUM(D44:AH44) -> -5679.9614 | AF44: =$AF$14/7/2 -> 5679.9614
B45: =B44+1 -> 2023 | C45: =-SUM(D45:AH45) -> -11359.923 | AF45: =$AF$14/7 -> 11359.923
B46: =B45+1 -> 2024 | C46: =-SUM(D46:AH46) -> -11359.923 | AF46: =$AF$14/7 -> 11359.923
A48: ST | B48: =SUM(D48:AH48) -> 51119.653 | C48: =SUM(C16:C47) -> -2245293.5 | D48: =-SUM(D16:D47)+D14 -> 0 | E48: =-SUM(E16:E47)+E14 -> 0 | F48: =-SUM(F16:F47)+F14 -> 0 | G48: =-SUM(G16:G47)+G14 -> 0 | H48: =-SUM(H16:H47)+H14 -> 0 | I48: =-SUM(I16:I47)+I14 -> 0 | J48: =-SUM(J16:J47)+J14 -> 0 | K48: =-SUM(K16:K47)+K14 -> 0 | ... AF48: =-SUM(AF16:AF47)+AF14 -> 51119.653
A50: Net Book Value | C50: =+C14+C48 -> 51119.653
N53: =SUM(E32:E53) -> 0

Sheet 112
A1: ABS EQUIPMENT LEASING INC.
A2: Equipment List
A3: Source: F 2009 Fixed Asset Summary
R4: Total | T4: Book
A5: Description | B5: Asset # | C5: Serial # | R5: Costs | S5: Depr. | T5: Value
A7: TOSHIBA BTD-110 - R 16 | B7: 112 | C7: 143601 | R7: =+C14 -> 668543.53 | S7: =+-C42 -> 668543.53 | T7: =+R7-S7 -> 0
A8: HB&M
A9: TABLE TOP HORIZONTAL BORING & MILLING MACHINE WITH TOSNUC 888
A11: Location: | B11: MISS | C11: C1
A13: Purchased Year Ending | C13: Total | D13: 1994 | E13: 1995 | F13: 1996 | G13: 1997 | H13: 1998 | I13: 1999 | J13: 2000 | K13: 2001 | L13: 2002 | M13: 2003 | N13: 2004 | O13: 2005 | P13: 2006 | Q13: 2007 | R13: 2008 | S13: 2009 | T13: 2010 | U13: 2011 | V13: 2012 | W13: 2013 | X13: 2014 | Y13: 2015 | Z13: 2016 | AA13: 2017 | AB13: 2018
A14: Purchases (Fiscal Yr.) | C14: =SUM(D14:Y14) -> 668543.53 | D14: =+'Equip Review 032310'!G14 -> 0 | E14: =+'Equip Review 032310'!H14 -> 0 | F14: =+'Equip Review 032310'!I14 -> 0 | G14: =+'Equip Review 032310'!J14 -> 668543.53 | H14: =+'Equip Review 032310'!K14 -> 0 | I14: =+'Equip Review 032310'!L14 -> 0 | J14: =+'Equip Review 032310'!M14 -> 0 | K14: =+'Equip Review 032310'!N14 -> 0 | ... P14: =+'Equip Review 032310'!S14 -> 0 | Q14: =+'Equip Review 032310'!T14+'Equip Review 032310'!U14 -> 0 | R14: =+'Equip Review 032310'!V14 -> 0 | S14: =+'Equip Review 032310'!W14 -> 0
A15: =IF(+C14-'Equip Review 032310'!Y14=0,"ok","check") -> ok
A16: Depreciation | B16: 1994 | C16: =-SUM(D16:Y16) -> 0 | D16: =+D$14/7/2 -> 0
B17: 1995 | C17: =-SUM(D17:Y17) -> 0 | D17: =+D$14/7 -> 0 | E17: =+E$14/7/2 -> 0
B18: 1996 | C18: =-SUM(D18:Y18) -> 0 | D18: =+D17 -> 0 | E18: =+E$14/7 -> 0 | F18: =+F$14/7/2 -> 0
B19: 1997 | C19: =-SUM(D19:Y19) -> -47753.109 | D19: =+D18 -> 0 | E19: =+E18 -> 0 | F19: =+F$14/7 -> 0 | G19: =+G$14/7/2 -> 47753.109
B20: 1998 | C20: =-SUM(D20:Y20) -> -95506.219 | D20: =+D19 -> 0 | E20: =+E19 -> 0 | F20: =+F19 -> 0 | G20: =+G$14/7 -> 95506.219 | H20: =+H$14/7/2 -> 0
B21: 1999 | C21: =-SUM(D21:Y21) -> -95506.219 | D21: =+D20 -> 0 | E21: =+E20 -> 0 | F21: =+F20 -> 0 | G21: =+G20 -> 95506.219 | H21: =+H$14/7 -> 0 | I21: =+I$14/7/2 -> 0
B22: 2000 | C22: =-SUM(D22:Y22) -> -95506.219 | D22: =+D21 -> 0 | E22: =+E21 -> 0 | F22: =+F21 -> 0 | G22: =+G21 -> 95506.219 | H22: =+H21 -> 0 | I22: =+I$14/7 -> 0 | J22: =+J$14/7/2 -> 0
B23: 2001 | C23: =-SUM(D23:Y23) -> -95506.219 | D23: =+D$14/7/2 -> 0 | E23: =+E22 -> 0 | F23: =+F22 -> 0 | G23: =+G22 -> 95506.219 | H23: =+H22 -> 0 | I23: =+I22 -> 0 | J23: =+J$14/7 -> 0 | K23: =+K$14/7/2 -> 0
B24: 2002 | C24: =-SUM(D24:Y24) -> -95506.219 | E24: =+E$14/7/2 -> 0 | F24: =+F23 -> 0 | G24: =+G23 -> 95506.219 | H24: =+H23 -> 0 | I24: =+I23 -> 0 | J24: =+J23 -> 0 | K24: =+K$14/7 -> 0 | L24: =+L$14/7/2 -> 0
B25: 2003 | C25: =-SUM(D25:Y25) -> -95506.219 | F25: =+F$14/7/2 -> 0 | G25: =+G24 -> 95506.219 | H25: =+H24 -> 0 | I25: =+I24 -> 0 | J25: =+J24 -> 0 | K25: =+K24 -> 0 | L25: =+L$14/7 -> 0 | M25: =+M$14/7/2 -> 0
B26: 2004 | C26: =-SUM(D26:Y26) -> -47753.109 | G26: =+G$14/7/2 -> 47753.109 | H26: =+H25 -> 0 | I26: =+I25 -> 0 | J26: =+J25 -> 0 | K26: =+K25 -> 0 | L26: =+L25 -> 0 | M26: =+M$14/7 -> 0 | N26: =+N$14/7/2 -> 0
B27: 2005 | C27: =-SUM(D27:Y27) -> 0 | H27: =+H$14/7/2 -> 0 | I27: =+I26 -> 0 | J27: =+J26 -> 0 | K27: =+K26 -> 0 | L27: =+L26 -> 0 | M27: =+M26 -> 0 | N27: =+N$14/7 -> 0 | O27: =+O$14/7/2 -> 0
B28: 2006 | C28: =-SUM(D28:Y28) -> 0 | I28: =+I$14/7/2 -> 0 | J28: =+J27 -> 0 | K28: =+K27 -> 0 | L28: =+L27 -> 0 | M28: =+M27 -> 0 | N28: =+N27 -> 0 | O28: =+O$14/7 -> 0 | P28: =+P$14/7/2 -> 0
B29: 2007 | C29: =-SUM(D29:Y29) -> 0 | J29: =+J$14/7/2 -> 0 | K29: =+K28 -> 0 | L29: =+L28 -> 0 | M29: =+M28 -> 0 | N29: =+N28 -> 0 | O29: =+O28 -> 0 | P29: =+P$14/7 -> 0 | Q29: =+Q$14/7/2 -> 0
B30: 2008 | C30: =-SUM(D30:Y30) -> 0 | K30: =+K$14/7/2 -> 0 | L30: =+L29 -> 0 | M30: =+M29 -> 0 | N30: =+N29 -> 0 | O30: =+O29 -> 0 | P30: =+P29 -> 0 | Q30: =+Q$14/7 -> 0 | R30: =+R$14/7/2 -> 0
B31: 2009 | C31: =-SUM(D31:Y31) -> 0 | L31: =+L$14/7/2 -> 0 | M31: =+M30 -> 0 | N31: =+N30 -> 0 | O31: =+O30 -> 0 | P31: =+P30 -> 0 | Q31: =+Q30 -> 0 | R31: =+R$14/7 -> 0 | S31: =+S$14/7/2 -> 0
A32: To April 30th, 2010 | B32: 2010 | C32: =-SUM(D32:Y32) -> 0 | M32: =+M$14/7/2 -> 0 | N32: =+N31 -> 0 | O32: =+O31 -> 0 | P32: =+P31 -> 0 | Q32: =+Q31 -> 0 | R32: =+R31 -> 0 | S32: =+S$14/7 -> 0 | T32: =+T$14/7/2 -> 0
B33: 2011 | C33: =-SUM(D33:Y33) -> 0 | N33: =+N$14/7/2 -> 0 | O33: =+O32 -> 0 | P33: =+P32 -> 0 | Q33: =+Q32 -> 0 | R33: =+R32 -> 0 | S33: =+S32 -> 0 | T33: =+T$14/7 -> 0 | U33: =+U$14/7/2 -> 0
B34: 2012 | C34: =-SUM(D34:Y34) -> 0 | Q34: =+Q33 -> 0 | R34: =+R33 -> 0 | S34: =+S33 -> 0 | T34: =+T$14/7 -> 0 | U34: =+U$14/7 -> 0 | V34: =+V$14/7/2 -> 0
B35: 2013 | C35: =-SUM(D35:Y35) -> 0 | Q35: =+Q34 -> 0 | R35: =+R34 -> 0 | S35: =+S34 -> 0 | T35: =+T$14/7 -> 0 | U35: =+U$14/7 -> 0 | V35: =+V$14/7/2 -> 0
B36: 2014 | C36: =-SUM(D36:Y36) -> 0 | Q36: =+Q35 -> 0 | R36: =+R35 -> 0 | S36: =+S35 -> 0 | T36: =+T$14/7 -> 0 | U36: =+U$14/7 -> 0 | V36: =+V$14/7/2 -> 0
B37: 2015 | C37: =-SUM(D37:Y37) -> 0 | Q37: =+Q36 -> 0 | R37: =+R36 -> 0 | S37: =+S36 -> 0 | T37: =+T$14/7 -> 0 | U37: =+U$14/7 -> 0 | V37: =+V$14/7/2 -> 0
B38: 2016 | C38: =-SUM(D38:Y38) -> 0
B39: 2017 | C39: =-SUM(D39:AB39) -> 0
B40: 2018 | C40: =-SUM(D40:AB40) -> 0
A42: ST | B42: =SUM(D42:Y42) -> 0 | C42: =SUM(C16:C41) -> -668543.53 | D42: =-SUM(D16:D41)+D14 -> 0 | E42: =-SUM(E16:E41)+E14 -> 0 | F42: =-SUM(F16:F41)+F14 -> 0 | G42: =-SUM(G16:G41)+G14 -> 0 | H42: =-SUM(H16:H41)+H14 -> 0 | I42: =-SUM(I16:I41)+I14 -> 0 | J42: =-SUM(J16:J41)+J14 -> 0 | K42: =-SUM(K16:K41)+K14 -> 0 | ... AB42: =-SUM(AB16:AB41)+AB14 -> 0
A44: Net Book Value | C44: =+C14+C42 -> 0
N47: =SUM(E32:E47) -> 0

Sheet 113
A1: ABS EQUIPMENT LEASING INC.
A2: Equipment List
A3: Source: F 2009 Fixed Asset Summary
R4: Total | T4: Book
A5: Description | B5: Asset # | C5: Serial # | R5: Costs | S5: Depr. | T5: Value
A7: Toshiba BTD 200QF | B7: =+SUMMARY!A21 -> 113 | C7: 143601 | R7: =+C14 -> 685302.63 | S7: =+-C42 -> 685302.63 | T7: =+R7-S7 -> 0
A8: HB&M
A9: TABLE TOP HORIZONTAL BORING & MILLING MACHINE WITH TOSNUC 888
A11: Location: | B11: MISS | C11: A4
A13: Purchased Year Ending | C13: Total | D13: 1994 | E13: 1995 | F13: 1996 | G13: 1997 | H13: 1998 | I13: 1999 | J13: 2000 | K13: 2001 | L13: 2002 | M13: 2003 | N13: 2004 | O13: 2005 | P13: 2006 | Q13: 2007 | R13: 2008 | S13: 2009 | T13: 2010 | U13: 2011 | V13: 2012 | W13: 2013 | X13: 2014 | Y13: 2015 | Z13: 2016 | AA13: 2017 | AB13: 2018
A14: Purchases (Fiscal Yr.) | C14: =SUM(D14:Y14) -> 685302.63 | D14: =+'Equip Review 032310'!G22 -> 0 | E14: =+'Equip Review 032310'!H22 -> 0 | F14: =+'Equip Review 032310'!I22 -> 0 | G14: =+'Equip Review 032310'!J22 -> 0 | H14: =+'Equip Review 032310'!K22 -> 0 | I14: =+'Equip Review 032310'!L22 -> 0 | J14: =+'Equip Review 032310'!M22 -> 0 | K14: =+'Equip Review 032310'!N22 -> 685302.63 | ... P14: =+'Equip Review 032310'!S22 -> 0 | Q14: =+'Equip Review 032310'!T22+'Equip Review 032310'!U22 -> 0 | R14: =+'Equip Review 032310'!V22 -> 0 | S14: =+'Equip Review 032310'!W22 -> 0
A15: =IF(+C14-'Equip Review 032310'!Y22=0,"ok","check") -> ok
A16: Depreciation | B16: 1994 | C16: =-SUM(D16:Y16) -> 0 | D16: =+D$14/7/2 -> 0
B17: 1995 | C17: =-SUM(D17:Y17) -> 0 | D17: =+D$14/7 -> 0 | E17: =+E$14/7/2 -> 0
B18: 1996 | C18: =-SUM(D18:Y18) -> 0 | D18: =+D17 -> 0 | E18: =+E$14/7 -> 0 | F18: =+F$14/7/2 -> 0
B19: 1997 | C19: =-SUM(D19:Y19) -> 0 | D19: =+D18 -> 0 | E19: =+E18 -> 0 | F19: =+F$14/7 -> 0 | G19: =+G$14/7/2 -> 0
B20: 1998 | C20: =-SUM(D20:Y20) -> 0 | D20: =+D19 -> 0 | E20: =+E19 -> 0 | F20: =+F19 -> 0 | G20: =+G$14/7 -> 0 | H20: =+H$14/7/2 -> 0
B21: 1999 | C21: =-SUM(D21:Y21) -> 0 | D21: =+D20 -> 0 | E21: =+E20 -> 0 | F21: =+F20 -> 0 | G21: =+G20 -> 0 | H21: =+H$14/7 -> 0 | I21: =+I$14/7/2 -> 0
B22: 2000 | C22: =-SUM(D22:Y22) -> 0 | D22: =+D21 -> 0 | E22: =+E21 -> 0 | F22: =+F21 -> 0 | G22: =+G21 -> 0 | H22: =+H21 -> 0 | I22: =+I$14/7 -> 0 | J22: =+J$14/7/2 -> 0
B23: 2001 | C23: =-SUM(D23:Y23) -> -48950.188 | D23: =+D$14/7/2 -> 0 | E23: =+E22 -> 0 | F23: =+F22 -> 0 | G23: =+G22 -> 0 | H23: =+H22 -> 0 | I23: =+I22 -> 0 | J23: =+J$14/7 -> 0 | K23: =+K$14/7/2 -> 48950.188
B24: 2002 | C24: =-SUM(D24:Y24) -> -97900.376 | E24: =+E$14/7/2 -> 0 | F24: =+F23 -> 0 | G24: =+G23 -> 0 | H24: =+H23 -> 0 | I24: =+I23 -> 0 | J24: =+J23 -> 0 | K24: =+K$14/7 -> 97900.376 | L24: =+L$14/7/2 -> 0
B25: 2003 | C25: =-SUM(D25:Y25) -> -97900.376 | F25: =+F$14/7/2 -> 0 | G25: =+G24 -> 0 | H25: =+H24 -> 0 | I25: =+I24 -> 0 | J25: =+J24 -> 0 | K25: =+K24 -> 97900.376 | L25: =+L$14/7 -> 0 | M25: =+M$14/7/2 -> 0
B26: 2004 | C26: =-SUM(D26:Y26) -> -97900.376 | G26: =+G$14/7/2 -> 0 | H26: =+H25 -> 0 | I26: =+I25 -> 0 | J26: =+J25 -> 0 | K26: =+K25 -> 97900.376 | L26: =+L25 -> 0 | M26: =+M$14/7 -> 0 | N26: =+N$14/7/2 -> 0
B27: 2005 | C27: =-SUM(D27:Y27) -> -97900.376 | H27: =+H$14/7/2 -> 0 | I27: =+I26 -> 0 | J27: =+J26 -> 0 | K27: =+K26 -> 97900.376 | L27: =+L26 -> 0 | M27: =+M26 -> 0 | N27: =+N$14/7 -> 0 | O27: =+O$14/7/2 -> 0
B28: 2006 | C28: =-SUM(D28:Y28) -> -97900.376 | I28: =+I$14/7/2 -> 0 | J28: =+J27 -> 0 | K28: =+K27 -> 97900.376 | L28: =+L27 -> 0 | M28: =+M27 -> 0 | N28: =+N27 -> 0 | O28: =+O$14/7 -> 0 | P28: =+P$14/7/2 -> 0
B29: 2007 | C29: =-SUM(D29:Y29) -> -97900.376 | J29: =+J$14/7/2 -> 0 | K29: =+K28 -> 97900.376 | L29: =+L28 -> 0 | M29: =+M28 -> 0 | N29: =+N28 -> 0 | O29: =+O28 -> 0 | P29: =+P$14/7 -> 0 | Q29: =+Q$14/7/2 -> 0
B30: 2008 | C30: =-SUM(D30:Y30) -> -48950.188 | K30: =+K$14/7/2 -> 48950.188 | L30: =+L29 -> 0 | M30: =+M29 -> 0 | N30: =+N29 -> 0 | O30: =+O29 -> 0 | P30: =+P29 -> 0 | Q30: =+Q$14/7 -> 0 | R30: =+R$14/7/2 -> 0
B31: 2009 | C31: =-SUM(D31:Y31) -> 0 | L31: =+L$14/7/2 -> 0 | M31: =+M30 -> 0 | N31: =+N30 -> 0 | O31: =+O30 -> 0 | P31: =+P30 -> 0 | Q31: =+Q30 -> 0 | R31: =+R$14/7 -> 0 | S31: =+S$14/7/2 -> 0
A32: To April 30th, 2010 | B32: 2010 | C32: =-SUM(D32:Y32) -> 0 | M32: =+M$14/7/2 -> 0 | N32: =+N31 -> 0 | O32: =+O31 -> 0 | P32: =+P31 -> 0 | Q32: =+Q31 -> 0 | R32: =+R31 -> 0 | S32: =+S$14/7 -> 0 | T32: =+T$14/7/2 -> 0
B33: 2011 | C33: =-SUM(D33:Y33) -> 0 | N33: =+N$14/7/2 -> 0 | O33: =+O32 -> 0 | P33: =+P32 -> 0 | Q33: =+Q32 -> 0 | R33: =+R32 -> 0 | S33: =+S32 -> 0 | T33: =+T$14/7 -> 0 | U33: =+U$14/7/2 -> 0
B34: 2012 | C34: =-SUM(D34:Y34) -> 0 | Q34: =+Q33 -> 0 | R34: =+R33 -> 0 | S34: =+S33 -> 0 | T34: =+T$14/7 -> 0 | U34: =+U$14/7 -> 0 | V34: =+V$14/7/2 -> 0
B35: 2013 | C35: =-SUM(D35:Y35) -> 0
B36: 2014 | C36: =-SUM(D36:Y36) -> 0
B37: 2015 | C37: =-SUM(D37:Y37) -> 0
B38: 2016 | C38: =-SUM(D38:Y38) -> 0
B39: 2017 | C39: =-SUM(D39:AB39) -> 0
B40: 2018 | C40: =-SUM(D40:AB40) -> 0
A42: ST | B42: =SUM(D42:Y42) -> 0 | C42: =SUM(C16:C41) -> -685302.63 | D42: =-SUM(D16:D41)+D14 -> 0 | E42: =-SUM(E16:E41)+E14 -> 0 | F42: =-SUM(F16:F41)+F14 -> 0 | G42: =-SUM(G16:G41)+G14 -> 0 | H42: =-SUM(H16:H41)+H14 -> 0 | I42: =-SUM(I16:I41)+I14 -> 0 | J42: =-SUM(J16:J41)+J14 -> 0 | K42: =-SUM(K16:K41)+K14 -> 0 | ... AB42: =-SUM(AB16:AB41)+AB14 -> 0
A44: Net Book Value | C44: =+C14+C42 -> 0
N47: =SUM(E32:E47) -> 0

Sheet 115
A1: ABS EQUIPMENT LEASING INC.
A2: Select Equipment List
A3: Source: F 2009 Fixed Asset Summary
R4: Total | T4: Book
A5: Description | B5: Asset # | C5: Serial # | R5: Costs | S5: Depr. | T5: Value
A6: Welding Positioner - 3100 | B6: 115
R7: =+C14 -> 38496.5 | S7: =+-C48 -> 38496.5 | T7: =+R7-S7 -> 0
A11: Location: | B11: MISS | C11: 3100
A13: Purchased Year Ending | C13: Total | D13: 1994 | E13: 1995 | F13: 1996 | G13: 1997 | H13: 1998 | I13: 1999 | J13: 2000 | K13: 2001 | L13: 2002 | M13: 2003 | N13: 2004 | O13: =N13+1 -> 2005 | P13: =O13+1 -> 2006 | Q13: =P13+1 -> 2007 | R13: =Q13+1 -> 2008 | S13: =R13+1 -> 2009 | T13: =S13+1 -> 2010 | U13: =T13+1 -> 2011 | V13: =U13+1 -> 2012 | ... AH13: =AG13+1 -> 2024
A14: Purchases (Fiscal Yr.) | C14: =SUM(D14:AH14) -> 38496.5 | S14: 19120.07 | Z14: 19376.43
A15: =IF(+C14-'Equip Review 032310'!Y29=0,"ok","check") -> check
A16: Depreciation | B16: 1994 | C16: =-SUM(D16:AH16) -> 0 | D16: =+D$14/7/2 -> 0
B17: =B16+1 -> 1995 | C17: =-SUM(D17:AH17) -> 0 | D17: =+D$14/7 -> 0 | E17: =+E$14/7/2 -> 0
B18: =B17+1 -> 1996 | C18: =-SUM(D18:AH18) -> 0 | D18: =+D17 -> 0 | E18: =+E$14/7 -> 0 | F18: =+F$14/7/2 -> 0
B19: =B18+1 -> 1997 | C19: =-SUM(D19:AH19) -> 0 | D19: =+D18 -> 0 | E19: =+E18 -> 0 | F19: =+F$14/7 -> 0 | G19: =+G$14/7/2 -> 0
B20: =B19+1 -> 1998 | C20: =-SUM(D20:AH20) -> 0 | D20: =+D19 -> 0 | E20: =+E19 -> 0 | F20: =+F19 -> 0 | G20: =+G$14/7 -> 0 | H20: =+H$14/7/2 -> 0
B21: =B20+1 -> 1999 | C21: =-SUM(D21:AH21) -> 0 | D21: =+D20 -> 0 | E21: =+E20 -> 0 | F21: =+F20 -> 0 | G21: =+G20 -> 0 | H21: =+H$14/7 -> 0 | I21: =+I$14/7/2 -> 0
B22: =B21+1 -> 2000 | C22: =-SUM(D22:AH22) -> 0 | D22: =+D21 -> 0 | E22: =+E21 -> 0 | F22: =+F21 -> 0 | G22: =+G21 -> 0 | H22: =+H21 -> 0 | I22: =+I$14/7 -> 0 | J22: =+J$14/7/2 -> 0
B23: =B22+1 -> 2001 | C23: =-SUM(D23:AH23) -> 0 | D23: =+D$14/7/2 -> 0 | E23: =+E22 -> 0 | F23: =+F22 -> 0 | G23: =+G22 -> 0 | H23: =+H22 -> 0 | I23: =+I22 -> 0 | J23: =+J$14/7 -> 0 | K23: =+K$14/7/2 -> 0
B24: =B23+1 -> 2002 | C24: =-SUM(D24:AH24) -> 0 | E24: =+E$14/7/2 -> 0 | F24: =+F23 -> 0 | G24: =+G23 -> 0 | H24: =+H23 -> 0 | I24: =+I23 -> 0 | J24: =+J23 -> 0 | K24: =+K$14/7 -> 0 | L24: =+L$14/7/2 -> 0
B25: =B24+1 -> 2003 | C25: =-SUM(D25:AH25) -> 0 | F25: =+F$14/7/2 -> 0 | G25: =+G24 -> 0 | H25: =+H24 -> 0 | I25: =+I24 -> 0 | J25: =+J24 -> 0 | K25: =+K24 -> 0 | L25: =+L$14/7 -> 0 | M25: =+M$14/7/2 -> 0
B26: =B25+1 -> 2004 | C26: =-SUM(D26:AH26) -> 0 | G26: =+G$14/7/2 -> 0 | H26: =+H25 -> 0 | I26: =+I25 -> 0 | J26: =+J25 -> 0 | K26: =+K25 -> 0 | L26: =+L25 -> 0 | M26: =+M$14/7 -> 0 | N26: =+N$14/7/2 -> 0
B27: =B26+1 -> 2005 | C27: =-SUM(D27:AH27) -> 0 | H27: =+H$14/7/2 -> 0 | I27: =+I26 -> 0 | J27: =+J26 -> 0 | K27: =+K26 -> 0 | L27: =+L26 -> 0 | M27: =+M26 -> 0 | N27: =+N$14/7 -> 0 | O27: =+O$14/7/2 -> 0
B28: =B27+1 -> 2006 | C28: =-SUM(D28:AH28) -> 0 | I28: =+I$14/7/2 -> 0 | J28: =+J27 -> 0 | K28: =+K27 -> 0 | L28: =+L27 -> 0 | M28: =+M27 -> 0 | N28: =+N27 -> 0 | O28: =+O$14/7 -> 0 | P28: =+P$14/7/2 -> 0
B29: =B28+1 -> 2007 | C29: =-SUM(D29:AH29) -> 0 | J29: =+J$14/7/2 -> 0 | K29: =+K28 -> 0 | L29: =+L28 -> 0 | M29: =+M28 -> 0 | N29: =+N28 -> 0 | O29: =+O28 -> 0 | P29: =+P$14/7 -> 0 | Q29: =+Q$14/7/2 -> 0
B30: =B29+1 -> 2008 | C30: =-SUM(D30:AH30) -> 0 | K30: =+K$14/7/2 -> 0 | L30: =+L29 -> 0 | M30: =+M29 -> 0 | N30: =+N29 -> 0 | O30: =+O29 -> 0 | P30: =+P29 -> 0 | Q30: =+Q$14/7 -> 0 | R30: =+R$14/7/2 -> 0
B31: =B30+1 -> 2009 | C31: =-SUM(D31:AH31) -> -1365.7193 | L31: =+L$14/7/2 -> 0 | M31: =+M30 -> 0 | N31: =+N30 -> 0 | O31: =+O30 -> 0 | P31: =+P30 -> 0 | Q31: =+Q30 -> 0 | R31: =+R$14/7 -> 0 | S31: =+S$14/7/2 -> 1365.7193
A32: To April 30th, 2010 | B32: =B31+1 -> 2010 | C32: =-SUM(D32:AH32) -> -2731.4386 | M32: =+M$14/7/2 -> 0 | N32: =+N31 -> 0 | O32: =+O31 -> 0 | P32: =+P31 -> 0 | Q32: =+Q31 -> 0 | R32: =+R31 -> 0 | S32: =+S$14/7 -> 2731.4386 | T32: =+T$14/7/2 -> 0
B33: =B32+1 -> 2011 | C33: =-SUM(D33:AH33) -> -2731.4386 | N33: =+N$14/7/2 -> 0 | O33: =+O32 -> 0 | P33: =+P32 -> 0 | Q33: =+Q32 -> 0 | R33: =+R32 -> 0 | S33: =+S32 -> 2731.4386 | T33: =+T$14/7 -> 0 | U33: =+U$14/7/2 -> 0
B34: =B33+1 -> 2012 | C34: =-SUM(D34:AH34) -> -2731.4386 | Q34: =+Q33 -> 0 | R34: =+R33 -> 0 | S34: =+S33 -> 2731.4386 | T34: =+T$14/7 -> 0 | U34: =+U$14/7 -> 0 | V34: =+V$14/7/2 -> 0
B35: =B34+1 -> 2013 | C35: =-SUM(D35:AH35) -> -2731.4386 | S35: =+S34 -> 2731.4386
B36: =B35+1 -> 2014 | C36: =-SUM(D36:AH36) -> -2731.4386 | S36: =+S35 -> 2731.4386
B37: =B36+1 -> 2015 | C37: =-SUM(D37:AH37) -> -2731.4386 | S37: =S36 -> 2731.4386
B38: =B37+1 -> 2016 | C38: =-SUM(D38:AH38) -> -2749.75 | S38: =S37/2 -> 1365.7193 | Z38: =$Z$14/7/2 -> 1384.0307
B39: =B38+1 -> 2017 | C39: =-SUM(D39:AH39) -> -2768.0614 | Z39: =$Z$14/7 -> 2768.0614
B40: =B39+1 -> 2018 | C40: =-SUM(D40:AH40) -> -2768.0614 | Z40: =$Z$14/7 -> 2768.0614
B41: =B40+1 -> 2019 | C41: =-SUM(D41:AH41) -> -2768.0614 | Z41: =$Z$14/7 -> 2768.0614
B42: =B41+1 -> 2020 | C42: =-SUM(D42:AH42) -> -2768.0614 | Z42: =$Z$14/7 -> 2768.0614
B43: =B42+1 -> 2021 | C43: =-SUM(D43:AH43) -> -2768.0614 | Z43: =$Z$14/7 -> 2768.0614
B44: =B43+1 -> 2022 | C44: =-SUM(D44:AH44) -> -2768.0614 | Z44: =$Z$14/7 -> 2768.0614
B45: =B44+1 -> 2023 | C45: =-SUM(D45:AH45) -> -1384.0307 | Z45: =$Z$14/7/2 -> 1384.0307
B46: =B45+1 -> 2024 | C46: =-SUM(D46:AH46) -> 0
A48: ST | B48: =SUM(D48:AH48) -> 0 | C48: =SUM(C16:C47) -> -38496.5 | D48: =-SUM(D16:D47)+D14 -> 0 | E48: =-SUM(E16:E47)+E14 -> 0 | F48: =-SUM(F16:F47)+F14 -> 0 | G48: =-SUM(G16:G47)+G14 -> 0 | H48: =-SUM(H16:H47)+H14 -> 0 | I48: =-SUM(I16:I47)+I14 -> 0 | J48: =-SUM(J16:J47)+J14 -> 0 | K48: =-SUM(K16:K47)+K14 -> 0 | ... AH48: =-SUM(AH16:AH47)+AH14 -> 0
A50: Net Book Value | C50: =+C14+C48 -> 0

Sheet 117
A1: ABS EQUIPMENT LEASING INC.
A2: Equipment List
A3: Source: F 2009 Fixed Asset Summary
R4: Total | T4: Book
A5: Description | B5: Asset # | C5: Serial # | R5: Costs | S5: Depr. | T5: Value
A6: =+SUMMARY!B23 -> TOSHIBA BTD-13F.R22 | B6: =+SUMMARY!A23 -> 117 | C6: =+SUMMARY!D23 -> 144926
A7: =+SUMMARY!C23 -> 0 | R7: =+C14 -> 749420.97 | S7: =+-C43 -> 749420.97 | T7: =+R7-S7 -> 0
B11: =+SUMMARY!F23 -> MISS | C11: B
A13: Purchased Year Ending | C13: Total | D13: 1994 | E13: 1995 | F13: 1996 | G13: 1997 | H13: 1998 | I13: 1999 | J13: 2000 | K13: 2001 | L13: 2002 | M13: 2003 | N13: 2004 | O13: 2005 | P13: 2006 | Q13: 2007 | R13: 2008 | S13: 2009 | T13: 2010 | U13: 2011 | V13: 2012 | W13: 2013 | X13: 2014 | Y13: 2015 | Z13: 2016 | AA13: 2017 | AB13: 2018 | AC13: 2019
A14: Purchases (Fiscal Yr.) | C14: =SUM(D14:Y14) -> 749420.97 | Q14: 738809.94 | R14: 10611.03
A15: =IF(+C14-'Equip Review 032310'!Y29=0,"ok","check") -> check
A16: Depreciation | B16: 1994 | C16: =-SUM(D16:Y16) -> 0 | D16: =+D$14/7/2 -> 0
B17: 1995 | C17: =-SUM(D17:Y17) -> 0 | D17: =+D$14/7 -> 0 | E17: =+E$14/7/2 -> 0
B18: 1996 | C18: =-SUM(D18:Y18) -> 0 | D18: =+D17 -> 0 | E18: =+E$14/7 -> 0 | F18: =+F$14/7/2 -> 0
B19: 1997 | C19: =-SUM(D19:Y19) -> 0 | D19: =+D18 -> 0 | E19: =+E18 -> 0 | F19: =+F$14/7 -> 0 | G19: =+G$14/7/2 -> 0
B20: 1998 | C20: =-SUM(D20:Y20) -> 0 | D20: =+D19 -> 0 | E20: =+E19 -> 0 | F20: =+F19 -> 0 | G20: =+G$14/7 -> 0 | H20: =+H$14/7/2 -> 0
B21: 1999 | C21: =-SUM(D21:Y21) -> 0 | D21: =+D20 -> 0 | E21: =+E20 -> 0 | F21: =+F20 -> 0 | G21: =+G20 -> 0 | H21: =+H$14/7 -> 0 | I21: =+I$14/7/2 -> 0
B22: 2000 | C22: =-SUM(D22:Y22) -> 0 | D22: =+D21 -> 0 | E22: =+E21 -> 0 | F22: =+F21 -> 0 | G22: =+G21 -> 0 | H22: =+H21 -> 0 | I22: =+I$14/7 -> 0 | J22: =+J$14/7/2 -> 0
B23: 2001 | C23: =-SUM(D23:Y23) -> 0 | D23: =+D$14/7/2 -> 0 | E23: =+E22 -> 0 | F23: =+F22 -> 0 | G23: =+G22 -> 0 | H23: =+H22 -> 0 | I23: =+I22 -> 0 | J23: =+J$14/7 -> 0 | K23: =+K$14/7/2 -> 0
B24: 2002 | C24: =-SUM(D24:Y24) -> 0 | E24: =+E$14/7/2 -> 0 | F24: =+F23 -> 0 | G24: =+G23 -> 0 | H24: =+H23 -> 0 | I24: =+I23 -> 0 | J24: =+J23 -> 0 | K24: =+K$14/7 -> 0 | L24: =+L$14/7/2 -> 0
B25: 2003 | C25: =-SUM(D25:Y25) -> 0 | F25: =+F$14/7/2 -> 0 | G25: =+G24 -> 0 | H25: =+H24 -> 0 | I25: =+I24 -> 0 | J25: =+J24 -> 0 | K25: =+K24 -> 0 | L25: =+L$14/7 -> 0 | M25: =+M$14/7/2 -> 0
B26: 2004 | C26: =-SUM(D26:Y26) -> 0 | G26: =+G$14/7/2 -> 0 | H26: =+H25 -> 0 | I26: =+I25 -> 0 | J26: =+J25 -> 0 | K26: =+K25 -> 0 | L26: =+L25 -> 0 | M26: =+M$14/7 -> 0 | N26: =+N$14/7/2 -> 0
B27: 2005 | C27: =-SUM(D27:Y27) -> 0 | H27: =+H$14/7/2 -> 0 | I27: =+I26 -> 0 | J27: =+J26 -> 0 | K27: =+K26 -> 0 | L27: =+L26 -> 0 | M27: =+M26 -> 0 | N27: =+N$14/7 -> 0 | O27: =+O$14/7/2 -> 0
B28: 2006 | C28: =-SUM(D28:Y28) -> 0 | I28: =+I$14/7/2 -> 0 | J28: =+J27 -> 0 | K28: =+K27 -> 0 | L28: =+L27 -> 0 | M28: =+M27 -> 0 | N28: =+N27 -> 0 | O28: =+O$14/7 -> 0 | P28: =+P$14/7/2 -> 0
B29: 2007 | C29: =-SUM(D29:Y29) -> -52772.139 | J29: =+J$14/7/2 -> 0 | K29: =+K28 -> 0 | L29: =+L28 -> 0 | M29: =+M28 -> 0 | N29: =+N28 -> 0 | O29: =+O28 -> 0 | P29: =+P$14/7 -> 0 | Q29: =+Q$14/7/2 -> 52772.139
B30: 2008 | C30: =-SUM(D30:Y30) -> -106302.21 | K30: =+K$14/7/2 -> 0 | L30: =+L29 -> 0 | M30: =+M29 -> 0 | N30: =+N29 -> 0 | O30: =+O29 -> 0 | P30: =+P29 -> 0 | Q30: =+Q$14/7 -> 105544.28 | R30: =+R$14/7/2 -> 757.93071
B31: 2009 | C31: =-SUM(D31:Y31) -> -107060.14 | L31: =+L$14/7/2 -> 0 | M31: =+M30 -> 0 | N31: =+N30 -> 0 | O31: =+O30 -> 0 | P31: =+P30 -> 0 | Q31: =+Q30 -> 105544.28 | R31: =+R$14/7 -> 1515.8614 | S31: =+S$14/7/2 -> 0
A32: To April 30th, 2010 | B32: 2010 | C32: =-SUM(D32:Y32) -> -107060.14 | M32: =+M$14/7/2 -> 0 | N32: =+N31 -> 0 | O32: =+O31 -> 0 | P32: =+P31 -> 0 | Q32: =+Q31 -> 105544.28 | R32: =+R31 -> 1515.8614 | S32: =+S$14/7 -> 0 | T32: =+T$14/7/2 -> 0
B33: 2011 | C33: =-SUM(D33:Y33) -> -107060.14 | N33: =+N$14/7/2 -> 0 | O33: =+O32 -> 0 | P33: =+P32 -> 0 | Q33: =+Q32 -> 105544.28 | R33: =+R32 -> 1515.8614 | S33: =+S32 -> 0 | T33: =+T$14/7 -> 0 | U33: =+U$14/7/2 -> 0
B34: 2012 | C34: =-SUM(D34:Y34) -> -107060.14 | Q34: =+Q33 -> 105544.28 | R34: =+R33 -> 1515.8614 | S34: =+S33 -> 0 | T34: =+T$14/7 -> 0 | U34: =+U$14/7 -> 0 | V34: =+V$14/7/2 -> 0
B35: 2013 | C35: =-SUM(D35:Y35) -> -107060.14 | Q35: =+Q34 -> 105544.28 | R35: =+R34 -> 1515.8614
B36: 2014 | C36: =-SUM(D36:Y36) -> -54288 | Q36: =Q14/7/2 -> 52772.139 | R36: =+R35 -> 1515.8614
B37: 2015 | C37: =-SUM(D37:Y37) -> -757.93071 | R37: =R14/7/2 -> 757.93071
B38: 2016 | C38: =-SUM(D38:Y38) -> 0
B39: 2017 | C39: =-SUM(D39:AB39) -> 0
B40: 2018 | C40: =-SUM(D40:AB40) -> 0
B41: 2019
A43: ST | B43: =SUM(D43:Y43) -> 0 | C43: =SUM(C16:C42) -> -749420.97 | D43: =-SUM(D16:D42)+D14 -> 0 | E43: =-SUM(E16:E42)+E14 -> 0 | F43: =-SUM(F16:F42)+F14 -> 0 | G43: =-SUM(G16:G42)+G14 -> 0 | H43: =-SUM(H16:H42)+H14 -> 0 | I43: =-SUM(I16:I42)+I14 -> 0 | J43: =-SUM(J16:J42)+J14 -> 0 | K43: =-SUM(K16:K42)+K14 -> 0 | ... AC43: =-SUM(AC16:AC42)+AC14 -> 0
A45: Net Book Value | C45: =+C14+C43 -> 0
N48: =SUM(E32:E48) -> 0

Sheet 118
A1: ABS EQUIPMENT LEASING INC.
A2: Equipment List
A3: Source: F 2009 Fixed Asset Summary
R4: Total | T4: Book
A5: Description | B5: Asset # | C5: Serial # | R5: Costs | S5: Depr. | T5: Value
A6: =+SUMMARY!B24 -> TOSHIBA TMD - 16 | B6: =+SUMMARY!A24 -> 118 | C6: =+SUMMARY!D24 -> 420165
A7: =+SUMMARY!C24 -> CNC VBM | R7: =+C14 -> 691113.35 | S7: =+-C42 -> 691113.35 | T7: =+R7-S7 -> 0
B11: =+SUMMARY!F24 -> MISS
A13: Purchased Year Ending | C13: Total | D13: 1994 | E13: 1995 | F13: 1996 | G13: 1997 | H13: 1998 | I13: 1999 | J13: 2000 | K13: 2001 | L13: 2002 | M13: 2003 | N13: 2004 | O13: 2005 | P13: 2006 | Q13: 2007 | R13: 2008 | S13: 2009 | T13: 2010 | U13: 2011 | V13: 2012 | W13: 2013 | X13: 2014 | Y13: 2015 | Z13: 2016 | AA13: 2017 | AB13: 2018
A14: Purchases (Fiscal Yr.) | C14: =SUM(D14:Y14) -> 691113.35 | Q14: 691113.35
A15: =IF(+C14-'Equip Review 032310'!Y29=0,"ok","check") -> check
A16: Depreciation | B16: 1994 | C16: =-SUM(D16:Y16) -> 0 | D16: =+D$14/7/2 -> 0
B17: 1995 | C17: =-SUM(D17:Y17) -> 0 | D17: =+D$14/7 -> 0 | E17: =+E$14/7/2 -> 0
B18: 1996 | C18: =-SUM(D18:Y18) -> 0 | D18: =+D17 -> 0 | E18: =+E$14/7 -> 0 | F18: =+F$14/7/2 -> 0
B19: 1997 | C19: =-SUM(D19:Y19) -> 0 | D19: =+D18 -> 0 | E19: =+E18 -> 0 | F19: =+F$14/7 -> 0 | G19: =+G$14/7/2 -> 0
B20: 1998 | C20: =-SUM(D20:Y20) -> 0 | D20: =+D19 -> 0 | E20: =+E19 -> 0 | F20: =+F19 -> 0 | G20: =+G$14/7 -> 0 | H20: =+H$14/7/2 -> 0
B21: 1999 | C21: =-SUM(D21:Y21) -> 0 | D21: =+D20 -> 0 | E21: =+E20 -> 0 | F21: =+F20 -> 0 | G21: =+G20 -> 0 | H21: =+H$14/7 -> 0 | I21: =+I$14/7/2 -> 0
B22: 2000 | C22: =-SUM(D22:Y22) -> 0 | D22: =+D21 -> 0 | E22: =+E21 -> 0 | F22: =+F21 -> 0 | G22: =+G21 -> 0 | H22: =+H21 -> 0 | I22: =+I$14/7 -> 0 | J22: =+J$14/7/2 -> 0
B23: 2001 | C23: =-SUM(D23:Y23) -> 0 | D23: =+D$14/7/2 -> 0 | E23: =+E22 -> 0 | F23: =+F22 -> 0 | G23: =+G22 -> 0 | H23: =+H22 -> 0 | I23: =+I22 -> 0 | J23: =+J$14/7 -> 0 | K23: =+K$14/7/2 -> 0
B24: 2002 | C24: =-SUM(D24:Y24) -> 0 | E24: =+E$14/7/2 -> 0 | F24: =+F23 -> 0 | G24: =+G23 -> 0 | H24: =+H23 -> 0 | I24: =+I23 -> 0 | J24: =+J23 -> 0 | K24: =+K$14/7 -> 0 | L24: =+L$14/7/2 -> 0
B25: 2003 | C25: =-SUM(D25:Y25) -> 0 | F25: =+F$14/7/2 -> 0 | G25: =+G24 -> 0 | H25: =+H24 -> 0 | I25: =+I24 -> 0 | J25: =+J24 -> 0 | K25: =+K24 -> 0 | L25: =+L$14/7 -> 0 | M25: =+M$14/7/2 -> 0
B26: 2004 | C26: =-SUM(D26:Y26) -> 0 | G26: =+G$14/7/2 -> 0 | H26: =+H25 -> 0 | I26: =+I25 -> 0 | J26: =+J25 -> 0 | K26: =+K25 -> 0 | L26: =+L25 -> 0 | M26: =+M$14/7 -> 0 | N26: =+N$14/7/2 -> 0
B27: 2005 | C27: =-SUM(D27:Y27) -> 0 | H27: =+H$14/7/2 -> 0 | I27: =+I26 -> 0 | J27: =+J26 -> 0 | K27: =+K26 -> 0 | L27: =+L26 -> 0 | M27: =+M26 -> 0 | N27: =+N$14/7 -> 0 | O27: =+O$14/7/2 -> 0
B28: 2006 | C28: =-SUM(D28:Y28) -> 0 | I28: =+I$14/7/2 -> 0 | J28: =+J27 -> 0 | K28: =+K27 -> 0 | L28: =+L27 -> 0 | M28: =+M27 -> 0 | N28: =+N27 -> 0 | O28: =+O$14/7 -> 0 | P28: =+P$14/7/2 -> 0
B29: 2007 | C29: =-SUM(D29:Y29) -> -49365.239 | J29: =+J$14/7/2 -> 0 | K29: =+K28 -> 0 | L29: =+L28 -> 0 | M29: =+M28 -> 0 | N29: =+N28 -> 0 | O29: =+O28 -> 0 | P29: =+P$14/7 -> 0 | Q29: =+Q$14/7/2 -> 49365.239
B30: 2008 | C30: =-SUM(D30:Y30) -> -98730.479 | K30: =+K$14/7/2 -> 0 | L30: =+L29 -> 0 | M30: =+M29 -> 0 | N30: =+N29 -> 0 | O30: =+O29 -> 0 | P30: =+P29 -> 0 | Q30: =+Q$14/7 -> 98730.479 | R30: =+R$14/7/2 -> 0
B31: 2009 | C31: =-SUM(D31:Y31) -> -98730.479 | L31: =+L$14/7/2 -> 0 | M31: =+M30 -> 0 | N31: =+N30 -> 0 | O31: =+O30 -> 0 | P31: =+P30 -> 0 | Q31: =+Q30 -> 98730.479 | R31: =+R$14/7 -> 0 | S31: =+S$14/7/2 -> 0
A32: To April 30th, 2010 | B32: 2010 | C32: =-SUM(D32:Y32) -> -98730.479 | M32: =+M$14/7/2 -> 0 | N32: =+N31 -> 0 | O32: =+O31 -> 0 | P32: =+P31 -> 0 | Q32: =+Q31 -> 98730.479 | R32: =+R31 -> 0 | S32: =+S$14/7 -> 0 | T32: =+T$14/7/2 -> 0
B33: 2011 | C33: =-SUM(D33:Y33) -> -98730.479 | N33: =+N$14/7/2 -> 0 | O33: =+O32 -> 0 | P33: =+P32 -> 0 | Q33: =+Q32 -> 98730.479 | R33: =+R32 -> 0 | S33: =+S32 -> 0 | T33: =+T$14/7 -> 0 | U33: =+U$14/7/2 -> 0
B34: 2012 | C34: =-SUM(D34:Y34) -> -98730.479 | Q34: =+Q33 -> 98730.479 | R34: =+R33 -> 0 | S34: =+S33 -> 0 | T34: =+T$14/7 -> 0 | U34: =+U$14/7 -> 0 | V34: =+V$14/7/2 -> 0
B35: 2013 | C35: =-SUM(D35:Y35) -> -98730.479 | Q35: =+Q34 -> 98730.479
B36: 2014 | C36: =-SUM(D36:Y36) -> -49365.239 | Q36: =Q14/7/2 -> 49365.239
B37: 2015 | C37: =-SUM(D37:Y37) -> 0
B38: 2016 | C38: =-SUM(D38:Y38) -> 0
B39: 2017 | C39: =-SUM(D39:AB39) -> 0
B40: 2018 | C40: =-SUM(D40:AB40) -> 0
A42: ST | B42: =SUM(D42:Y42) -> 0 | C42: =SUM(C16:C41) -> -691113.35 | D42: =-SUM(D16:D41)+D14 -> 0 | E42: =-SUM(E16:E41)+E14 -> 0 | F42: =-SUM(F16:F41)+F14 -> 0 | G42: =-SUM(G16:G41)+G14 -> 0 | H42: =-SUM(H16:H41)+H14 -> 0 | I42: =-SUM(I16:I41)+I14 -> 0 | J42: =-SUM(J16:J41)+J14 -> 0 | K42: =-SUM(K16:K41)+K14 -> 0 | ... AB42: =-SUM(AB16:AB41)+AB14 -> 0
A44: Net Book Value | C44: =+C14+C42 -> 0
N47: =SUM(E32:E47) -> 0

Sheet 119
A1: ABS EQUIPMENT LEASING INC.
A2: Equipment List
A3: Source: F 2009 Fixed Asset Summary
R4: Total | T4: Book
A5: Description | B5: Asset # | C5: Serial # | R5: Costs | S5: Depr. | T5: Value
A6: =+SUMMARY!B25 -> TOSHIBA TUE-15 | B6: 119 | C6: =+SUMMARY!D25 -> 440376
A7: VBM | R7: =+C14 -> 442044 | S7: =+-C42 -> 442044 | T7: =+R7-S7 -> 0
A11: Location: | B11: =+SUMMARY!F25 -> MISS | C11: B | D11: 1495
A13: Purchased Year Ending | C13: Total | D13: 1994 | E13: 1995 | F13: 1996 | G13: 1997 | H13: 1998 | I13: 1999 | J13: 2000 | K13: 2001 | L13: 2002 | M13: 2003 | N13: 2004 | O13: 2005 | P13: 2006 | Q13: 2007 | R13: 2008 | S13: 2009 | T13: 2010 | U13: 2011 | V13: 2012 | W13: 2013 | X13: 2014 | Y13: 2015 | Z13: 2016 | AA13: 2017 | AB13: 2018
A14: Purchases (Fiscal Yr.) | C14: =SUM(D14:Y14) -> 442044 | S14: 442044
A15: =IF(+C14-'Equip Review 032310'!Y29=0,"ok","check") -> check
A16: Depreciation | B16: 1994 | C16: =-SUM(D16:Y16) -> 0 | D16: =+D$14/7/2 -> 0
B17: 1995 | C17: =-SUM(D17:Y17) -> 0 | D17: =+D$14/7 -> 0 | E17: =+E$14/7/2 -> 0
B18: 1996 | C18: =-SUM(D18:Y18) -> 0 | D18: =+D17 -> 0 | E18: =+E$14/7 -> 0 | F18: =+F$14/7/2 -> 0
B19: 1997 | C19: =-SUM(D19:Y19) -> 0 | D19: =+D18 -> 0 | E19: =+E18 -> 0 | F19: =+F$14/7 -> 0 | G19: =+G$14/7/2 -> 0
B20: 1998 | C20: =-SUM(D20:Y20) -> 0 | D20: =+D19 -> 0 | E20: =+E19 -> 0 | F20: =+F19 -> 0 | G20: =+G$14/7 -> 0 | H20: =+H$14/7/2 -> 0
B21: 1999 | C21: =-SUM(D21:Y21) -> 0 | D21: =+D20 -> 0 | E21: =+E20 -> 0 | F21: =+F20 -> 0 | G21: =+G20 -> 0 | H21: =+H$14/7 -> 0 | I21: =+I$14/7/2 -> 0
B22: 2000 | C22: =-SUM(D22:Y22) -> 0 | D22: =+D21 -> 0 | E22: =+E21 -> 0 | F22: =+F21 -> 0 | G22: =+G21 -> 0 | H22: =+H21 -> 0 | I22: =+I$14/7 -> 0 | J22: =+J$14/7/2 -> 0
B23: 2001 | C23: =-SUM(D23:Y23) -> 0 | D23: =+D$14/7/2 -> 0 | E23: =+E22 -> 0 | F23: =+F22 -> 0 | G23: =+G22 -> 0 | H23: =+H22 -> 0 | I23: =+I22 -> 0 | J23: =+J$14/7 -> 0 | K23: =+K$14/7/2 -> 0
B24: 2002 | C24: =-SUM(D24:Y24) -> 0 | E24: =+E$14/7/2 -> 0 | F24: =+F23 -> 0 | G24: =+G23 -> 0 | H24: =+H23 -> 0 | I24: =+I23 -> 0 | J24: =+J23 -> 0 | K24: =+K$14/7 -> 0 | L24: =+L$14/7/2 -> 0
B25: 2003 | C25: =-SUM(D25:Y25) -> 0 | F25: =+F$14/7/2 -> 0 | G25: =+G24 -> 0 | H25: =+H24 -> 0 | I25: =+I24 -> 0 | J25: =+J24 -> 0 | K25: =+K24 -> 0 | L25: =+L$14/7 -> 0 | M25: =+M$14/7/2 -> 0
B26: 2004 | C26: =-SUM(D26:Y26) -> 0 | G26: =+G$14/7/2 -> 0 | H26: =+H25 -> 0 | I26: =+I25 -> 0 | J26: =+J25 -> 0 | K26: =+K25 -> 0 | L26: =+L25 -> 0 | M26: =+M$14/7 -> 0 | N26: =+N$14/7/2 -> 0
B27: 2005 | C27: =-SUM(D27:Y27) -> 0 | H27: =+H$14/7/2 -> 0 | I27: =+I26 -> 0 | J27: =+J26 -> 0 | K27: =+K26 -> 0 | L27: =+L26 -> 0 | M27: =+M26 -> 0 | N27: =+N$14/7 -> 0 | O27: =+O$14/7/2 -> 0
B28: 2006 | C28: =-SUM(D28:Y28) -> 0 | I28: =+I$14/7/2 -> 0 | J28: =+J27 -> 0 | K28: =+K27 -> 0 | L28: =+L27 -> 0 | M28: =+M27 -> 0 | N28: =+N27 -> 0 | O28: =+O$14/7 -> 0 | P28: =+P$14/7/2 -> 0
B29: 2007 | C29: =-SUM(D29:Y29) -> 0 | J29: =+J$14/7/2 -> 0 | K29: =+K28 -> 0 | L29: =+L28 -> 0 | M29: =+M28 -> 0 | N29: =+N28 -> 0 | O29: =+O28 -> 0 | P29: =+P$14/7 -> 0 | Q29: =+Q$14/7/2 -> 0
B30: 2008 | C30: =-SUM(D30:Y30) -> 0 | K30: =+K$14/7/2 -> 0 | L30: =+L29 -> 0 | M30: =+M29 -> 0 | N30: =+N29 -> 0 | O30: =+O29 -> 0 | P30: =+P29 -> 0 | Q30: =+Q$14/7 -> 0 | R30: =+R$14/7/2 -> 0
B31: 2009 | C31: =-SUM(D31:Y31) -> -31574.571 | L31: =+L$14/7/2 -> 0 | M31: =+M30 -> 0 | N31: =+N30 -> 0 | O31: =+O30 -> 0 | P31: =+P30 -> 0 | Q31: =+Q30 -> 0 | R31: =+R$14/7 -> 0 | S31: =+S$14/7/2 -> 31574.571
A32: To April 30th, 2010 | B32: 2010 | C32: =-SUM(D32:Y32) -> -63149.143 | M32: =+M$14/7/2 -> 0 | N32: =+N31 -> 0 | O32: =+O31 -> 0 | P32: =+P31 -> 0 | Q32: =+Q31 -> 0 | R32: =+R31 -> 0 | S32: =+S$14/7 -> 63149.143 | T32: =+T$14/7/2 -> 0
B33: 2011 | C33: =-SUM(D33:Y33) -> -63149.143 | N33: =+N$14/7/2 -> 0 | O33: =+O32 -> 0 | P33: =+P32 -> 0 | Q33: =+Q32 -> 0 | R33: =+R32 -> 0 | S33: =+S32 -> 63149.143 | T33: =+T$14/7 -> 0 | U33: =+U$14/7/2 -> 0
B34: 2012 | C34: =-SUM(D34:Y34) -> -63149.143 | Q34: =+Q33 -> 0 | R34: =+R33 -> 0 | S34: =+S33 -> 63149.143 | T34: =+T$14/7 -> 0 | U34: =+U$14/7 -> 0 | V34: =+V$14/7/2 -> 0
B35: 2013 | C35: =-SUM(D35:Y35) -> -63149.143 | S35: =+S34 -> 63149.143
B36: 2014 | C36: =-SUM(D36:Y36) -> -63149.143 | S36: =+S35 -> 63149.143
B37: 2015 | C37: =-SUM(D37:Y37) -> -63149.143 | S37: =S36 -> 63149.143
B38: 2016 | C38: =-SUM(D38:Y38) -> -31574.571 | S38: =S37/2 -> 31574.571
B39: 2017 | C39: =-SUM(D39:AB39) -> 0
B40: 2018 | C40: =-SUM(D40:AB40) -> 0
A42: ST | B42: =SUM(D42:Y42) -> 0 | C42: =SUM(C16:C41) -> -442044 | D42: =-SUM(D16:D41)+D14 -> 0 | E42: =-SUM(E16:E41)+E14 -> 0 | F42: =-SUM(F16:F41)+F14 -> 0 | G42: =-SUM(G16:G41)+G14 -> 0 | H42: =-SUM(H16:H41)+H14 -> 0 | I42: =-SUM(I16:I41)+I14 -> 0 | J42: =-SUM(J16:J41)+J14 -> 0 | K42: =-SUM(K16:K41)+K14 -> 0 | ... AB42: =-SUM(AB16:AB41)+AB14 -> 0
A44: Net Book Value | C44: =+C14+C42 -> 0
N47: =SUM(E32:E47) -> 0

Sheet 122
A1: ABS EQUIPMENT LEASING INC.
A2: Equipment List
A3: Source: F 2009 Fixed Asset Summary
R4: Total | T4: Book
A5: Description | B5: Asset # | C5: Serial # | R5: Costs | S5: Depr. | T5: Value
A7: TOSHIBA BP 110 | B7: =+SUMMARY!A26 -> 122 | C7: 130255 | R7: =+C14 -> 583938.71 | S7: =+-C48 -> 583938.71 | T7: =+R7-S7 -> 0
A8: HORIZONTAL PLANER TYPE
A9: CNC BORING & MILLING
A11: Location: | B11: MISS | C11: C2
A13: Purchased Year Ending | C13: Total | D13: 1994 | E13: 1995 | F13: 1996 | G13: 1997 | H13: 1998 | I13: 1999 | J13: 2000 | K13: 2001 | L13: 2002 | M13: 2003 | N13: 2004 | O13: =N13+1 -> 2005 | P13: =O13+1 -> 2006 | Q13: =P13+1 -> 2007 | R13: =Q13+1 -> 2008 | S13: =R13+1 -> 2009 | T13: =S13+1 -> 2010 | U13: =T13+1 -> 2011 | V13: =U13+1 -> 2012 | ... AH13: =AG13+1 -> 2024
A14: Purchases (Fiscal Yr.) | C14: =SUM(D14:AH14) -> 583938.71 | H14: 579784.84 | Z14: 4153.87
A15: =IF(+C14-'Equip Review 032310'!Y15=0,"ok","check") -> check
A16: Depreciation | B16: 1994 | C16: =-SUM(D16:AH16) -> 0 | D16: =+D$14/7/2 -> 0
B17: =B16+1 -> 1995 | C17: =-SUM(D17:AH17) -> 0 | D17: =+D$14/7 -> 0 | E17: =+E$14/7/2 -> 0
B18: =B17+1 -> 1996 | C18: =-SUM(D18:AH18) -> 0 | D18: =+D17 -> 0 | E18: =+E$14/7 -> 0 | F18: =+F$14/7/2 -> 0
B19: =B18+1 -> 1997 | C19: =-SUM(D19:AH19) -> 0 | D19: =+D18 -> 0 | E19: =+E18 -> 0 | F19: =+F$14/7 -> 0 | G19: =+G$14/7/2 -> 0
B20: =B19+1 -> 1998 | C20: =-SUM(D20:AH20) -> -41413.203 | D20: =+D19 -> 0 | E20: =+E19 -> 0 | F20: =+F19 -> 0 | G20: =+G$14/7 -> 0 | H20: =+H$14/7/2 -> 41413.203
B21: =B20+1 -> 1999 | C21: =-SUM(D21:AH21) -> -82826.406 | D21: =+D20 -> 0 | E21: =+E20 -> 0 | F21: =+F20 -> 0 | G21: =+G20 -> 0 | H21: =+H$14/7 -> 82826.406 | I21: =+I$14/7/2 -> 0
B22: =B21+1 -> 2000 | C22: =-SUM(D22:AH22) -> -82826.406 | D22: =+D21 -> 0 | E22: =+E21 -> 0 | F22: =+F21 -> 0 | G22: =+G21 -> 0 | H22: =+H21 -> 82826.406 | I22: =+I$14/7 -> 0 | J22: =+J$14/7/2 -> 0
B23: =B22+1 -> 2001 | C23: =-SUM(D23:AH23) -> -82826.406 | D23: =+D$14/7/2 -> 0 | E23: =+E22 -> 0 | F23: =+F22 -> 0 | G23: =+G22 -> 0 | H23: =+H22 -> 82826.406 | I23: =+I22 -> 0 | J23: =+J$14/7 -> 0 | K23: =+K$14/7/2 -> 0
B24: =B23+1 -> 2002 | C24: =-SUM(D24:AH24) -> -82826.406 | E24: =+E$14/7/2 -> 0 | F24: =+F23 -> 0 | G24: =+G23 -> 0 | H24: =+H23 -> 82826.406 | I24: =+I23 -> 0 | J24: =+J23 -> 0 | K24: =+K$14/7 -> 0 | L24: =+L$14/7/2 -> 0
B25: =B24+1 -> 2003 | C25: =-SUM(D25:AH25) -> -82826.406 | F25: =+F$14/7/2 -> 0 | G25: =+G24 -> 0 | H25: =+H24 -> 82826.406 | I25: =+I24 -> 0 | J25: =+J24 -> 0 | K25: =+K24 -> 0 | L25: =+L$14/7 -> 0 | M25: =+M$14/7/2 -> 0
B26: =B25+1 -> 2004 | C26: =-SUM(D26:AH26) -> -82826.406 | G26: =+G$14/7/2 -> 0 | H26: =+H25 -> 82826.406 | I26: =+I25 -> 0 | J26: =+J25 -> 0 | K26: =+K25 -> 0 | L26: =+L25 -> 0 | M26: =+M$14/7 -> 0 | N26: =+N$14/7/2 -> 0
B27: =B26+1 -> 2005 | C27: =-SUM(D27:AH27) -> -41413.203 | H27: =+H$14/7/2 -> 41413.203 | I27: =+I26 -> 0 | J27: =+J26 -> 0 | K27: =+K26 -> 0 | L27: =+L26 -> 0 | M27: =+M26 -> 0 | N27: =+N$14/7 -> 0 | O27: =+O$14/7/2 -> 0
B28: =B27+1 -> 2006 | C28: =-SUM(D28:AH28) -> 0 | I28: =+I$14/7/2 -> 0 | J28: =+J27 -> 0 | K28: =+K27 -> 0 | L28: =+L27 -> 0 | M28: =+M27 -> 0 | N28: =+N27 -> 0 | O28: =+O$14/7 -> 0 | P28: =+P$14/7/2 -> 0
B29: =B28+1 -> 2007 | C29: =-SUM(D29:AH29) -> 0 | J29: =+J$14/7/2 -> 0 | K29: =+K28 -> 0 | L29: =+L28 -> 0 | M29: =+M28 -> 0 | N29: =+N28 -> 0 | O29: =+O28 -> 0 | P29: =+P$14/7 -> 0 | Q29: =+Q$14/7/2 -> 0
B30: =B29+1 -> 2008 | C30: =-SUM(D30:AH30) -> 0 | K30: =+K$14/7/2 -> 0 | L30: =+L29 -> 0 | M30: =+M29 -> 0 | N30: =+N29 -> 0 | O30: =+O29 -> 0 | P30: =+P29 -> 0 | Q30: =+Q$14/7 -> 0 | R30: =+R$14/7/2 -> 0
B31: =B30+1 -> 2009 | C31: =-SUM(D31:AH31) -> 0 | L31: =+L$14/7/2 -> 0 | M31: =+M30 -> 0 | N31: =+N30 -> 0 | O31: =+O30 -> 0 | P31: =+P30 -> 0 | Q31: =+Q30 -> 0 | R31: =+R$14/7 -> 0 | S31: =+S$14/7/2 -> 0
A32: To April 30th, 2010 | B32: =B31+1 -> 2010 | C32: =-SUM(D32:AH32) -> 0 | M32: =+M$14/7/2 -> 0 | N32: =+N31 -> 0 | O32: =+O31 -> 0 | P32: =+P31 -> 0 | Q32: =+Q31 -> 0 | R32: =+R31 -> 0 | S32: =+S$14/7 -> 0 | T32: =+T$14/7/2 -> 0
B33: =B32+1 -> 2011 | C33: =-SUM(D33:AH33) -> 0 | N33: =+N$14/7/2 -> 0 | O33: =+O32 -> 0 | P33: =+P32 -> 0 | Q33: =+Q32 -> 0 | R33: =+R32 -> 0 | S33: =+S32 -> 0 | T33: =+T$14/7 -> 0 | U33: =+U$14/7/2 -> 0
B34: =B33+1 -> 2012 | C34: =-SUM(D34:AH34) -> 0 | Q34: =+Q33 -> 0 | R34: =+R33 -> 0 | S34: =+S33 -> 0 | T34: =+T$14/7 -> 0 | U34: =+U$14/7 -> 0 | V34: =+V$14/7/2 -> 0
B35: =B34+1 -> 2013 | C35: =-SUM(D35:AH35) -> 0
B36: =B35+1 -> 2014 | C36: =-SUM(D36:AH36) -> 0
B37: =B36+1 -> 2015 | C37: =-SUM(D37:AH37) -> 0
B38: =B37+1 -> 2016 | C38: =-SUM(D38:AH38) -> -296.705 | Z38: =$Z$14/7/2 -> 296.705
B39: =B38+1 -> 2017 | C39: =-SUM(D39:AH39) -> -593.41 | Z39: =$Z$14/7 -> 593.41
B40: =B39+1 -> 2018 | C40: =-SUM(D40:AH40) -> -593.41 | Z40: =$Z$14/7 -> 593.41
B41: =B40+1 -> 2019 | C41: =-SUM(D41:AH41) -> -593.41 | Z41: =$Z$14/7 -> 593.41
B42: =B41+1 -> 2020 | C42: =-SUM(D42:AH42) -> -593.41 | Z42: =$Z$14/7 -> 593.41
B43: =B42+1 -> 2021 | C43: =-SUM(D43:AH43) -> -593.41 | Z43: =$Z$14/7 -> 593.41
B44: =B43+1 -> 2022 | C44: =-SUM(D44:AH44) -> -593.41 | Z44: =$Z$14/7 -> 593.41
B45: =B44+1 -> 2023 | C45: =-SUM(D45:AH45) -> -296.705 | Z45: =$Z$14/7/2 -> 296.705
B46: =B45+1 -> 2024 | C46: =-SUM(D46:AH46) -> 0
A48: ST | B48: =SUM(D48:AC48) -> 0 | C48: =SUM(C16:C47) -> -583938.71 | D48: =-SUM(D16:D47)+D14 -> 0 | E48: =-SUM(E16:E47)+E14 -> 0 | F48: =-SUM(F16:F47)+F14 -> 0 | G48: =-SUM(G16:G47)+G14 -> 0 | H48: =-SUM(H16:H47)+H14 -> 0 | I48: =-SUM(I16:I47)+I14 -> 0 | J48: =-SUM(J16:J47)+J14 -> 0 | K48: =-SUM(K16:K47)+K14 -> 0 | ... AC48: =-SUM(AC16:AC47)+AC14 -> 0
A50: Net Book Value | C50: =+C14+C48 -> 0
N53: =SUM(E32:E53) -> 0

Sheet 123
A1: ABS EQUIPMENT LEASING INC.
A2: Equipment List
A3: Source: F 2009 Fixed Asset Summary
R4: Total | T4: Book
A5: Description | B5: Asset # | C5: Serial # | R5: Costs | S5: Depr. | T5: Value
A7: DAEWOO ACE H100 | B7: =+SUMMARY!A368 -> 705 | C7: AH100067 | R7: =+C14 -> 709325.92 | S7: =+-C42 -> 709325.92 | T7: =+R7-S7 -> 0 | U7: SOLD
A9: HIGH PRECISION HD HMC
A11: Location: | B11: MISS | C11: C1
A13: Purchased Year Ending | C13: Total | D13: 1994 | E13: 1995 | F13: 1996 | G13: 1997 | H13: 1998 | I13: 1999 | J13: 2000 | K13: 2001 | L13: 2002 | M13: 2003 | N13: 2004 | O13: 2005 | P13: 2006 | Q13: 2007 | R13: 2008 | S13: 2009 | T13: 2010 | U13: 2011 | V13: 2012 | W13: 2013 | X13: 2014 | Y13: 2015 | Z13: 2016 | AA13: 2017 | AB13: 2018 | AC13: 2019
A14: Purchases (Fiscal Yr.) | C14: =SUM(D14:Y14) -> 709325.92 | H14: 691893.01 | I14: 6085.43 | O14: 11347.48
A15: =IF(+C14-'Equip Review 032310'!Y16=0,"ok","check") -> ok
A16: Depreciation | B16: 1994 | C16: =-SUM(D16:Y16) -> 0 | D16: =+D$14/7/2 -> 0
B17: 1995 | C17: =-SUM(D17:Y17) -> 0 | D17: =+D$14/7 -> 0 | E17: =+E$14/7/2 -> 0
B18: 1996 | C18: =-SUM(D18:Y18) -> 0 | D18: =+D17 -> 0 | E18: =+E$14/7 -> 0 | F18: =+F$14/7/2 -> 0
B19: 1997 | C19: =-SUM(D19:Y19) -> 0 | D19: =+D18 -> 0 | E19: =+E18 -> 0 | F19: =+F$14/7 -> 0 | G19: =+G$14/7/2 -> 0
B20: 1998 | C20: =-SUM(D20:Y20) -> -49420.929 | D20: =+D19 -> 0 | E20: =+E19 -> 0 | F20: =+F19 -> 0 | G20: =+G$14/7 -> 0 | H20: =+H$14/7/2 -> 49420.929
B21: 1999 | C21: =-SUM(D21:Y21) -> -99276.532 | D21: =+D20 -> 0 | E21: =+E20 -> 0 | F21: =+F20 -> 0 | G21: =+G20 -> 0 | H21: =+H$14/7 -> 98841.859 | I21: =+I$14/7/2 -> 434.67357
B22: 2000 | C22: =-SUM(D22:Y22) -> -99711.206 | D22: =+D21 -> 0 | E22: =+E21 -> 0 | F22: =+F21 -> 0 | G22: =+G21 -> 0 | H22: =+H21 -> 98841.859 | I22: =+I$14/7 -> 869.34714 | J22: =+J$14/7/2 -> 0
B23: 2001 | C23: =-SUM(D23:Y23) -> -99711.206 | D23: =+D$14/7/2 -> 0 | E23: =+E22 -> 0 | F23: =+F22 -> 0 | G23: =+G22 -> 0 | H23: =+H22 -> 98841.859 | I23: =+I22 -> 869.34714 | J23: =+J$14/7 -> 0 | K23: =+K$14/7/2 -> 0
B24: 2002 | C24: =-SUM(D24:Y24) -> -99711.206 | E24: =+E$14/7/2 -> 0 | F24: =+F23 -> 0 | G24: =+G23 -> 0 | H24: =+H23 -> 98841.859 | I24: =+I23 -> 869.34714 | J24: =+J23 -> 0 | K24: =+K$14/7 -> 0 | L24: =+L$14/7/2 -> 0
B25: 2003 | C25: =-SUM(D25:Y25) -> -99711.206 | F25: =+F$14/7/2 -> 0 | G25: =+G24 -> 0 | H25: =+H24 -> 98841.859 | I25: =+I24 -> 869.34714 | J25: =+J24 -> 0 | K25: =+K24 -> 0 | L25: =+L$14/7 -> 0 | M25: =+M$14/7/2 -> 0
B26: 2004 | C26: =-SUM(D26:Y26) -> -99711.206 | G26: =+G$14/7/2 -> 0 | H26: =+H25 -> 98841.859 | I26: =+I25 -> 869.34714 | J26: =+J25 -> 0 | K26: =+K25 -> 0 | L26: =+L25 -> 0 | M26: =+M$14/7 -> 0 | N26: =+N$14/7/2 -> 0
B27: 2005 | C27: =-SUM(D27:Y27) -> -51100.811 | H27: =+H$14/7/2 -> 49420.929 | I27: =+I26 -> 869.34714 | J27: =+J26 -> 0 | K27: =+K26 -> 0 | L27: =+L26 -> 0 | M27: =+M26 -> 0 | N27: =+N$14/7 -> 0 | O27: =+O$14/7/2 -> 810.53429
B28: 2006 | C28: =-SUM(D28:Y28) -> -2055.7421 | I28: =+I$14/7/2 -> 434.67357 | J28: =+J27 -> 0 | K28: =+K27 -> 0 | L28: =+L27 -> 0 | M28: =+M27 -> 0 | N28: =+N27 -> 0 | O28: =+O$14/7 -> 1621.0686 | P28: =+P$14/7/2 -> 0
B29: 2007 | C29: =-SUM(D29:Y29) -> -1621.0686 | J29: =+J$14/7/2 -> 0 | K29: =+K28 -> 0 | L29: =+L28 -> 0 | M29: =+M28 -> 0 | N29: =+N28 -> 0 | O29: =+O28 -> 1621.0686 | P29: =+P$14/7 -> 0 | Q29: =+Q$14/7/2 -> 0
B30: 2008 | C30: =-SUM(D30:Y30) -> -1621.0686 | K30: =+K$14/7/2 -> 0 | L30: =+L29 -> 0 | M30: =+M29 -> 0 | N30: =+N29 -> 0 | O30: =+O29 -> 1621.0686 | P30: =+P29 -> 0 | Q30: =+Q$14/7 -> 0 | R30: =+R$14/7/2 -> 0
B31: 2009 | C31: =-SUM(D31:Y31) -> -1621.0686 | L31: =+L$14/7/2 -> 0 | M31: =+M30 -> 0 | N31: =+N30 -> 0 | O31: =+O30 -> 1621.0686 | P31: =+P30 -> 0 | Q31: =+Q30 -> 0 | R31: =+R$14/7 -> 0 | S31: =+S$14/7/2 -> 0
A32: To April 30th, 2010 | B32: 2010 | C32: =-SUM(D32:Y32) -> -1621.0686 | M32: =+M$14/7/2 -> 0 | N32: =+N31 -> 0 | O32: =+O31 -> 1621.0686 | P32: =+P31 -> 0 | Q32: =+Q31 -> 0 | R32: =+R31 -> 0 | S32: =+S$14/7 -> 0 | T32: =+T$14/7/2 -> 0
B33: 2011 | C33: =-SUM(D33:Y33) -> -1621.0686 | N33: =+N$14/7/2 -> 0 | O33: =+O32 -> 1621.0686 | P33: =+P32 -> 0 | Q33: =+Q32 -> 0 | R33: =+R32 -> 0 | S33: =+S32 -> 0 | T33: =+T$14/7 -> 0 | U33: =+U$14/7/2 -> 0
B34: 2012 | C34: =-SUM(D34:Y34) -> -810.53429 | O34: =+O$14/7/2 -> 810.53429 | Q34: =+Q33 -> 0 | R34: =+R33 -> 0 | S34: =+S33 -> 0 | T34: =+T$14/7 -> 0 | U34: =+U$14/7 -> 0 | V34: =+V$14/7/2 -> 0
B35: 2013 | C35: =-SUM(D35:Y35) -> 0
B36: 2014 | C36: =-SUM(D36:Y36) -> 0
B37: 2015 | C37: =-SUM(D37:Y37) -> 0
B38: 2016 | C38: =-SUM(D38:Y38) -> 0
B39: 2017 | C39: =-SUM(D39:AB39) -> 0
B40: 2018 | C40: =-SUM(D40:AB40) -> 0
A42: ST | B42: =SUM(D42:Y42) -> 0 | C42: =SUM(C16:C41) -> -709325.92 | D42: =-SUM(D16:D41)+D14 -> 0 | E42: =-SUM(E16:E41)+E14 -> 0 | F42: =-SUM(F16:F41)+F14 -> 0 | G42: =-SUM(G16:G41)+G14 -> 0 | H42: =-SUM(H16:H41)+H14 -> 0 | I42: =-SUM(I16:I41)+I14 -> 0 | J42: =-SUM(J16:J41)+J14 -> 0 | K42: =-SUM(K16:K41)+K14 -> 0 | ... AC42: =-SUM(AC16:AC41)+AC14 -> 0
A44: Net Book Value | C44: =+C14+C42 -> 0
N47: =SUM(E32:E47) -> 0

Sheet 124
A1: ABS EQUIPMENT LEASING INC.
A2: Equipment List
A3: Source: F 2009 Fixed Asset Summary
R4: Total | T4: Book
A5: Description | B5: Asset # | C5: Serial # | R5: Costs | S5: Depr. | T5: Value
A6: =+SUMMARY!B27 -> DAEWOO ACE V850 | B6: =+SUMMARY!A27 -> 124 | C6: V850075
A7: =+SUMMARY!C27 -> ACE V850 | R7: =+C14 -> 342161.39 | S7: =+-C42 -> 342161.39 | T7: =+R7-S7 -> 0
A11: Location: | B11: =+SUMMARY!F27 -> MISS | C11: C2
A13: Purchased Year Ending | C13: Total | D13: 1994 | E13: 1995 | F13: 1996 | G13: 1997 | H13: 1998 | I13: 1999 | J13: 2000 | K13: 2001 | L13: 2002 | M13: 2003 | N13: 2004 | O13: 2005 | P13: 2006 | Q13: 2007 | R13: 2008 | S13: 2009 | T13: 2010 | U13: 2011 | V13: 2012 | W13: 2013 | X13: 2014 | Y13: 2015 | Z13: 2016 | AA13: 2017 | AB13: 2018
A14: Purchases (Fiscal Yr.) | C14: =SUM(D14:Y14) -> 342161.39 | H14: 342161.39
A15: =IF(+C14-'Equip Review 032310'!Y29=0,"ok","check") -> check
A16: Depreciation | B16: 1994 | C16: =-SUM(D16:Y16) -> 0 | D16: =+D$14/7/2 -> 0
B17: 1995 | C17: =-SUM(D17:Y17) -> 0 | D17: =+D$14/7 -> 0 | E17: =+E$14/7/2 -> 0
B18: 1996 | C18: =-SUM(D18:Y18) -> 0 | D18: =+D17 -> 0 | E18: =+E$14/7 -> 0 | F18: =+F$14/7/2 -> 0
B19: 1997 | C19: =-SUM(D19:Y19) -> 0 | D19: =+D18 -> 0 | E19: =+E18 -> 0 | F19: =+F$14/7 -> 0 | G19: =+G$14/7/2 -> 0
B20: 1998 | C20: =-SUM(D20:Y20) -> -24440.099 | D20: =+D19 -> 0 | E20: =+E19 -> 0 | F20: =+F19 -> 0 | G20: =+G$14/7 -> 0 | H20: =+H$14/7/2 -> 24440.099
B21: 1999 | C21: =-SUM(D21:Y21) -> -48880.199 | D21: =+D20 -> 0 | E21: =+E20 -> 0 | F21: =+F20 -> 0 | G21: =+G20 -> 0 | H21: =+H$14/7 -> 48880.199 | I21: =+I$14/7/2 -> 0
B22: 2000 | C22: =-SUM(D22:Y22) -> -48880.199 | D22: =+D21 -> 0 | E22: =+E21 -> 0 | F22: =+F21 -> 0 | G22: =+G21 -> 0 | H22: =+H21 -> 48880.199 | I22: =+I$14/7 -> 0 | J22: =+J$14/7/2 -> 0
B23: 2001 | C23: =-SUM(D23:Y23) -> -48880.199 | D23: =+D$14/7/2 -> 0 | E23: =+E22 -> 0 | F23: =+F22 -> 0 | G23: =+G22 -> 0 | H23: =+H22 -> 48880.199 | I23: =+I22 -> 0 | J23: =+J$14/7 -> 0 | K23: =+K$14/7/2 -> 0
B24: 2002 | C24: =-SUM(D24:Y24) -> -48880.199 | E24: =+E$14/7/2 -> 0 | F24: =+F23 -> 0 | G24: =+G23 -> 0 | H24: =+H23 -> 48880.199 | I24: =+I23 -> 0 | J24: =+J23 -> 0 | K24: =+K$14/7 -> 0 | L24: =+L$14/7/2 -> 0
B25: 2003 | C25: =-SUM(D25:Y25) -> -48880.199 | F25: =+F$14/7/2 -> 0 | G25: =+G24 -> 0 | H25: =+H24 -> 48880.199 | I25: =+I24 -> 0 | J25: =+J24 -> 0 | K25: =+K24 -> 0 | L25: =+L$14/7 -> 0 | M25: =+M$14/7/2 -> 0
B26: 2004 | C26: =-SUM(D26:Y26) -> -48880.199 | G26: =+G$14/7/2 -> 0 | H26: =+H25 -> 48880.199 | I26: =+I25 -> 0 | J26: =+J25 -> 0 | K26: =+K25 -> 0 | L26: =+L25 -> 0 | M26: =+M$14/7 -> 0 | N26: =+N$14/7/2 -> 0
B27: 2005 | C27: =-SUM(D27:Y27) -> -24440.099 | H27: =+H$14/7/2 -> 24440.099 | I27: =+I26 -> 0 | J27: =+J26 -> 0 | K27: =+K26 -> 0 | L27: =+L26 -> 0 | M27: =+M26 -> 0 | N27: =+N$14/7 -> 0 | O27: =+O$14/7/2 -> 0
B28: 2006 | C28: =-SUM(D28:Y28) -> 0 | I28: =+I$14/7/2 -> 0 | J28: =+J27 -> 0 | K28: =+K27 -> 0 | L28: =+L27 -> 0 | M28: =+M27 -> 0 | N28: =+N27 -> 0 | O28: =+O$14/7 -> 0 | P28: =+P$14/7/2 -> 0
B29: 2007 | C29: =-SUM(D29:Y29) -> 0 | J29: =+J$14/7/2 -> 0 | K29: =+K28 -> 0 | L29: =+L28 -> 0 | M29: =+M28 -> 0 | N29: =+N28 -> 0 | O29: =+O28 -> 0 | P29: =+P$14/7 -> 0 | Q29: =+Q$14/7/2 -> 0
B30: 2008 | C30: =-SUM(D30:Y30) -> 0 | K30: =+K$14/7/2 -> 0 | L30: =+L29 -> 0 | M30: =+M29 -> 0 | N30: =+N29 -> 0 | O30: =+O29 -> 0 | P30: =+P29 -> 0 | Q30: =+Q$14/7 -> 0 | R30: =+R$14/7/2 -> 0
B31: 2009 | C31: =-SUM(D31:Y31) -> 0 | L31: =+L$14/7/2 -> 0 | M31: =+M30 -> 0 | N31: =+N30 -> 0 | O31: =+O30 -> 0 | P31: =+P30 -> 0 | Q31: =+Q30 -> 0 | R31: =+R$14/7 -> 0 | S31: =+S$14/7/2 -> 0
A32: To April 30th, 2010 | B32: 2010 | C32: =-SUM(D32:Y32) -> 0 | M32: =+M$14/7/2 -> 0 | N32: =+N31 -> 0 | O32: =+O31 -> 0 | P32: =+P31 -> 0 | Q32: =+Q31 -> 0 | R32: =+R31 -> 0 | S32: =+S$14/7 -> 0 | T32: =+T$14/7/2 -> 0
B33: 2011 | C33: =-SUM(D33:Y33) -> 0 | N33: =+N$14/7/2 -> 0 | O33: =+O32 -> 0 | P33: =+P32 -> 0 | Q33: =+Q32 -> 0 | R33: =+R32 -> 0 | S33: =+S32 -> 0 | T33: =+T$14/7 -> 0 | U33: =+U$14/7/2 -> 0
B34: 2012 | C34: =-SUM(D34:Y34) -> 0 | Q34: =+Q33 -> 0 | R34: =+R33 -> 0 | S34: =+S33 -> 0 | T34: =+T$14/7 -> 0 | U34: =+U$14/7 -> 0 | V34: =+V$14/7/2 -> 0
B35: 2013 | C35: =-SUM(D35:Y35) -> 0
B36: 2014 | C36: =-SUM(D36:Y36) -> 0
B37: 2015 | C37: =-SUM(D37:Y37) -> 0
B38: 2016 | C38: =-SUM(D38:Y38) -> 0
B39: 2017 | C39: =-SUM(D39:AB39) -> 0
B40: 2018 | C40: =-SUM(D40:AB40) -> 0
A42: ST | B42: =SUM(D42:Y42) -> 0 | C42: =SUM(C16:C41) -> -342161.39 | D42: =-SUM(D16:D41)+D14 -> 0 | E42: =-SUM(E16:E41)+E14 -> 0 | F42: =-SUM(F16:F41)+F14 -> 0 | G42: =-SUM(G16:G41)+G14 -> 0 | H42: =-SUM(H16:H41)+H14 -> 0 | I42: =-SUM(I16:I41)+I14 -> 0 | J42: =-SUM(J16:J41)+J14 -> 0 | K42: =-SUM(K16:K41)+K14 -> 0 | ... AB42: =-SUM(AB16:AB41)+AB14 -> 0
A44: Net Book Value | C44: =+C14+C42 -> 0
N47: =SUM(E32:E47) -> 0

Sheet 126
A1: ABS EQUIPMENT LEASING INC.
A2: Equipment List
A3: Source: F 2009 Fixed Asset Summary
R4: Total | T4: Book
A5: Description | B5: Asset # | C5: Serial # | R5: Costs | S5: Depr. | T5: Value
A7: TOSHIBA BF-130B | B7: =+SUMMARY!A28 -> 126 | C7: 510658 | R7: =+C14 -> 1239553.1 | S7: =+-C42 -> 1239553.1 | T7: =+R7-S7 -> 0
A9: HORIZONTAL BORING & MILLING MACHINE
A11: Location: | B11: MISS | C11: A2
A13: Purchased Year Ending | C13: Total | D13: 1994 | E13: 1995 | F13: 1996 | G13: 1997 | H13: 1998 | I13: 1999 | J13: 2000 | K13: 2001 | L13: 2002 | M13: 2003 | N13: 2004 | O13: 2005 | P13: 2006 | Q13: 2007 | R13: 2008 | S13: 2009 | T13: 2010 | U13: 2011 | V13: 2012 | W13: 2013 | X13: 2014 | Y13: 2015 | Z13: 2016 | AA13: 2017 | AB13: 2018
A14: Purchases (Fiscal Yr.) | C14: =SUM(D14:Y14) -> 1239553.1 | I14: 1284553.1 | O14: -45000
A15: =IF(+C14-'Equip Review 032310'!Y18=0,"ok","check") -> ok
A16: Depreciation | B16: 1994 | C16: =-SUM(D16:Y16) -> 0 | D16: =+D$14/7/2 -> 0
B17: 1995 | C17: =-SUM(D17:Y17) -> 0 | D17: =+D$14/7 -> 0 | E17: =+E$14/7/2 -> 0
B18: 1996 | C18: =-SUM(D18:Y18) -> 0 | D18: =+D17 -> 0 | E18: =+E$14/7 -> 0 | F18: =+F$14/7/2 -> 0
B19: 1997 | C19: =-SUM(D19:Y19) -> 0 | D19: =+D18 -> 0 | E19: =+E18 -> 0 | F19: =+F$14/7 -> 0 | G19: =+G$14/7/2 -> 0
B20: 1998 | C20: =-SUM(D20:Y20) -> 0 | D20: =+D19 -> 0 | E20: =+E19 -> 0 | F20: =+F19 -> 0 | G20: =+G$14/7 -> 0 | H20: =+H$14/7/2 -> 0
B21: 1999 | C21: =-SUM(D21:Y21) -> -91753.794 | D21: =+D20 -> 0 | E21: =+E20 -> 0 | F21: =+F20 -> 0 | G21: =+G20 -> 0 | H21: =+H$14/7 -> 0 | I21: =+I$14/7/2 -> 91753.794
B22: 2000 | C22: =-SUM(D22:Y22) -> -183507.59 | D22: =+D21 -> 0 | E22: =+E21 -> 0 | F22: =+F21 -> 0 | G22: =+G21 -> 0 | H22: =+H21 -> 0 | I22: =+I$14/7 -> 183507.59 | J22: =+J$14/7/2 -> 0
B23: 2001 | C23: =-SUM(D23:Y23) -> -183507.59 | D23: =+D$14/7/2 -> 0 | E23: =+E22 -> 0 | F23: =+F22 -> 0 | G23: =+G22 -> 0 | H23: =+H22 -> 0 | I23: =+I22 -> 183507.59 | J23: =+J$14/7 -> 0 | K23: =+K$14/7/2 -> 0
B24: 2002 | C24: =-SUM(D24:Y24) -> -183507.59 | E24: =+E$14/7/2 -> 0 | F24: =+F23 -> 0 | G24: =+G23 -> 0 | H24: =+H23 -> 0 | I24: =+I23 -> 183507.59 | J24: =+J23 -> 0 | K24: =+K$14/7 -> 0 | L24: =+L$14/7/2 -> 0
B25: 2003 | C25: =-SUM(D25:Y25) -> -183507.59 | F25: =+F$14/7/2 -> 0 | G25: =+G24 -> 0 | H25: =+H24 -> 0 | I25: =+I24 -> 183507.59 | J25: =+J24 -> 0 | K25: =+K24 -> 0 | L25: =+L$14/7 -> 0 | M25: =+M$14/7/2 -> 0
B26: 2004 | C26: =-SUM(D26:Y26) -> -183507.59 | G26: =+G$14/7/2 -> 0 | H26: =+H25 -> 0 | I26: =+I25 -> 183507.59 | J26: =+J25 -> 0 | K26: =+K25 -> 0 | L26: =+L25 -> 0 | M26: =+M$14/7 -> 0 | N26: =+N$14/7/2 -> 0
B27: 2005 | C27: =-SUM(D27:Y27) -> -180293.3 | H27: =+H$14/7/2 -> 0 | I27: =+I26 -> 183507.59 | J27: =+J26 -> 0 | K27: =+K26 -> 0 | L27: =+L26 -> 0 | M27: =+M26 -> 0 | N27: =+N$14/7 -> 0 | O27: =+O$14/7/2 -> -3214.2857
B28: 2006 | C28: =-SUM(D28:Y28) -> -85325.222 | I28: =+I$14/7/2 -> 91753.794 | J28: =+J27 -> 0 | K28: =+K27 -> 0 | L28: =+L27 -> 0 | M28: =+M27 -> 0 | N28: =+N27 -> 0 | O28: =+O$14/7 -> -6428.5714 | P28: =+P$14/7/2 -> 0
B29: 2007 | C29: =-SUM(D29:Y29) -> 6428.5714 | J29: =+J$14/7/2 -> 0 | K29: =+K28 -> 0 | L29: =+L28 -> 0 | M29: =+M28 -> 0 | N29: =+N28 -> 0 | O29: =+O28 -> -6428.5714 | P29: =+P$14/7 -> 0 | Q29: =+Q$14/7/2 -> 0
B30: 2008 | C30: =-SUM(D30:Y30) -> 6428.5714 | K30: =+K$14/7/2 -> 0 | L30: =+L29 -> 0 | M30: =+M29 -> 0 | N30: =+N29 -> 0 | O30: =+O29 -> -6428.5714 | P30: =+P29 -> 0 | Q30: =+Q$14/7 -> 0 | R30: =+R$14/7/2 -> 0
B31: 2009 | C31: =-SUM(D31:Y31) -> 6428.5714 | L31: =+L$14/7/2 -> 0 | M31: =+M30 -> 0 | N31: =+N30 -> 0 | O31: =+O30 -> -6428.5714 | P31: =+P30 -> 0 | Q31: =+Q30 -> 0 | R31: =+R$14/7 -> 0 | S31: =+S$14/7/2 -> 0
A32: To April 30th, 2010 | B32: 2010 | C32: =-SUM(D32:Y32) -> 6428.5714 | M32: =+M$14/7/2 -> 0 | N32: =+N31 -> 0 | O32: =+O31 -> -6428.5714 | P32: =+P31 -> 0 | Q32: =+Q31 -> 0 | R32: =+R31 -> 0 | S32: =+S$14/7 -> 0 | T32: =+T$14/7/2 -> 0
B33: 2011 | C33: =-SUM(D33:Y33) -> 6428.5714 | N33: =+N$14/7/2 -> 0 | O33: =+O32 -> -6428.5714 | P33: =+P32 -> 0 | Q33: =+Q32 -> 0 | R33: =+R32 -> 0 | S33: =+S32 -> 0 | T33: =+T$14/7 -> 0 | U33: =+U$14/7/2 -> 0
B34: 2012 | C34: =-SUM(D34:Y34) -> 3214.2857 | O34: =+O33/2 -> -3214.2857 | Q34: =+Q33 -> 0 | R34: =+R33 -> 0 | S34: =+S33 -> 0 | T34: =+T$14/7 -> 0 | U34: =+U$14/7 -> 0 | V34: =+V$14/7/2 -> 0
B35: 2013 | C35: =-SUM(D35:Y35) -> 0
B36: 2014 | C36: =-SUM(D36:Y36) -> 0
B37: 2015 | C37: =-SUM(D37:Y37) -> 0
B38: 2016 | C38: =-SUM(D38:Z38) -> 0
B39: 2017 | C39: =-SUM(D39:AB39) -> 0
B40: 2018 | C40: =-SUM(D40:AB40) -> 0
A42: ST | B42: =SUM(D42:Y42) -> 0 | C42: =SUM(C16:C41) -> -1239553.1 | D42: =-SUM(D16:D41)+D14 -> 0 | E42: =-SUM(E16:E41)+E14 -> 0 | F42: =-SUM(F16:F41)+F14 -> 0 | G42: =-SUM(G16:G41)+G14 -> 0 | H42: =-SUM(H16:H41)+H14 -> 0 | I42: =-SUM(I16:I41)+I14 -> 0 | J42: =-SUM(J16:J41)+J14 -> 0 | K42: =-SUM(K16:K41)+K14 -> 0 | ... AB42: =-SUM(AB16:AB41)+AB14 -> 0
A44: Net Book Value | C44: =+C14+C42 -> 0
A46: CHECK!!!
N47: =SUM(E32:E47) -> 0

Sheet 127
A1: ABS EQUIPMENT LEASING INC.
A2: Equipment List
A3: Source: F 2009 Fixed Asset Summary
R4: Total | T4: Book
A5: Description | B5: Asset # | C5: Serial # | R5: Costs | S5: Depr. | T5: Value
A6: TOYODA HMC | B6: 127 | C6: 8932
R7: =+C14 -> 159378.26 | S7: =+-C42 -> 159378.26 | T7: =+R7-S7 -> 0 | U7: SOLD
A11: Location: | B11: MISSP1 | C11: B
A13: Purchased Year Ending | C13: Total | D13: 1994 | E13: 1995 | F13: 1996 | G13: 1997 | H13: 1998 | I13: 1999 | J13: 2000 | K13: 2001 | L13: 2002 | M13: 2003 | N13: 2004 | O13: 2005 | P13: 2006 | Q13: 2007 | R13: 2008 | S13: 2009 | T13: 2010 | U13: 2011 | V13: 2012 | W13: 2013 | X13: 2014 | Y13: 2015 | Z13: 2016 | AA13: 2017 | AB13: 2018
A14: Purchases (Fiscal Yr.) | C14: =SUM(D14:Y14) -> 159378.26 | N14: 151632.89 | O14: 7745.37
A15: =IF(+C14-'Equip Review 032310'!Y29=0,"ok","check") -> check
A16: Depreciation | B16: 1994 | C16: =-SUM(D16:Y16) -> 0 | D16: =+D$14/7/2 -> 0
B17: 1995 | C17: =-SUM(D17:Y17) -> 0 | D17: =+D$14/7 -> 0 | E17: =+E$14/7/2 -> 0
B18: 1996 | C18: =-SUM(D18:Y18) -> 0 | D18: =+D17 -> 0 | E18: =+E$14/7 -> 0 | F18: =+F$14/7/2 -> 0
B19: 1997 | C19: =-SUM(D19:Y19) -> 0 | D19: =+D18 -> 0 | E19: =+E18 -> 0 | F19: =+F$14/7 -> 0 | G19: =+G$14/7/2 -> 0
B20: 1998 | C20: =-SUM(D20:Y20) -> 0 | D20: =+D19 -> 0 | E20: =+E19 -> 0 | F20: =+F19 -> 0 | G20: =+G$14/7 -> 0 | H20: =+H$14/7/2 -> 0
B21: 1999 | C21: =-SUM(D21:Y21) -> 0 | D21: =+D20 -> 0 | E21: =+E20 -> 0 | F21: =+F20 -> 0 | G21: =+G20 -> 0 | H21: =+H$14/7 -> 0 | I21: =+I$14/7/2 -> 0
B22: 2000 | C22: =-SUM(D22:Y22) -> 0 | D22: =+D21 -> 0 | E22: =+E21 -> 0 | F22: =+F21 -> 0 | G22: =+G21 -> 0 | H22: =+H21 -> 0 | I22: =+I$14/7 -> 0 | J22: =+J$14/7/2 -> 0
B23: 2001 | C23: =-SUM(D23:Y23) -> 0 | D23: =+D$14/7/2 -> 0 | E23: =+E22 -> 0 | F23: =+F22 -> 0 | G23: =+G22 -> 0 | H23: =+H22 -> 0 | I23: =+I22 -> 0 | J23: =+J$14/7 -> 0 | K23: =+K$14/7/2 -> 0
B24: 2002 | C24: =-SUM(D24:Y24) -> 0 | E24: =+E$14/7/2 -> 0 | F24: =+F23 -> 0 | G24: =+G23 -> 0 | H24: =+H23 -> 0 | I24: =+I23 -> 0 | J24: =+J23 -> 0 | K24: =+K$14/7 -> 0 | L24: =+L$14/7/2 -> 0
B25: 2003 | C25: =-SUM(D25:Y25) -> 0 | F25: =+F$14/7/2 -> 0 | G25: =+G24 -> 0 | H25: =+H24 -> 0 | I25: =+I24 -> 0 | J25: =+J24 -> 0 | K25: =+K24 -> 0 | L25: =+L$14/7 -> 0 | M25: =+M$14/7/2 -> 0
B26: 2004 | C26: =-SUM(D26:Y26) -> -10830.921 | G26: =+G$14/7/2 -> 0 | H26: =+H25 -> 0 | I26: =+I25 -> 0 | J26: =+J25 -> 0 | K26: =+K25 -> 0 | L26: =+L25 -> 0 | M26: =+M$14/7 -> 0 | N26: =+N$14/7/2 -> 10830.921
B27: 2005 | C27: =-SUM(D27:Y27) -> -22215.082 | H27: =+H$14/7/2 -> 0 | I27: =+I26 -> 0 | J27: =+J26 -> 0 | K27: =+K26 -> 0 | L27: =+L26 -> 0 | M27: =+M26 -> 0 | N27: =+N$14/7 -> 21661.841 | O27: =+O$14/7/2 -> 553.24071
B28: 2006 | C28: =-SUM(D28:Y28) -> -22768.323 | I28: =+I$14/7/2 -> 0 | J28: =+J27 -> 0 | K28: =+K27 -> 0 | L28: =+L27 -> 0 | M28: =+M27 -> 0 | N28: =+N27 -> 21661.841 | O28: =+O$14/7 -> 1106.4814 | P28: =+P$14/7/2 -> 0
B29: 2007 | C29: =-SUM(D29:Y29) -> -22768.323 | J29: =+J$14/7/2 -> 0 | K29: =+K28 -> 0 | L29: =+L28 -> 0 | M29: =+M28 -> 0 | N29: =+N28 -> 21661.841 | O29: =+O28 -> 1106.4814 | P29: =+P$14/7 -> 0 | Q29: =+Q$14/7/2 -> 0
B30: 2008 | C30: =-SUM(D30:Y30) -> -22768.323 | K30: =+K$14/7/2 -> 0 | L30: =+L29 -> 0 | M30: =+M29 -> 0 | N30: =+N29 -> 21661.841 | O30: =+O29 -> 1106.4814 | P30: =+P29 -> 0 | Q30: =+Q$14/7 -> 0 | R30: =+R$14/7/2 -> 0
B31: 2009 | C31: =-SUM(D31:Y31) -> -22768.323 | L31: =+L$14/7/2 -> 0 | M31: =+M30 -> 0 | N31: =+N30 -> 21661.841 | O31: =+O30 -> 1106.4814 | P31: =+P30 -> 0 | Q31: =+Q30 -> 0 | R31: =+R$14/7 -> 0 | S31: =+S$14/7/2 -> 0
A32: To April 30th, 2010 | B32: 2010 | C32: =-SUM(D32:Y32) -> -22768.323 | M32: =+M$14/7/2 -> 0 | N32: =+N31 -> 21661.841 | O32: =+O31 -> 1106.4814 | P32: =+P31 -> 0 | Q32: =+Q31 -> 0 | R32: =+R31 -> 0 | S32: =+S$14/7 -> 0 | T32: =+T$14/7/2 -> 0
B33: 2011 | C33: =-SUM(D33:Y33) -> -11937.402 | N33: =+N$14/7/2 -> 10830.921 | O33: =+O32 -> 1106.4814 | P33: =+P32 -> 0 | Q33: =+Q32 -> 0 | R33: =+R32 -> 0 | S33: =+S32 -> 0 | T33: =+T$14/7 -> 0 | U33: =+U$14/7/2 -> 0
B34: 2012 | C34: =-SUM(D34:Y34) -> -553.24071 | O34: =O14/7/2 -> 553.24071 | Q34: =+Q33 -> 0 | R34: =+R33 -> 0 | S34: =+S33 -> 0 | T34: =+T$14/7 -> 0 | U34: =+U$14/7 -> 0 | V34: =+V$14/7/2 -> 0
B35: 2013 | C35: =-SUM(D35:Y35) -> 0
B36: 2014 | C36: =-SUM(D36:Y36) -> 0
B37: 2015 | C37: =-SUM(D37:Y37) -> 0
B38: 2016 | C38: =-SUM(D38:Y38) -> 0
B39: 2017 | C39: =-SUM(D39:AB39) -> 0
B40: 2018 | C40: =-SUM(D40:AB40) -> 0
A42: ST | B42: =SUM(D42:Y42) -> 0 | C42: =SUM(C16:C41) -> -159378.26 | D42: =-SUM(D16:D41)+D14 -> 0 | E42: =-SUM(E16:E41)+E14 -> 0 | F42: =-SUM(F16:F41)+F14 -> 0 | G42: =-SUM(G16:G41)+G14 -> 0 | H42: =-SUM(H16:H41)+H14 -> 0 | I42: =-SUM(I16:I41)+I14 -> 0 | J42: =-SUM(J16:J41)+J14 -> 0 | K42: =-SUM(K16:K41)+K14 -> 0 | ... AB42: =-SUM(AB16:AB41)+AB14 -> 0
A44: Net Book Value | C44: =+C14+C42 -> 0
N47: =SUM(E32:E47) -> 0

Sheet 128
A1: ABS EQUIPMENT LEASING INC.
A2: Select Equipment List
A3: Source: F 2009 Fixed Asset Summary
R4: Total | T4: Book
A5: Description | B5: Asset # | C5: Serial # | R5: Costs | S5: Depr. | T5: Value
A6: TOSHIBA MPC 3680B | B6: 128
R7: =+C14 -> 2553028.6 | S7: =+-C42 -> 2553028.6 | T7: =+R7-S7 -> 0
A11: Location: | B11: MISS | C11: A2
A13: Purchased Year Ending | C13: Total | D13: 1994 | E13: 1995 | F13: 1996 | G13: 1997 | H13: 1998 | I13: 1999 | J13: 2000 | K13: 2001 | L13: 2002 | M13: 2003 | N13: 2004 | O13: 2005 | P13: 2006 | Q13: 2007 | R13: 2008 | S13: 2009 | T13: 2010 | U13: 2011 | V13: 2012 | W13: 2013 | X13: 2014 | Y13: 2015 | Z13: 2016 | AA13: 2017 | AB13: 2018
A14: Purchases (Fiscal Yr.) | C14: =SUM(D14:Y14) -> 2553028.6 | K14: 2553028.6
A15: =IF(+C14-'Equip Review 032310'!Y29=0,"ok","check") -> check
A16: Depreciation | B16: 1994 | C16: =-SUM(D16:Y16) -> 0 | D16: =+D$14/7/2 -> 0
B17: 1995 | C17: =-SUM(D17:Y17) -> 0 | D17: =+D$14/7 -> 0 | E17: =+E$14/7/2 -> 0
B18: 1996 | C18: =-SUM(D18:Y18) -> 0 | D18: =+D17 -> 0 | E18: =+E$14/7 -> 0 | F18: =+F$14/7/2 -> 0
B19: 1997 | C19: =-SUM(D19:Y19) -> 0 | D19: =+D18 -> 0 | E19: =+E18 -> 0 | F19: =+F$14/7 -> 0 | G19: =+G$14/7/2 -> 0
B20: 1998 | C20: =-SUM(D20:Y20) -> 0 | D20: =+D19 -> 0 | E20: =+E19 -> 0 | F20: =+F19 -> 0 | G20: =+G$14/7 -> 0 | H20: =+H$14/7/2 -> 0
B21: 1999 | C21: =-SUM(D21:Y21) -> 0 | D21: =+D20 -> 0 | E21: =+E20 -> 0 | F21: =+F20 -> 0 | G21: =+G20 -> 0 | H21: =+H$14/7 -> 0 | I21: =+I$14/7/2 -> 0
B22: 2000 | C22: =-SUM(D22:Y22) -> 0 | D22: =+D21 -> 0 | E22: =+E21 -> 0 | F22: =+F21 -> 0 | G22: =+G21 -> 0 | H22: =+H21 -> 0 | I22: =+I$14/7 -> 0 | J22: =+J$14/7/2 -> 0
B23: 2001 | C23: =-SUM(D23:Y23) -> -182359.18 | D23: =+D$14/7/2 -> 0 | E23: =+E22 -> 0 | F23: =+F22 -> 0 | G23: =+G22 -> 0 | H23: =+H22 -> 0 | I23: =+I22 -> 0 | J23: =+J$14/7 -> 0 | K23: =+K$14/7/2 -> 182359.18
B24: 2002 | C24: =-SUM(D24:Y24) -> -364718.37 | E24: =+E$14/7/2 -> 0 | F24: =+F23 -> 0 | G24: =+G23 -> 0 | H24: =+H23 -> 0 | I24: =+I23 -> 0 | J24: =+J23 -> 0 | K24: =+K$14/7 -> 364718.37 | L24: =+L$14/7/2 -> 0
B25: 2003 | C25: =-SUM(D25:Y25) -> -364718.37 | F25: =+F$14/7/2 -> 0 | G25: =+G24 -> 0 | H25: =+H24 -> 0 | I25: =+I24 -> 0 | J25: =+J24 -> 0 | K25: =+K24 -> 364718.37 | L25: =+L$14/7 -> 0 | M25: =+M$14/7/2 -> 0
B26: 2004 | C26: =-SUM(D26:Y26) -> -364718.37 | G26: =+G$14/7/2 -> 0 | H26: =+H25 -> 0 | I26: =+I25 -> 0 | J26: =+J25 -> 0 | K26: =+K25 -> 364718.37 | L26: =+L25 -> 0 | M26: =+M$14/7 -> 0 | N26: =+N$14/7/2 -> 0
B27: 2005 | C27: =-SUM(D27:Y27) -> -364718.37 | H27: =+H$14/7/2 -> 0 | I27: =+I26 -> 0 | J27: =+J26 -> 0 | K27: =+K26 -> 364718.37 | L27: =+L26 -> 0 | M27: =+M26 -> 0 | N27: =+N$14/7 -> 0 | O27: =+O$14/7/2 -> 0
B28: 2006 | C28: =-SUM(D28:Y28) -> -364718.37 | I28: =+I$14/7/2 -> 0 | J28: =+J27 -> 0 | K28: =+K27 -> 364718.37 | L28: =+L27 -> 0 | M28: =+M27 -> 0 | N28: =+N27 -> 0 | O28: =+O$14/7 -> 0 | P28: =+P$14/7/2 -> 0
B29: 2007 | C29: =-SUM(D29:Y29) -> -364718.37 | J29: =+J$14/7/2 -> 0 | K29: =+K28 -> 364718.37 | L29: =+L28 -> 0 | M29: =+M28 -> 0 | N29: =+N28 -> 0 | O29: =+O28 -> 0 | P29: =+P$14/7 -> 0 | Q29: =+Q$14/7/2 -> 0
B30: 2008 | C30: =-SUM(D30:Y30) -> -182359.18 | K30: =+K$14/7/2 -> 182359.18 | L30: =+L29 -> 0 | M30: =+M29 -> 0 | N30: =+N29 -> 0 | O30: =+O29 -> 0 | P30: =+P29 -> 0 | Q30: =+Q$14/7 -> 0 | R30: =+R$14/7/2 -> 0
B31: 2009 | C31: =-SUM(D31:Y31) -> 0 | L31: =+L$14/7/2 -> 0 | M31: =+M30 -> 0 | N31: =+N30 -> 0 | O31: =+O30 -> 0 | P31: =+P30 -> 0 | Q31: =+Q30 -> 0 | R31: =+R$14/7 -> 0 | S31: =+S$14/7/2 -> 0
A32: To April 30th, 2010 | B32: 2010 | C32: =-SUM(D32:Y32) -> 0 | M32: =+M$14/7/2 -> 0 | N32: =+N31 -> 0 | O32: =+O31 -> 0 | P32: =+P31 -> 0 | Q32: =+Q31 -> 0 | R32: =+R31 -> 0 | S32: =+S$14/7 -> 0 | T32: =+T$14/7/2 -> 0
B33: 2011 | C33: =-SUM(D33:Y33) -> 0 | N33: =+N$14/7/2 -> 0 | O33: =+O32 -> 0 | P33: =+P32 -> 0 | Q33: =+Q32 -> 0 | R33: =+R32 -> 0 | S33: =+S32 -> 0 | T33: =+T$14/7 -> 0 | U33: =+U$14/7/2 -> 0
B34: 2012 | C34: =-SUM(D34:Y34) -> 0 | Q34: =+Q33 -> 0 | R34: =+R33 -> 0 | S34: =+S33 -> 0 | T34: =+T$14/7 -> 0 | U34: =+U$14/7 -> 0 | V34: =+V$14/7/2 -> 0
B35: 2013 | C35: =-SUM(D35:Y35) -> 0
B36: 2014 | C36: =-SUM(D36:Y36) -> 0
B37: 2015 | C37: =-SUM(D37:Y37) -> 0
B38: 2016 | C38: =-SUM(D38:Y38) -> 0
B39: 2017 | C39: =-SUM(D39:AB39) -> 0
B40: 2018 | C40: =-SUM(D40:AB40) -> 0
A42: ST | B42: =SUM(D42:Y42) -> 0 | C42: =SUM(C16:C41) -> -2553028.6 | D42: =-SUM(D16:D41)+D14 -> 0 | E42: =-SUM(E16:E41)+E14 -> 0 | F42: =-SUM(F16:F41)+F14 -> 0 | G42: =-SUM(G16:G41)+G14 -> 0 | H42: =-SUM(H16:H41)+H14 -> 0 | I42: =-SUM(I16:I41)+I14 -> 0 | J42: =-SUM(J16:J41)+J14 -> 0 | K42: =-SUM(K16:K41)+K14 -> 0 | ... AB42: =-SUM(AB16:AB41)+AB14 -> 0
A44: Net Book Value | C44: =+C14+C42 -> 0
N47: =SUM(E32:E47) -> 0

Sheet 133
A1: ABS EQUIPMENT LEASING INC.
A2: Equipment List
A3: Source: F 2009 Fixed Asset Summary
R4: Total | T4: Book
A5: Description | B5: Asset # | C5: Serial # | R5: Costs | S5: Depr. | T5: Value
A6: =+SUMMARY!B30 -> SAFOP LATHE | B6: =+SUMMARY!A30 -> 133 | C6: =+SUMMARY!D30 -> 3281
A7: =+SUMMARY!C30 -> HT-850/CNC | R7: =+C14 -> 904845.26 | S7: =+-C46 -> 904845.26 | T7: =+R7-S7 -> 0
A8: Cahmac Int'l
A11: Location: | B11: =+SUMMARY!F30 -> MISS | C11: B4
A13: Purchased Year Ending | C13: Total | D13: 1994 | E13: 1995 | F13: 1996 | G13: 1997 | H13: 1998 | I13: 1999 | J13: 2000 | K13: 2001 | L13: 2002 | M13: 2003 | N13: 2004 | O13: 2005 | P13: 2006 | Q13: 2007 | R13: 2008 | S13: 2009 | T13: 2010 | U13: 2011 | V13: 2012 | W13: 2013 | X13: 2014 | Y13: 2015 | Z13: 2016 | AA13: 2017 | AB13: 2018 | AC13: 2019
A14: Purchases (Fiscal Yr.) | C14: =SUM(D14:Y14) -> 904845.26 | I14: 885890.26 | Y14: 18955
A15: =IF(+C14-'Equip Review 032310'!Y29=0,"ok","check") -> check
A16: Depreciation | B16: 1994 | C16: =-SUM(D16:Y16) -> 0 | D16: =+D$14/7/2 -> 0
B17: 1995 | C17: =-SUM(D17:Y17) -> 0 | D17: =+D$14/7 -> 0 | E17: =+E$14/7/2 -> 0
B18: 1996 | C18: =-SUM(D18:Y18) -> 0 | D18: =+D17 -> 0 | E18: =+E$14/7 -> 0 | F18: =+F$14/7/2 -> 0
B19: 1997 | C19: =-SUM(D19:Y19) -> 0 | D19: =+D18 -> 0 | E19: =+E18 -> 0 | F19: =+F$14/7 -> 0 | G19: =+G$14/7/2 -> 0
B20: 1998 | C20: =-SUM(D20:Y20) -> 0 | D20: =+D19 -> 0 | E20: =+E19 -> 0 | F20: =+F19 -> 0 | G20: =+G$14/7 -> 0 | H20: =+H$14/7/2 -> 0
B21: 1999 | C21: =-SUM(D21:Y21) -> -63277.876 | D21: =+D20 -> 0 | E21: =+E20 -> 0 | F21: =+F20 -> 0 | G21: =+G20 -> 0 | H21: =+H$14/7 -> 0 | I21: =+I$14/7/2 -> 63277.876
B22: 2000 | C22: =-SUM(D22:Y22) -> -126555.75 | D22: =+D21 -> 0 | E22: =+E21 -> 0 | F22: =+F21 -> 0 | G22: =+G21 -> 0 | H22: =+H21 -> 0 | I22: =+I$14/7 -> 126555.75 | J22: =+J$14/7/2 -> 0
B23: 2001 | C23: =-SUM(D23:Y23) -> -126555.75 | D23: =+D$14/7/2 -> 0 | E23: =+E22 -> 0 | F23: =+F22 -> 0 | G23: =+G22 -> 0 | H23: =+H22 -> 0 | I23: =+I22 -> 126555.75 | J23: =+J$14/7 -> 0 | K23: =+K$14/7/2 -> 0
B24: 2002 | C24: =-SUM(D24:Y24) -> -126555.75 | E24: =+E$14/7/2 -> 0 | F24: =+F23 -> 0 | G24: =+G23 -> 0 | H24: =+H23 -> 0 | I24: =+I23 -> 126555.75 | J24: =+J23 -> 0 | K24: =+K$14/7 -> 0 | L24: =+L$14/7/2 -> 0
B25: 2003 | C25: =-SUM(D25:Y25) -> -126555.75 | F25: =+F$14/7/2 -> 0 | G25: =+G24 -> 0 | H25: =+H24 -> 0 | I25: =+I24 -> 126555.75 | J25: =+J24 -> 0 | K25: =+K24 -> 0 | L25: =+L$14/7 -> 0 | M25: =+M$14/7/2 -> 0
B26: 2004 | C26: =-SUM(D26:Y26) -> -126555.75 | G26: =+G$14/7/2 -> 0 | H26: =+H25 -> 0 | I26: =+I25 -> 126555.75 | J26: =+J25 -> 0 | K26: =+K25 -> 0 | L26: =+L25 -> 0 | M26: =+M$14/7 -> 0 | N26: =+N$14/7/2 -> 0
B27: 2005 | C27: =-SUM(D27:Y27) -> -126555.75 | H27: =+H$14/7/2 -> 0 | I27: =+I26 -> 126555.75 | J27: =+J26 -> 0 | K27: =+K26 -> 0 | L27: =+L26 -> 0 | M27: =+M26 -> 0 | N27: =+N$14/7 -> 0 | O27: =+O$14/7/2 -> 0
B28: 2006 | C28: =-SUM(D28:Y28) -> -63277.876 | I28: =+I$14/7/2 -> 63277.876 | J28: =+J27 -> 0 | K28: =+K27 -> 0 | L28: =+L27 -> 0 | M28: =+M27 -> 0 | N28: =+N27 -> 0 | O28: =+O$14/7 -> 0 | P28: =+P$14/7/2 -> 0
B29: 2007 | C29: =-SUM(D29:Y29) -> 0 | J29: =+J$14/7/2 -> 0 | K29: =+K28 -> 0 | L29: =+L28 -> 0 | M29: =+M28 -> 0 | N29: =+N28 -> 0 | O29: =+O28 -> 0 | P29: =+P$14/7 -> 0 | Q29: =+Q$14/7/2 -> 0
B30: 2008 | C30: =-SUM(D30:Y30) -> 0 | K30: =+K$14/7/2 -> 0 | L30: =+L29 -> 0 | M30: =+M29 -> 0 | N30: =+N29 -> 0 | O30: =+O29 -> 0 | P30: =+P29 -> 0 | Q30: =+Q$14/7 -> 0 | R30: =+R$14/7/2 -> 0
B31: 2009 | C31: =-SUM(D31:Y31) -> 0 | L31: =+L$14/7/2 -> 0 | M31: =+M30 -> 0 | N31: =+N30 -> 0 | O31: =+O30 -> 0 | P31: =+P30 -> 0 | Q31: =+Q30 -> 0 | R31: =+R$14/7 -> 0 | S31: =+S$14/7/2 -> 0
B32: 2010 | C32: =-SUM(D32:Y32) -> 0 | M32: =+M$14/7/2 -> 0 | N32: =+N31 -> 0 | O32: =+O31 -> 0 | P32: =+P31 -> 0 | Q32: =+Q31 -> 0 | R32: =+R31 -> 0 | S32: =+S$14/7 -> 0 | T32: =+T$14/7/2 -> 0
B33: 2011 | C33: =-SUM(D33:Y33) -> 0 | N33: =+N$14/7/2 -> 0 | O33: =+O32 -> 0 | P33: =+P32 -> 0 | Q33: =+Q32 -> 0 | R33: =+R32 -> 0 | S33: =+S32 -> 0 | T33: =+T$14/7 -> 0 | U33: =+U$14/7/2 -> 0
B34: 2012 | C34: =-SUM(D34:Y34) -> 0 | Q34: =+Q33 -> 0 | R34: =+R33 -> 0 | S34: =+S33 -> 0 | T34: =+T$14/7 -> 0 | U34: =+U$14/7 -> 0 | V34: =+V$14/7/2 -> 0
B35: 2013 | C35: =-SUM(D35:Y35) -> 0 | R35: =+R34 -> 0 | S35: =+S34 -> 0 | T35: =+T$14/7 -> 0 | U35: =+U$14/7 -> 0 | V35: =+V$14/7/2 -> 0
B36: 2014 | C36: =-SUM(D36:Y36) -> 0 | R36: =+R35 -> 0 | S36: =+S35 -> 0 | T36: =+T$14/7 -> 0 | U36: =+U$14/7 -> 0 | V36: =+V$14/7/2 -> 0
B37: 2015 | C37: =-SUM(D37:Y37) -> -1353.9286 | R37: =+R36 -> 0 | S37: =+S36 -> 0 | T37: =+T$14/7 -> 0 | U37: =+U$14/7 -> 0 | V37: =+V$14/7/2 -> 0 | Y37: =+$Y$14/7/2 -> 1353.9286
B38: 2016 | C38: =-SUM(D38:Y38) -> -2707.8571 | Y38: =+$Y$14/7 -> 2707.8571
B39: 2017 | C39: =-SUM(D39:AA39) -> -2707.8571 | Y39: =+$Y$14/7 -> 2707.8571
B40: 2018 | C40: =-SUM(D40:AB40) -> -2707.8571 | Y40: =+$Y$14/7 -> 2707.8571
B41: 2019 | C41: =-SUM(D41:AB41) -> -2707.8571 | Y41: =+$Y$14/7 -> 2707.8571
B42: 2020 | C42: =-SUM(D42:AB42) -> -2707.8571 | Y42: =+$Y$14/7 -> 2707.8571
B43: 2021 | C43: =-SUM(D43:AB43) -> -2707.8571 | Y43: =+$Y$14/7 -> 2707.8571
B44: 2022 | C44: =-SUM(D44:AB44) -> -1353.9286 | Y44: =+$Y$14/7/2 -> 1353.9286
